Workbook

Sheet GDP data
A1: country | B1: 44927 | C1: 44958 | D1: 44986 | E1: 45017 | F1: 45047 | G1: 45078 | H1: 45108 | I1: 45139 | J1: 45170 | K1: 45200 | L1: 45231 | M1: 45261 | N1: 45292 | O1: 45323 | P1: 45352 | Q1: 45383 | R1: 45413 | S1: 45444 | T1: 45474 | U1: 45505 | V1: 45536 | W1: 45566 | X1: 45597 | Y1: 45627 | Z1: 45658 | AA1: 45689 | AB1: 45717 | AC1: 45748 | AD1: 45778 | AE1: 45809 | AF1: 45839 | AG1: 45870 | AH1: 45901 | AI1: 45931 | AJ1: 45962 | AK1: 45992 | AL1: 46023 | AM1: 46054 | AN1: 46082 | AO1: 46113 | AP1: 46143 | AQ1: 46174 | AR1: 46204 | AS1: 46235 | AT1: 46266 | AU1: 46296 | AV1: 46327 | AW1: 46357
A2: Australia | B2: 2.8 | C2: 2.8 | D2: 2.8 | E2: 2.2 | F2: 2.2 | G2: 2.2 | H2: 2.2 | I2: 2.2 | J2: 2.2 | K2: 1.3 | L2: 1.3 | M2: 1.3 | N2: 1.1 | O2: 1.1 | P2: 1.1 | Q2: 0.9 | R2: 0.9 | S2: 0.9 | T2: 0.8 | U2: 0.8 | V2: 0.8 | W2: 1.2 | X2: 1.2 | Y2: 1.2 | Z2: 1.3 | AA2: 1.3 | AB2: 1.3 | AC2: 1.9 | AD2: 1.9 | AE2: 1.9 | AF2: 2.1 | AG2: 2.1 | AH2: 2.1 | AI2: 2.6 | AJ2: 2.6 | AK2: 2.6 | AL2: 2.5 | AM2: 2.5 | AN2: 2.5 | AO2: 2.1 | AP2: 2.1 | AQ2: 2.1 | AR2: 2.1 | AS2: 2.1 | AT2: 2.1 | AU2: 1.5 | AV2: 1.5 | AW2: 1.5 | AY2: Valeur | AZ2: rating
A3: Canada | B3: 3.1 | C3: 3.1 | D3: 3.1 | E3: 2.1 | F3: 2.1 | G3: 2.1 | H3: 1.3 | I3: 1.3 | J3: 1.3 | K3: 1.3 | L3: 1.3 | M3: 1.3 | N3: 1 | O3: 1 | P3: 1 | Q3: 1.7 | R3: 1.7 | S3: 1.7 | T3: 2.4 | U3: 2.4 | V3: 2.4 | W3: 3.1 | X3: 3.1 | Y3: 3.1 | Z3: 3.1 | AA3: 3.1 | AB3: 3.1 | AC3: 2 | AD3: 2 | AE3: 2 | AF3: 1.7 | AG3: 1.7 | AH3: 1.7 | AI3: 0.7 | AJ3: 0.7 | AK3: 0.7 | AL3: 0.1 | AM3: 0.1 | AN3: 0.1 | AO3: 1.1 | AP3: 1.1 | AQ3: 1.1 | AR3: 0.9 | AS3: 0.9 | AT3: 0.9 | AU3: 1.5 | AV3: 1.5 | AW3: 1.5 | AY3: 5 | AZ3: 10
A4: Japan | B4: 2.1 | C4: 2.1 | D4: 2.1 | E4: 1.2 | F4: 1.2 | G4: 1.2 | H4: 0.2 | I4: 0.2 | J4: 0.2 | K4: 0.1 | L4: 0.1 | M4: 0.1 | N4: -0.9 | O4: -0.9 | P4: -0.9 | Q4: -0.9 | R4: -0.9 | S4: -0.9 | T4: 1.1 | U4: 1.1 | V4: 1.1 | W4: 0.9 | X4: 0.9 | Y4: 0.9 | Z4: 1.6 | AA4: 1.6 | AB4: 1.6 | AC4: 2.1 | AD4: 2.1 | AE4: 2.1 | AF4: 0.6 | AG4: 0.6 | AH4: 0.6 | AI4: 0.4 | AJ4: 0.4 | AK4: 0.4 | AL4: 0.5 | AM4: 0.5 | AN4: 0.5 | AO4: 0.7 | AP4: 0.7 | AQ4: 0.7 | AR4: 0.9 | AS4: 0.9 | AT4: 0.9 | AU4: 1.1 | AV4: 1.1 | AW4: 1.1 | AY4: 4 | AZ4: 8
A5: New Zealand | B5: 3.1 | C5: 3.1 | D5: 3.1 | E5: 3 | F5: 3 | G5: 3 | H5: 1.2 | I5: 1.2 | J5: 1.2 | K5: 1.4 | L5: 1.4 | M5: 1.4 | N5: 1.6 | O5: 1.6 | P5: 1.6 | Q5: 0.1 | R5: 0.1 | S5: 0.1 | T5: -1.2 | U5: -1.2 | V5: -1.2 | W5: -1.6 | X5: -1.6 | Y5: -1.6 | Z5: -0.7 | AA5: -0.7 | AB5: -0.7 | AC5: -0.9 | AD5: -0.9 | AE5: -0.9 | AF5: 1.2 | AG5: 1.2 | AH5: 1.2 | AI5: 1.6 | AJ5: 1.6 | AK5: 1.6 | AL5: 1.7 | AM5: 1.7 | AN5: 1.7 | AO5: 2.6 | AP5: 2.6 | AQ5: 2.6 | AR5: 2 | AS5: 2 | AT5: 2 | AU5: 2.1 | AV5: 2.1 | AW5: 2.1 | AY5: 3 | AZ5: 6
A6: Switzerland | B6: 2 | C6: 2 | D6: 2 | E6: 1 | F6: 1 | G6: 1 | H6: 0.8 | I6: 0.8 | J6: 0.8 | K6: 1.1 | L6: 1.1 | M6: 1.1 | N6: 0.1 | O6: 0.1 | P6: 0.1 | Q6: 1.6 | R6: 1.6 | S6: 1.6 | T6: 1.6 | U6: 1.6 | V6: 1.6 | W6: 1.3 | X6: 1.3 | Y6: 1.3 | Z6: 2.6 | AA6: 2.6 | AB6: 2.6 | AC6: 1.4 | AD6: 1.4 | AE6: 1.4 | AF6: 0.7 | AG6: 0.7 | AH6: 0.7 | AI6: 1.1 | AJ6: 1.1 | AK6: 1.1 | AL6: 0.4 | AM6: 0.4 | AN6: 0.4 | AO6: 2.3 | AP6: 2.3 | AQ6: 2.3 | AR6: 1.8 | AS6: 1.8 | AT6: 1.8 | AU6: 1.7 | AV6: 1.7 | AW6: 1.7 | AY6: 2 | AZ6: 4
A7: United Kingdom | B7: 1 | C7: 1 | D7: 1 | E7: 0.5 | F7: 0.5 | G7: 0.5 | H7: 0.1 | I7: 0.1 | J7: 0.1 | K7: -0.5 | L7: -0.5 | M7: -0.5 | N7: 0.2 | O7: 0.2 | P7: 0.2 | Q7: 0.8 | R7: 0.8 | S7: 0.8 | T7: 1.2 | U7: 1.2 | V7: 1.2 | W7: 2 | X7: 2 | Y7: 2 | Z7: 1.8 | AA7: 1.8 | AB7: 1.8 | AC7: 1.3 | AD7: 1.3 | AE7: 1.3 | AF7: 1.2 | AG7: 1.2 | AH7: 1.2 | AI7: 0.9 | AJ7: 0.9 | AK7: 0.9 | AL7: 0.9 | AM7: 0.9 | AN7: 0.9 | AO7: 1.2 | AP7: 1.2 | AQ7: 1.2 | AR7: 1.7 | AS7: 1.7 | AT7: 1.7 | AU7: 1.4 | AV7: 1.4 | AW7: 1.4 | AY7: 1 | AZ7: 2
A8: United States | B8: 2.3 | C8: 2.3 | D8: 2.3 | E8: 2.8 | F8: 2.8 | G8: 2.8 | H8: 3.2 | I8: 3.2 | J8: 3.2 | K8: 3.4 | L8: 3.4 | M8: 3.4 | N8: 2.9 | O8: 2.9 | P8: 2.9 | Q8: 3.1 | R8: 3.1 | S8: 3.1 | T8: 2.8 | U8: 2.8 | V8: 2.8 | W8: 2.4 | X8: 2.4 | Y8: 2.4 | Z8: 2 | AA8: 2 | AB8: 2 | AC8: 2.1 | AD8: 2.1 | AE8: 2.1 | AF8: 2.3 | AG8: 2.3 | AH8: 2.3 | AI8: 2 | AJ8: 2 | AK8: 2 | AL8: 2.7 | AM8: 2.7 | AN8: 2.7 | AO8: 2.1 | AP8: 2.1 | AQ8: 2.1 | AR8: 1.8 | AS8: 1.8 | AT8: 1.8 | AU8: 1.6 | AV8: 1.6 | AW8: 1.6 | AY8: 0 | AZ8: 0
A9: Euro area (19 countries) | B9: 1.2 | C9: 1.2 | D9: 1.2 | E9: 0.5 | F9: 0.5 | G9: 0.5 | H9: 0.1 | I9: 0.1 | J9: 0.1 | K9: 0.2 | L9: 0.2 | M9: 0.2 | N9: 0.8 | O9: 0.8 | P9: 0.8 | Q9: 0.9 | R9: 0.9 | S9: 0.9 | T9: 1.2 | U9: 1.2 | V9: 1.2 | W9: 1.5 | X9: 1.5 | Y9: 1.5 | Z9: 1.6 | AA9: 1.6 | AB9: 1.6 | AC9: 1.4 | AD9: 1.4 | AE9: 1.4 | AF9: 1.2 | AG9: 1.2 | AH9: 1.2 | AI9: 1.1 | AJ9: 1.1 | AK9: 1.1 | AL9: 0.6 | AM9: 0.6 | AN9: 0.6 | AO9: 1.2 | AP9: 1.2 | AQ9: 1.2 | AR9: 1 | AS9: 1 | AT9: 1 | AU9: 0.7 | AV9: 0.7 | AW9: 0.7 | AY9: -1 | AZ9: -2
AY10: -2 | AZ10: -4
A11: Pair | B11: 44927 | C11: 44958 | D11: 44986 | E11: 45017 | F11: 45047 | G11: 45078 | H11: 45108 | I11: 45139 | J11: 45170 | K11: 45200 | L11: 45231 | M11: 45261 | N11: 45292 | O11: 45323 | P11: 45352 | Q11: 45383 | R11: 45413 | S11: 45444 | T11: 45474 | U11: 45505 | V11: 45536 | W11: 45566 | X11: 45597 | Y11: 45627 | Z11: 45658 | AA11: 45689 | AB11: 45717 | AC11: 45748 | AD11: 45778 | AE11: 45809 | AF11: 45839 | AG11: 45870 | AH11: 45901 | AI11: 45931 | AJ11: 45962 | AK11: 45992 | AL11: 46023 | AM11: 46054 | AN11: 46082 | AO11: 46113 | AP11: 46143 | AQ11: 46174 | AR11: 46204 | AS11: 46235 | AT11: 46266 | AU11: 46296 | AV11: 46327 | AW11: 46357 | AY11: -3 | AZ11: -6
A12: USD JPY | B12: =B8-B3 | C12: =C8-C3 | D12: =D8-D3 | E12: =E8-E3 | F12: =F8-F3 | G12: =G8-G3 | H12: =H8-H3 | I12: =I8-I3 | ... AW12: =AW8-AW3 | AY12: -4 | AZ12: -8
A13: USD CHF | B13: =B8-B6 | C13: =C8-C6 | D13: =D8-D6 | E13: =E8-E6 | F13: =F8-F6 | G13: =G8-G6 | H13: =H8-H6 | I13: =I8-I6 | ... AW13: =AW8-AW6 | AY13: -5 | AZ13: -10
A14: USD CAD | B14: =B8-B3 | C14: =C8-C3 | D14: =D8-D3 | E14: =E8-E3 | F14: =F8-F3 | G14: =G8-G3 | H14: =H8-H3 | I14: =I8-I3 | ... AW14: =AW8-AW3
A15: EUR USD | B15: =B9-B8 | C15: =C9-C8 | D15: =D9-D8 | E15: =E9-E8 | F15: =F9-F8 | G15: =G9-G8 | H15: =H9-H8 | I15: =I9-I8 | ... AW15: =AW9-AW8
A16: EUR JPY | B16: =B9-B4 | C16: =C9-C4 | D16: =D9-D4 | E16: =E9-E4 | F16: =F9-F4 | G16: =G9-G4 | H16: =H9-H4 | I16: =I9-I4 | ... AW16: =AW9-AW4
A17: EUR CHF | B17: =B9-B6 | C17: =C9-C6 | D17: =D9-D6 | E17: =E9-E6 | F17: =F9-F6 | G17: =G9-G6 | H17: =H9-H6 | I17: =I9-I6 | ... AW17: =AW9-AW6
A18: EUR GBP | B18: =B9-B7 | C18: =C9-C7 | D18: =D9-D7 | E18: =E9-E7 | F18: =F9-F7 | G18: =G9-G7 | H18: =H9-H7 | I18: =I9-I7 | ... AW18: =AW9-AW7
A19: EUR CAD | B19: =B9-B3 | C19: =C9-C3 | D19: =D9-D3 | E19: =E9-E3 | F19: =F9-F3 | G19: =G9-G3 | H19: =H9-H3 | I19: =I9-I3 | ... AW19: =AW9-AW3
A20: EUR AUD | B20: =B9-B2 | C20: =C9-C2 | D20: =D9-D2 | E20: =E9-E2 | F20: =F9-F2 | G20: =G9-G2 | H20: =H9-H2 | I20: =I9-I2 | ... AW20: =AW9-AW2
A21: EUR NZD | B21: =B9-B5 | C21: =C9-C5 | D21: =D9-D5 | E21: =E9-E5 | F21: =F9-F5 | G21: =G9-G5 | H21: =H9-H5 | I21: =I9-I5 | ... AW21: =AW9-AW5
A22: GBP USD | B22: =B7-B8 | C22: =C7-C8 | D22: =D7-D8 | E22: =E7-E8 | F22: =F7-F8 | G22: =G7-G8 | H22: =H7-H8 | I22: =I7-I8 | ... AW22: =AW7-AW8
A23: GBP JPY | B23: =B7-B4 | C23: =C7-C4 | D23: =D7-D4 | E23: =E7-E4 | F23: =F7-F4 | G23: =G7-G4 | H23: =H7-H4 | I23: =I7-I4 | ... AW23: =AW7-AW4
A24: GBP CHF | B24: =B7-B6 | C24: =C7-C6 | D24: =D7-D6 | E24: =E7-E6 | F24: =F7-F6 | G24: =G7-G6 | H24: =H7-H6 | I24: =I7-I6 | ... AW24: =AW7-AW6
A25: GBP CAD | B25: =B7-B3 | C25: =C7-C3 | D25: =D7-D3 | E25: =E7-E3 | F25: =F7-F3 | G25: =G7-G3 | H25: =H7-H3 | I25: =I7-I3 | ... AW25: =AW7-AW3
A26: GBP AUD | B26: =B7-B2 | C26: =C7-C2 | D26: =D7-D2 | E26: =E7-E2 | F26: =F7-F2 | G26: =G7-G2 | H26: =H7-H2 | I26: =I7-I2 | ... AW26: =AW7-AW2
A27: GBP NZD | B27: =B7-B5 | C27: =C7-C5 | D27: =D7-D5 | E27: =E7-E5 | F27: =F7-F5 | G27: =G7-G5 | H27: =H7-H5 | I27: =I7-I5 | ... AW27: =AW7-AW5
A28: CHF JPY | B28: =B6-B4 | C28: =C6-C4 | D28: =D6-D4 | E28: =E6-E4 | F28: =F6-F4 | G28: =G6-G4 | H28: =H6-H4 | I28: =I6-I4 | ... AW28: =AW6-AW4
A29: AUD USD | B29: =B2-B8 | C29: =C2-C8 | D29: =D2-D8 | E29: =E2-E8 | F29: =F2-F8 | G29: =G2-G8 | H29: =H2-H8 | I29: =I2-I8 | ... AW29: =AW2-AW8
A30: AUD CHF | B30: =B2-B6 | C30: =C2-C6 | D30: =D2-D6 | E30: =E2-E6 | F30: =F2-F6 | G30: =G2-G6 | H30: =H2-H6 | I30: =I2-I6 | ... AW30: =AW2-AW6
A31: AUD JPY | B31: =B2-B4 | C31: =C2-C4 | D31: =D2-D4 | E31: =E2-E4 | F31: =F2-F4 | G31: =G2-G4 | H31: =H2-H4 | I31: =I2-I4 | ... AW31: =AW2-AW4
A32: AUD NZD | B32: =B2-B5 | C32: =C2-C5 | D32: =D2-D5 | E32: =E2-E5 | F32: =F2-F5 | G32: =G2-G5 | H32: =H2-H5 | I32: =I2-I5 | ... AW32: =AW2-AW5
A33: AUD CAD | B33: =B2-B3 | C33: =C2-C3 | D33: =D2-D3 | E33: =E2-E3 | F33: =F2-F3 | G33: =G2-G3 | H33: =H2-H3 | I33: =I2-I3 | ... AW33: =AW2-AW3
A34: CAD JPY | B34: =B3-B4 | C34: =C3-C4 | D34: =D3-D4 | E34: =E3-E4 | F34: =F3-F4 | G34: =G3-G4 | H34: =H3-H4 | I34: =I3-I4 | ... AW34: =AW3-AW4
A37: Pair | B37: 44927 | C37: 44958 | D37: 44986 | E37: 45017 | F37: 45047 | G37: 45078 | H37: 45108 | I37: 45139 | J37: 45170 | K37: 45200 | L37: 45231 | M37: 45261 | N37: 45292 | O37: 45323 | P37: 45352 | Q37: 45383 | R37: 45413 | S37: 45444 | T37: 45474 | U37: 45505 | V37: 45536 | W37: 45566 | X37: 45597 | Y37: 45627 | Z37: 45658 | AA37: 45689 | AB37: 45717 | AC37: 45748 | AD37: 45778 | AE37: 45809 | AF37: 45839 | AG37: 45870 | AH37: 45901 | AI37: 45931 | AJ37: 45962 | AK37: 45992 | AL37: 46023 | AM37: 46054 | AN37: 46082 | AO37: 46113 | AP37: 46143 | AQ37: 46174 | AR37: 46204 | AS37: 46235 | AT37: 46266 | AU37: 46296 | AV37: 46327 | AW37: 46357
A38: USD JPY | B38: =VLOOKUP(ROUND(B12, 0), $AY$3:$AZ$13, 2, FALSE) | C38: =VLOOKUP(ROUND(C12, 0), $AY$3:$AZ$13, 2, FALSE) | D38: =VLOOKUP(ROUND(D12, 0), $AY$3:$AZ$13, 2, FALSE) | E38: =VLOOKUP(ROUND(E12, 0), $AY$3:$AZ$13, 2, FALSE) | F38: =VLOOKUP(ROUND(F12, 0), $AY$3:$AZ$13, 2, FALSE) | G38: =VLOOKUP(ROUND(G12, 0), $AY$3:$AZ$13, 2, FALSE) | H38: =VLOOKUP(ROUND(H12, 0), $AY$3:$AZ$13, 2, FALSE) | I38: =VLOOKUP(ROUND(I12, 0), $AY$3:$AZ$13, 2, FALSE) | ... AW38: =VLOOKUP(ROUND(AW12, 0), $AY$3:$AZ$13, 2, FALSE)
A39: USD CHF | B39: =VLOOKUP(ROUND(B13, 0), $AY$3:$AZ$13, 2, FALSE) | C39: =VLOOKUP(ROUND(C13, 0), $AY$3:$AZ$13, 2, FALSE) | D39: =VLOOKUP(ROUND(D13, 0), $AY$3:$AZ$13, 2, FALSE) | E39: =VLOOKUP(ROUND(E13, 0), $AY$3:$AZ$13, 2, FALSE) | F39: =VLOOKUP(ROUND(F13, 0), $AY$3:$AZ$13, 2, FALSE) | G39: =VLOOKUP(ROUND(G13, 0), $AY$3:$AZ$13, 2, FALSE) | H39: =VLOOKUP(ROUND(H13, 0), $AY$3:$AZ$13, 2, FALSE) | I39: =VLOOKUP(ROUND(I13, 0), $AY$3:$AZ$13, 2, FALSE) | ... AW39: =VLOOKUP(ROUND(AW13, 0), $AY$3:$AZ$13, 2, FALSE)
A40: USD CAD | B40: =VLOOKUP(ROUND(B14, 0), $AY$3:$AZ$13, 2, FALSE) | C40: =VLOOKUP(ROUND(C14, 0), $AY$3:$AZ$13, 2, FALSE) | D40: =VLOOKUP(ROUND(D14, 0), $AY$3:$AZ$13, 2, FALSE) | E40: =VLOOKUP(ROUND(E14, 0), $AY$3:$AZ$13, 2, FALSE) | F40: =VLOOKUP(ROUND(F14, 0), $AY$3:$AZ$13, 2, FALSE) | G40: =VLOOKUP(ROUND(G14, 0), $AY$3:$AZ$13, 2, FALSE) | H40: =VLOOKUP(ROUND(H14, 0), $AY$3:$AZ$13, 2, FALSE) | I40: =VLOOKUP(ROUND(I14, 0), $AY$3:$AZ$13, 2, FALSE) | ... AW40: =VLOOKUP(ROUND(AW14, 0), $AY$3:$AZ$13, 2, FALSE)
A41: EUR USD | B41: =VLOOKUP(ROUND(B15, 0), $AY$3:$AZ$13, 2, FALSE) | C41: =VLOOKUP(ROUND(C15, 0), $AY$3:$AZ$13, 2, FALSE) | D41: =VLOOKUP(ROUND(D15, 0), $AY$3:$AZ$13, 2, FALSE) | E41: =VLOOKUP(ROUND(E15, 0), $AY$3:$AZ$13, 2, FALSE) | F41: =VLOOKUP(ROUND(F15, 0), $AY$3:$AZ$13, 2, FALSE) | G41: =VLOOKUP(ROUND(G15, 0), $AY$3:$AZ$13, 2, FALSE) | H41: =VLOOKUP(ROUND(H15, 0), $AY$3:$AZ$13, 2, FALSE) | I41: =VLOOKUP(ROUND(I15, 0), $AY$3:$AZ$13, 2, FALSE) | ... AW41: =VLOOKUP(ROUND(AW15, 0), $AY$3:$AZ$13, 2, FALSE)
A42: EUR JPY | B42: =VLOOKUP(ROUND(B16, 0), $AY$3:$AZ$13, 2, FALSE) | C42: =VLOOKUP(ROUND(C16, 0), $AY$3:$AZ$13, 2, FALSE) | D42: =VLOOKUP(ROUND(D16, 0), $AY$3:$AZ$13, 2, FALSE) | E42: =VLOOKUP(ROUND(E16, 0), $AY$3:$AZ$13, 2, FALSE) | F42: =VLOOKUP(ROUND(F16, 0), $AY$3:$AZ$13, 2, FALSE) | G42: =VLOOKUP(ROUND(G16, 0), $AY$3:$AZ$13, 2, FALSE) | H42: =VLOOKUP(ROUND(H16, 0), $AY$3:$AZ$13, 2, FALSE) | I42: =VLOOKUP(ROUND(I16, 0), $AY$3:$AZ$13, 2, FALSE) | ... AW42: =VLOOKUP(ROUND(AW16, 0), $AY$3:$AZ$13, 2, FALSE)
A43: EUR CHF | B43: =VLOOKUP(ROUND(B17, 0), $AY$3:$AZ$13, 2, FALSE) | C43: =VLOOKUP(ROUND(C17, 0), $AY$3:$AZ$13, 2, FALSE) | D43: =VLOOKUP(ROUND(D17, 0), $AY$3:$AZ$13, 2, FALSE) | E43: =VLOOKUP(ROUND(E17, 0), $AY$3:$AZ$13, 2, FALSE) | F43: =VLOOKUP(ROUND(F17, 0), $AY$3:$AZ$13, 2, FALSE) | G43: =VLOOKUP(ROUND(G17, 0), $AY$3:$AZ$13, 2, FALSE) | H43: =VLOOKUP(ROUND(H17, 0), $AY$3:$AZ$13, 2, FALSE) | I43: =VLOOKUP(ROUND(I17, 0), $AY$3:$AZ$13, 2, FALSE) | ... AW43: =VLOOKUP(ROUND(AW17, 0), $AY$3:$AZ$13, 2, FALSE)
A44: EUR GBP | B44: =VLOOKUP(ROUND(B18, 0), $AY$3:$AZ$13, 2, FALSE) | C44: =VLOOKUP(ROUND(C18, 0), $AY$3:$AZ$13, 2, FALSE) | D44: =VLOOKUP(ROUND(D18, 0), $AY$3:$AZ$13, 2, FALSE) | E44: =VLOOKUP(ROUND(E18, 0), $AY$3:$AZ$13, 2, FALSE) | F44: =VLOOKUP(ROUND(F18, 0), $AY$3:$AZ$13, 2, FALSE) | G44: =VLOOKUP(ROUND(G18, 0), $AY$3:$AZ$13, 2, FALSE) | H44: =VLOOKUP(ROUND(H18, 0), $AY$3:$AZ$13, 2, FALSE) | I44: =VLOOKUP(ROUND(I18, 0), $AY$3:$AZ$13, 2, FALSE) | ... AW44: =VLOOKUP(ROUND(AW18, 0), $AY$3:$AZ$13, 2, FALSE)
A45: EUR CAD | B45: =VLOOKUP(ROUND(B19, 0), $AY$3:$AZ$13, 2, FALSE) | C45: =VLOOKUP(ROUND(C19, 0), $AY$3:$AZ$13, 2, FALSE) | D45: =VLOOKUP(ROUND(D19, 0), $AY$3:$AZ$13, 2, FALSE) | E45: =VLOOKUP(ROUND(E19, 0), $AY$3:$AZ$13, 2, FALSE) | F45: =VLOOKUP(ROUND(F19, 0), $AY$3:$AZ$13, 2, FALSE) | G45: =VLOOKUP(ROUND(G19, 0), $AY$3:$AZ$13, 2, FALSE) | H45: =VLOOKUP(ROUND(H19, 0), $AY$3:$AZ$13, 2, FALSE) | I45: =VLOOKUP(ROUND(I19, 0), $AY$3:$AZ$13, 2, FALSE) | ... AW45: =VLOOKUP(ROUND(AW19, 0), $AY$3:$AZ$13, 2, FALSE)
A46: EUR AUD | B46: =VLOOKUP(ROUND(B20, 0), $AY$3:$AZ$13, 2, FALSE) | C46: =VLOOKUP(ROUND(C20, 0), $AY$3:$AZ$13, 2, FALSE) | D46: =VLOOKUP(ROUND(D20, 0), $AY$3:$AZ$13, 2, FALSE) | E46: =VLOOKUP(ROUND(E20, 0), $AY$3:$AZ$13, 2, FALSE) | F46: =VLOOKUP(ROUND(F20, 0), $AY$3:$AZ$13, 2, FALSE) | G46: =VLOOKUP(ROUND(G20, 0), $AY$3:$AZ$13, 2, FALSE) | H46: =VLOOKUP(ROUND(H20, 0), $AY$3:$AZ$13, 2, FALSE) | I46: =VLOOKUP(ROUND(I20, 0), $AY$3:$AZ$13, 2, FALSE) | ... AW46: =VLOOKUP(ROUND(AW20, 0), $AY$3:$AZ$13, 2, FALSE)
A47: EUR NZD | B47: =VLOOKUP(ROUND(B21, 0), $AY$3:$AZ$13, 2, FALSE) | C47: =VLOOKUP(ROUND(C21, 0), $AY$3:$AZ$13, 2, FALSE) | D47: =VLOOKUP(ROUND(D21, 0), $AY$3:$AZ$13, 2, FALSE) | E47: =VLOOKUP(ROUND(E21, 0), $AY$3:$AZ$13, 2, FALSE) | F47: =VLOOKUP(ROUND(F21, 0), $AY$3:$AZ$13, 2, FALSE) | G47: =VLOOKUP(ROUND(G21, 0), $AY$3:$AZ$13, 2, FALSE) | H47: =VLOOKUP(ROUND(H21, 0), $AY$3:$AZ$13, 2, FALSE) | I47: =VLOOKUP(ROUND(I21, 0), $AY$3:$AZ$13, 2, FALSE) | ... AW47: =VLOOKUP(ROUND(AW21, 0), $AY$3:$AZ$13, 2, FALSE)
A48: GBP USD | B48: =VLOOKUP(ROUND(B22, 0), $AY$3:$AZ$13, 2, FALSE) | C48: =VLOOKUP(ROUND(C22, 0), $AY$3:$AZ$13, 2, FALSE) | D48: =VLOOKUP(ROUND(D22, 0), $AY$3:$AZ$13, 2, FALSE) | E48: =VLOOKUP(ROUND(E22, 0), $AY$3:$AZ$13, 2, FALSE) | F48: =VLOOKUP(ROUND(F22, 0), $AY$3:$AZ$13, 2, FALSE) | G48: =VLOOKUP(ROUND(G22, 0), $AY$3:$AZ$13, 2, FALSE) | H48: =VLOOKUP(ROUND(H22, 0), $AY$3:$AZ$13, 2, FALSE) | I48: =VLOOKUP(ROUND(I22, 0), $AY$3:$AZ$13, 2, FALSE) | ... AW48: =VLOOKUP(ROUND(AW22, 0), $AY$3:$AZ$13, 2, FALSE)
A49: GBP JPY | B49: =VLOOKUP(ROUND(B23, 0), $AY$3:$AZ$13, 2, FALSE) | C49: =VLOOKUP(ROUND(C23, 0), $AY$3:$AZ$13, 2, FALSE) | D49: =VLOOKUP(ROUND(D23, 0), $AY$3:$AZ$13, 2, FALSE) | E49: =VLOOKUP(ROUND(E23, 0), $AY$3:$AZ$13, 2, FALSE) | F49: =VLOOKUP(ROUND(F23, 0), $AY$3:$AZ$13, 2, FALSE) | G49: =VLOOKUP(ROUND(G23, 0), $AY$3:$AZ$13, 2, FALSE) | H49: =VLOOKUP(ROUND(H23, 0), $AY$3:$AZ$13, 2, FALSE) | I49: =VLOOKUP(ROUND(I23, 0), $AY$3:$AZ$13, 2, FALSE) | ... AW49: =VLOOKUP(ROUND(AW23, 0), $AY$3:$AZ$13, 2, FALSE)
... A60: CAD JPY | B60: =VLOOKUP(ROUND(B34, 0), $AY$3:$AZ$13, 2, FALSE) | C60: =VLOOKUP(ROUND(C34, 0), $AY$3:$AZ$13, 2, FALSE) | D60: =VLOOKUP(ROUND(D34, 0), $AY$3:$AZ$13, 2, FALSE) | E60: =VLOOKUP(ROUND(E34, 0), $AY$3:$AZ$13, 2, FALSE) | F60: =VLOOKUP(ROUND(F34, 0), $AY$3:$AZ$13, 2, FALSE) | G60: =VLOOKUP(ROUND(G34, 0), $AY$3:$AZ$13, 2, FALSE) | H60: =VLOOKUP(ROUND(H34, 0), $AY$3:$AZ$13, 2, FALSE) | I60: =VLOOKUP(ROUND(I34, 0), $AY$3:$AZ$13, 2, FALSE) | ... AW60: =VLOOKUP(ROUND(AW34, 0), $AY$3:$AZ$13, 2, FALSE)

Sheet CA GDP DATA
A2: BOP | B2: 44927 | C2: 44958 | D2: 44986 | E2: 45017 | F2: 45047 | G2: 45078 | H2: 45108 | I2: 45139 | J2: 45170 | K2: 45200 | L2: 45231 | M2: 45261 | N2: 45292 | O2: 45323 | P2: 45352 | Q2: 45383 | R2: 45413 | S2: 45444 | T2: 45474 | U2: 45505 | V2: 45536 | W2: 45566 | X2: 45597 | Y2: 45627 | Z2: 45658 | AA2: 45689 | AB2: 45717 | AC2: 45748 | AD2: 45778 | AE2: 45809 | AF2: 45839 | AG2: 45870 | AH2: 45901 | AI2: 45931 | AJ2: 45962 | AK2: 45992 | AL2: 46023 | AM2: 46054 | AN2: 46082 | AO2: 46113 | AP2: 46143 | AQ2: 46174 | AR2: 46204 | AS2: 46235 | AT2: 46266 | AU2: 46296 | AV2: 46327 | AW2: 46357
A3: Australia | B3: 0.5178161 | C3: 0.5178161 | D3: 0.5178161 | E3: -0.2283273 | F3: -0.2283273 | G3: -0.2283273 | H3: -1.40563 | I3: -1.40563 | J3: -1.40563 | K3: -0.2746948 | L3: -0.2746948 | M3: -0.2746948 | N3: -1.318746 | O3: -1.318746 | P3: -1.318746 | Q3: -2.394648 | R3: -2.394648 | S3: -2.394648 | T3: -2.472772 | U3: -2.472772 | V3: -2.472772 | W3: -2.611136 | X3: -2.611136 | Y3: -2.611136 | Z3: -2.264893 | AA3: -2.264893 | AB3: -2.264893 | AC3: -2.380304 | AD3: -2.380304 | AE3: -2.380304 | AF3: -2.648238 | AG3: -2.648238 | AH3: -2.648238 | AI3: -3.106944 | AJ3: -3.106944 | AK3: -3.106944 | AL3: -3.453962 | AM3: -3.453962 | AN3: -3.453962 | AO3: -3.665983 | AP3: -3.665983 | AQ3: -3.665983 | AR3: -3.665983 | AS3: -3.665983 | AT3: -3.665983
A4: Canada | B4: -0.9103057 | C4: -0.9103057 | D4: -0.9103057 | E4: -0.7758245 | F4: -0.7758245 | G4: -0.7758245 | H4: -0.7987553 | I4: -0.7987553 | J4: -0.7987553 | K4: -0.2814779 | L4: -0.2814779 | M4: -0.2814779 | N4: -0.7692237 | O4: -0.7692237 | P4: -0.7692237 | Q4: -0.4802992 | R4: -0.4802992 | S4: -0.4802992 | T4: -0.5910502 | U4: -0.5910502 | V4: -0.5910502 | W4: -0.1004742 | X4: -0.1004742 | Y4: -0.1004742 | Z4: -0.3616118 | AA4: -0.3616118 | AB4: -0.3616118 | AC4: -2.715445 | AD4: -2.715445 | AE4: -2.715445 | AF4: -0.6209641 | AG4: -0.6209641 | AH4: -0.6209641 | AI4: -0.1228772 | AJ4: -0.1228772 | AK4: -0.1228772 | AL4: -0.9986504 | AM4: -0.9986504 | AN4: -0.9986504 | AO4: 1.028123 | AP4: 1.028123 | AQ4: 1.028123 | AR4: 1.028123 | AS4: 1.028123 | AT4: 1.028123
A5: Japan | B5: 2.198734 | C5: 2.198734 | D5: 2.198734 | E5: 3.925856 | F5: 3.925856 | G5: 3.925856 | H5: 4.356519 | I5: 4.356519 | J5: 4.356519 | K5: 4.297242 | L5: 4.297242 | M5: 4.297242 | N5: 4.324823 | O5: 4.324823 | P5: 4.324823 | Q5: 4.471209 | R5: 4.471209 | S5: 4.471209 | T5: 4.842206 | U5: 4.842206 | V5: 4.842206 | W5: 4.697466 | X5: 4.697466 | Y5: 4.697466 | Z5: 4.628131 | AA5: 4.628131 | AB5: 4.628131 | AC5: 4.412066 | AD5: 4.412066 | AE5: 4.412066 | AF5: 5.328309 | AG5: 5.328309 | AH5: 5.328309 | AI5: 4.902074 | AJ5: 4.902074 | AK5: 4.902074 | AL5: 5.809678 | AM5: 5.809678 | AN5: 5.809678 | AO5: 5.033247 | AP5: 5.033247 | AQ5: 5.033247 | AR5: 5.033247 | AS5: 5.033247 | AT5: 5.033247
A6: Switzerland | B6: 5.051963 | C6: 5.051963 | D6: 5.051963 | E6: 6.851121 | F6: 6.851121 | G6: 6.851121 | H6: 7.81084 | I6: 7.81084 | J6: 7.81084 | K6: 3.0269 | L6: 3.0269 | M6: 3.0269 | N6: 11.87226 | O6: 11.87226 | P6: 11.87226 | Q6: 11.46023 | R6: 11.46023 | S6: 11.46023 | T6: 3.415149 | U6: 3.415149 | V6: 3.415149 | W6: 9.550939 | X6: 9.550939 | Y6: 9.550939 | Z6: 15.59482 | AA6: 15.59482 | AB6: 15.59482 | AC6: 3.399356 | AD6: 3.399356 | AE6: 3.399356 | AF6: 4.245384 | AG6: 4.245384 | AH6: 4.245384 | AI6: 0.1449953 | AJ6: 0.1449953 | AK6: 0.1449953 | AL6: 10.02279 | AM6: 10.02279 | AN6: 10.02279 | AO6: 9.198192 | AP6: 9.198192 | AQ6: 9.198192 | AR6: 9.198192 | AS6: 9.198192 | AT6: 9.198192
A7: New Zealand | B7: -7.207618 | C7: -7.207618 | D7: -7.207618 | E7: -5.753605 | F7: -5.753605 | G7: -5.753605 | H7: -5.886574 | I7: -5.886574 | J7: -5.886574 | K7: -5.338708 | L7: -5.338708 | M7: -5.338708 | N7: -5.368975 | O7: -5.368975 | P7: -5.368975 | Q7: -5.430479 | R7: -5.430479 | S7: -5.430479 | T7: -4.83238 | U7: -4.83238 | V7: -4.83238 | W7: -4.003401 | X7: -4.003401 | Y7: -4.003401 | Z7: -3.545576 | AA7: -3.545576 | AB7: -3.545576 | AC7: -2.391005 | AD7: -2.391005 | AE7: -2.391005 | AF7: -2.354201 | AG7: -2.354201 | AH7: -2.354201 | AI7: -3.647876 | AJ7: -3.647876 | AK7: -3.647876 | AL7: -3.849324 | AM7: -3.849324 | AN7: -3.849324 | AO7: -3.255669 | AP7: -3.255669 | AQ7: -3.255669 | AR7: -3.255669 | AS7: -3.255669 | AT7: -3.255669 | AY7: 14 | AZ7: 10
A8: United Kingdom | B8: -2.913895 | C8: -2.913895 | D8: -2.913895 | E8: -5.029161 | F8: -5.029161 | G8: -5.029161 | H8: -2.271199 | I8: -2.271199 | J8: -2.271199 | K8: -4.062315 | L8: -4.062315 | M8: -4.062315 | N8: -2.972881 | O8: -2.972881 | P8: -2.972881 | Q8: -3.261572 | R8: -3.261572 | S8: -3.261572 | T8: -1.932302 | U8: -1.932302 | V8: -1.932302 | W8: -3.654375 | X8: -3.654375 | Y8: -3.654375 | Z8: -3.101889 | AA8: -3.101889 | AB8: -3.101889 | AC8: -3.238587 | AD8: -3.238587 | AE8: -3.238587 | AF8: -2.634263 | AG8: -2.634263 | AH8: -2.634263 | AI8: -3.541209 | AJ8: -3.541209 | AK8: -3.541209 | AL8: -2.835533 | AM8: -2.835533 | AN8: -2.835533 | AO8: -2.835533 | AP8: -2.835533 | AQ8: -2.835533 | AR8: -2.835533 | AS8: -2.835533 | AT8: -2.835533 | AY8: 12 | AZ8: 9
A9: United States | B9: -3.276534 | C9: -3.276534 | D9: -3.276534 | E9: -3.371748 | F9: -3.371748 | G9: -3.371748 | H9: -3.181111 | I9: -3.181111 | J9: -3.181111 | K9: -3.561928 | L9: -3.561928 | M9: -3.561928 | N9: -3.606222 | O9: -3.606222 | P9: -3.606222 | Q9: -3.882617 | R9: -3.882617 | S9: -3.882617 | T9: -4.48155 | U9: -4.48155 | V9: -4.48155 | W9: -4.375336 | X9: -4.375336 | Y9: -4.375336 | Z9: -5.834996 | AA9: -5.834996 | AB9: -5.834996 | AC9: -3.344384 | AD9: -3.344384 | AE9: -3.344384 | AF9: -3.381205 | AG9: -3.381205 | AH9: -3.381205 | AI9: -2.814096 | AJ9: -2.814096 | AK9: -2.814096 | AL9: -2.668661 | AM9: -2.668661 | AN9: -2.668661 | AO9: -3.029274 | AP9: -3.029274 | AQ9: -3.029274 | AR9: -3.029274 | AS9: -3.029274 | AT9: -3.029274 | AY9: 11 | AZ9: 8
A10: EURO AREA | B10: 0.9049219 | C10: 0.9049219 | D10: 0.9049219 | E10: 1.469623 | F10: 1.469623 | G10: 1.469623 | H10: 1.854201 | I10: 1.854201 | J10: 1.854201 | K10: 2.415108 | L10: 2.415108 | M10: 2.415108 | N10: 2.868217 | O10: 2.868217 | P10: 2.868217 | Q10: 3.068143 | R10: 3.068143 | S10: 3.068143 | T10: 2.158417 | U10: 2.158417 | V10: 2.158417 | W10: 2.027561 | X10: 2.027561 | Y10: 2.027561 | Z10: 1.647232 | AA10: 1.647232 | AB10: 1.647232 | AC10: 1.952547 | AD10: 1.952547 | AE10: 1.952547 | AF10: 1.41954 | AG10: 1.41954 | AH10: 1.41954 | AI10: 1.554832 | AJ10: 1.554832 | AK10: 1.554832 | AL10: 1.917209 | AM10: 1.917209 | AN10: 1.917209 | AO10: 1.917209 | AP10: 1.917209 | AQ10: 1.917209 | AR10: 1.917209 | AS10: 1.917209 | AT10: 1.917209 | AY10: 10 | AZ10: 7
AY11: 9 | AZ11: 6
AX12: 8 | AY12: 8 | AZ12: 5
AY13: 7 | AZ13: 4
A14: Paire | B14: 44927 | C14: 44958 | D14: 44986 | E14: 45017 | F14: 45047 | G14: 45078 | H14: 45108 | I14: 45139 | J14: 45170 | K14: 45200 | L14: 45231 | M14: 45261 | N14: 45292 | O14: 45323 | P14: 45352 | Q14: 45383 | R14: 45413 | S14: 45444 | T14: 45474 | U14: 45505 | V14: 45536 | W14: 45566 | X14: 45597 | Y14: 45627 | Z14: 45658 | AA14: 45689 | AB14: 45717 | AC14: 45748 | AD14: 45778 | AE14: 45809 | AF14: 45839 | AG14: 45870 | AH14: 45901 | AI14: 45931 | AJ14: 45962 | AK14: 45992 | AL14: 46023 | AM14: 46054 | AN14: 46082 | AO14: 46113 | AP14: 46143 | AQ14: 46174 | AR14: 46204 | AS14: 46235 | AT14: 46266 | AU14: 46296 | AV14: 46327 | AW14: 46357 | AY14: 6 | AZ14: 3
A15: USD JPY | B15: =B9-B5 | C15: =C9-C5 | D15: =D9-D5 | E15: =E9-E5 | F15: =F9-F5 | G15: =G9-G5 | H15: =H9-H5 | I15: =I9-I5 | ... AW15: =AW9-AW5 | AY15: 4 | AZ15: 2
A16: USD CHF | B16: =B9-B6 | C16: =C9-C6 | D16: =D9-D6 | E16: =E9-E6 | F16: =F9-F6 | G16: =G9-G6 | H16: =H9-H6 | I16: =I9-I6 | ... AJ16: =AJ9-AJ6 | AK16: =AK10-AK6 | AL16: =AL10-AL6 | AM16: =AM10-AM6 | AN16: =AN10-AN6 | AO16: =AO10-AO6 | AP16: =AP10-AP6 | AQ16: =AQ10-AQ6 | AR16: =AR10-AR6 | ... AW16: =AW10-AW6 | AY16: 2 | AZ16: 1
A17: USD CAD | B17: =B9-B4 | C17: =C9-C4 | D17: =D9-D4 | E17: =E9-E4 | F17: =F9-F4 | G17: =G9-G4 | H17: =H9-H4 | I17: =I9-I4 | ... AW17: =AW9-AW4 | AY17: 0 | AZ17: 0
A18: EUR USD | B18: =B10-B9 | C18: =C10-C9 | D18: =D10-D9 | E18: =E10-E9 | F18: =F10-F9 | G18: =G10-G9 | H18: =H10-H9 | I18: =I10-I9 | ... AW18: =AW10-AW9 | AY18: -2 | AZ18: -1
A19: EUR JPY | B19: =B10-B5 | C19: =C10-C5 | D19: =D10-D5 | E19: =E10-E5 | F19: =F10-F5 | G19: =G10-G5 | H19: =H10-H5 | I19: =I10-I5 | ... AW19: =AW10-AW5 | AY19: -4 | AZ19: -2
A20: EUR CHF | B20: =B10-B6 | C20: =C10-C6 | D20: =D10-D6 | E20: =E10-E6 | F20: =F10-F6 | G20: =G10-G6 | H20: =H10-H6 | I20: =I10-I6 | ... AW20: =AW10-AW6 | AY20: -6 | AZ20: -3
A21: EUR GBP | B21: =B10-B8 | C21: =C10-C8 | D21: =D10-D8 | E21: =E10-E8 | F21: =F10-F8 | G21: =G10-G8 | H21: =H10-H8 | I21: =I10-I8 | ... AW21: =AW10-AW8 | AY21: -7 | AZ21: -4
A22: EUR CAD | B22: =B10-B4 | C22: =C10-C4 | D22: =D10-D4 | E22: =E10-E4 | F22: =F10-F4 | G22: =G10-G4 | H22: =H10-H4 | I22: =I10-I4 | ... AW22: =AW10-AW4 | AY22: -8 | AZ22: -5
A23: EUR AUD | B23: 0 | C23: 0 | D23: 0 | E23: 0 | F23: 0 | G23: 0 | H23: 0 | I23: 0 | J23: 0 | K23: 0 | L23: 0 | M23: 0 | N23: 0 | O23: 0 | P23: 0 | Q23: 0 | R23: 0 | S23: 0 | T23: 0 | U23: 0 | V23: 0 | W23: 0 | X23: 0 | Y23: 0 | Z23: 0 | AA23: 0 | AB23: 0 | AC23: =AC10-AC3 | AD23: =AD10-AD3 | AE23: =AE10-AE3 | AF23: =AF10-AF3 | AG23: =AG10-AG3 | AH23: =AH10-AH3 | AI23: =AI10-AI3 | AJ23: =AJ10-AJ3 | ... AW23: =AW10-AW3 | AY23: -9 | AZ23: -6
A24: EUR NZD | B24: =B10-B7 | C24: =C10-C7 | D24: =D10-D7 | E24: =E10-E7 | F24: =F10-F7 | G24: =G10-G7 | H24: =H10-H7 | I24: =I10-I7 | ... AW24: =AW10-AW7 | AY24: -10 | AZ24: -7
A25: GBP USD | B25: =B8-B9 | C25: =C8-C9 | D25: =D8-D9 | E25: =E8-E9 | F25: =F8-F9 | G25: =G8-G9 | H25: =H8-H9 | I25: =I8-I9 | ... AW25: =AW8-AW9 | AY25: -11 | AZ25: -8
A26: GBP JPY | B26: =B8-B5 | C26: =C8-C5 | D26: =D8-D5 | E26: =E8-E5 | F26: =F8-F5 | G26: =G8-G5 | H26: =H8-H5 | I26: =I8-I5 | ... AW26: =AW8-AW5 | AY26: -12 | AZ26: -9
A27: GBP CHF | B27: =B8-B6 | C27: =C8-C6 | D27: =D8-D6 | E27: =E8-E6 | F27: =F8-F6 | G27: =G8-G6 | H27: =H8-H6 | I27: =I8-I6 | ... AW27: =AW8-AW6 | AY27: -14 | AZ27: -10
A28: GBP CAD | B28: =B8-B4 | C28: =C8-C4 | D28: =D8-D4 | E28: =E8-E4 | F28: =F8-F4 | G28: =G8-G4 | H28: =H8-H4 | I28: =I8-I4 | ... AW28: =AW8-AW4
A29: GBP AUD | B29: =B8-B3 | C29: =C8-C3 | D29: =D8-D3 | E29: =E8-E3 | F29: =F8-F3 | G29: =G8-G3 | H29: =H8-H3 | I29: =I8-I3 | ... AW29: =AW8-AW3
A30: GBP NZD | B30: =B8-B7 | C30: =C8-C7 | D30: =D8-D7 | E30: =E8-E7 | F30: =F8-F7 | G30: =G8-G7 | H30: =H8-H7 | I30: =I8-I7 | ... AW30: =AW8-AW7
A31: CHF JPY | B31: =B6-B5 | C31: =C6-C5 | D31: =D6-D5 | E31: =E6-E5 | F31: =F6-F5 | G31: =G6-G5 | H31: =H6-H5 | I31: =I6-I5 | ... AW31: =AW6-AW5
A32: AUD USD | B32: =B3-B9 | C32: =C3-C9 | D32: =D3-D9 | E32: =E3-E9 | F32: =F3-F9 | G32: =G3-G9 | H32: =H3-H9 | I32: =I3-I9 | ... AW32: =AW3-AW9
A33: AUD CHF | B33: =B3-B6 | C33: =C3-C6 | D33: =D3-D6 | E33: =E3-E6 | F33: =F3-F6 | G33: =G3-G6 | H33: =H3-H6 | I33: =I3-I6 | ... AW33: =AW3-AW6
A34: AUD JPY | B34: =B3-B5 | C34: =C3-C5 | D34: =D3-D5 | E34: =E3-E5 | F34: =F3-F5 | G34: =G3-G5 | H34: =H3-H5 | I34: =I3-I5 | ... AW34: =AW3-AW5
A35: AUD NZD | B35: =B3-B7 | C35: =C3-C7 | D35: =D3-D7 | E35: =E3-E7 | F35: =F3-F7 | G35: =G3-G7 | H35: =H3-H7 | I35: =I3-I7 | ... AW35: =AW3-AW7
A36: AUD CAD | B36: =B3-B4 | C36: =C3-C4 | D36: =D3-D4 | E36: =E3-E4 | F36: =F3-F4 | G36: =G3-G4 | H36: =H3-H4 | I36: =I3-I4 | ... AW36: =AW3-AW4
A37: CAD JPY | B37: =B4-B5 | C37: =C4-C5 | D37: =D4-D5 | E37: =E4-E5 | F37: =F4-F5 | G37: =G4-G5 | H37: =H4-H5 | I37: =I4-I5 | ... AW37: =AW4-AW5
A43: Paire | B43: 44927 | C43: 44958 | D43: 44986 | E43: 45017 | F43: 45047 | G43: 45078 | H43: 45108 | I43: 45139 | J43: 45170 | K43: 45200 | L43: 45231 | M43: 45261 | N43: 45292 | O43: 45323 | P43: 45352 | Q43: 45383 | R43: 45413 | S43: 45444 | T43: 45474 | U43: 45505 | V43: 45536 | W43: 45566 | X43: 45597 | Y43: 45627 | Z43: 45658 | AA43: 45689 | AB43: 45717 | AC43: 45748 | AD43: 45778 | AE43: 45809 | AF43: 45839 | AG43: 45870 | AH43: 45901 | AI43: 45931 | AJ43: 45962 | AK43: 45992 | AL43: 46023 | AM43: 46054 | AN43: 46082 | AO43: 46113 | AP43: 46143 | AQ43: 46174 | AR43: 46204 | AS43: 46235 | AT43: 46266 | AU43: 46296 | AV43: 46327 | AW43: 46357
A44: USD JPY | B44: {=_xlfn.XLOOKUP(MIN(ABS($AY$7:$AY$27 - MEDIAN(MIN($AY$7:$AY$27), MAX($AY$7:$AY$27), B15))), ABS($AY$7:$AY$27 - MEDIAN(MIN($AY$7:$AY$27), MAX($AY$7:$AY$27), B15)), $AZ$7:$AZ$27, "Not Found", 0)} | C44: {=_xlfn.XLOOKUP(MIN(ABS($AY$7:$AY$27 - MEDIAN(MIN($AY$7:$AY$27), MAX($AY$7:$AY$27), C15))), ABS($AY$7:$AY$27 - MEDIAN(MIN($AY$7:$AY$27), MAX($AY$7:$AY$27), C15)), $AZ$7:$AZ$27, "Not Found", 0)} | D44: {=_xlfn.XLOOKUP(MIN(ABS($AY$7:$AY$27 - MEDIAN(MIN($AY$7:$AY$27), MAX($AY$7:$AY$27), D15))), ABS($AY$7:$AY$27 - MEDIAN(MIN($AY$7:$AY$27), MAX($AY$7:$AY$27), D15)), $AZ$7:$AZ$27, "Not Found", 0)} | E44: {=_xlfn.XLOOKUP(MIN(ABS($AY$7:$AY$27 - MEDIAN(MIN($AY$7:$AY$27), MAX($AY$7:$AY$27), E15))), ABS($AY$7:$AY$27 - MEDIAN(MIN($AY$7:$AY$27), MAX($AY$7:$AY$27), E15)), $AZ$7:$AZ$27, "Not Found", 0)} | F44: {=_xlfn.XLOOKUP(MIN(ABS($AY$7:$AY$27 - MEDIAN(MIN($AY$7:$AY$27), MAX($AY$7:$AY$27), F15))), ABS($AY$7:$AY$27 - MEDIAN(MIN($AY$7:$AY$27), MAX($AY$7:$AY$27), F15)), $AZ$7:$AZ$27, "Not Found", 0)} | G44: {=_xlfn.XLOOKUP(MIN(ABS($AY$7:$AY$27 - MEDIAN(MIN($AY$7:$AY$27), MAX($AY$7:$AY$27), G15))), ABS($AY$7:$AY$27 - MEDIAN(MIN($AY$7:$AY$27), MAX($AY$7:$AY$27), G15)), $AZ$7:$AZ$27, "Not Found", 0)} | H44: {=_xlfn.XLOOKUP(MIN(ABS($AY$7:$AY$27 - MEDIAN(MIN($AY$7:$AY$27), MAX($AY$7:$AY$27), H15))), ABS($AY$7:$AY$27 - MEDIAN(MIN($AY$7:$AY$27), MAX($AY$7:$AY$27), H15)), $AZ$7:$AZ$27, "Not Found", 0)} | I44: {=_xlfn.XLOOKUP(MIN(ABS($AY$7:$AY$27 - MEDIAN(MIN($AY$7:$AY$27), MAX($AY$7:$AY$27), I15))), ABS($AY$7:$AY$27 - MEDIAN(MIN($AY$7:$AY$27), MAX($AY$7:$AY$27), I15)), $AZ$7:$AZ$27, "Not Found", 0)} | ... AW44: {=_xlfn.XLOOKUP(MIN(ABS($AY$7:$AY$27 - MEDIAN(MIN($AY$7:$AY$27), MAX($AY$7:$AY$27), AW15))), ABS($AY$7:$AY$27 - MEDIAN(MIN($AY$7:$AY$27), MAX($AY$7:$AY$27), AW15)), $AZ$7:$AZ$27, "Not Found", 0)}
A45: USD CHF | B45: {=_xlfn.XLOOKUP(MIN(ABS($AY$7:$AY$27 - MEDIAN(MIN($AY$7:$AY$27), MAX($AY$7:$AY$27), B16))), ABS($AY$7:$AY$27 - MEDIAN(MIN($AY$7:$AY$27), MAX($AY$7:$AY$27), B16)), $AZ$7:$AZ$27, "Not Found", 0)} | C45: {=_xlfn.XLOOKUP(MIN(ABS($AY$7:$AY$27 - MEDIAN(MIN($AY$7:$AY$27), MAX($AY$7:$AY$27), C16))), ABS($AY$7:$AY$27 - MEDIAN(MIN($AY$7:$AY$27), MAX($AY$7:$AY$27), C16)), $AZ$7:$AZ$27, "Not Found", 0)} | D45: {=_xlfn.XLOOKUP(MIN(ABS($AY$7:$AY$27 - MEDIAN(MIN($AY$7:$AY$27), MAX($AY$7:$AY$27), D16))), ABS($AY$7:$AY$27 - MEDIAN(MIN($AY$7:$AY$27), MAX($AY$7:$AY$27), D16)), $AZ$7:$AZ$27, "Not Found", 0)} | E45: {=_xlfn.XLOOKUP(MIN(ABS($AY$7:$AY$27 - MEDIAN(MIN($AY$7:$AY$27), MAX($AY$7:$AY$27), E16))), ABS($AY$7:$AY$27 - MEDIAN(MIN($AY$7:$AY$27), MAX($AY$7:$AY$27), E16)), $AZ$7:$AZ$27, "Not Found", 0)} | F45: {=_xlfn.XLOOKUP(MIN(ABS($AY$7:$AY$27 - MEDIAN(MIN($AY$7:$AY$27), MAX($AY$7:$AY$27), F16))), ABS($AY$7:$AY$27 - MEDIAN(MIN($AY$7:$AY$27), MAX($AY$7:$AY$27), F16)), $AZ$7:$AZ$27, "Not Found", 0)} | G45: {=_xlfn.XLOOKUP(MIN(ABS($AY$7:$AY$27 - MEDIAN(MIN($AY$7:$AY$27), MAX($AY$7:$AY$27), G16))), ABS($AY$7:$AY$27 - MEDIAN(MIN($AY$7:$AY$27), MAX($AY$7:$AY$27), G16)), $AZ$7:$AZ$27, "Not Found", 0)} | H45: {=_xlfn.XLOOKUP(MIN(ABS($AY$7:$AY$27 - MEDIAN(MIN($AY$7:$AY$27), MAX($AY$7:$AY$27), H16))), ABS($AY$7:$AY$27 - MEDIAN(MIN($AY$7:$AY$27), MAX($AY$7:$AY$27), H16)), $AZ$7:$AZ$27, "Not Found", 0)} | I45: {=_xlfn.XLOOKUP(MIN(ABS($AY$7:$AY$27 - MEDIAN(MIN($AY$7:$AY$27), MAX($AY$7:$AY$27), I16))), ABS($AY$7:$AY$27 - MEDIAN(MIN($AY$7:$AY$27), MAX($AY$7:$AY$27), I16)), $AZ$7:$AZ$27, "Not Found", 0)} | ... AW45: {=_xlfn.XLOOKUP(MIN(ABS($AY$7:$AY$27 - MEDIAN(MIN($AY$7:$AY$27), MAX($AY$7:$AY$27), AW16))), ABS($AY$7:$AY$27 - MEDIAN(MIN($AY$7:$AY$27), MAX($AY$7:$AY$27), AW16)), $AZ$7:$AZ$27, "Not Found", 0)}
A46: USD CAD | B46: {=_xlfn.XLOOKUP(MIN(ABS($AY$7:$AY$27 - MEDIAN(MIN($AY$7:$AY$27), MAX($AY$7:$AY$27), B17))), ABS($AY$7:$AY$27 - MEDIAN(MIN($AY$7:$AY$27), MAX($AY$7:$AY$27), B17)), $AZ$7:$AZ$27, "Not Found", 0)} | C46: {=_xlfn.XLOOKUP(MIN(ABS($AY$7:$AY$27 - MEDIAN(MIN($AY$7:$AY$27), MAX($AY$7:$AY$27), C17))), ABS($AY$7:$AY$27 - MEDIAN(MIN($AY$7:$AY$27), MAX($AY$7:$AY$27), C17)), $AZ$7:$AZ$27, "Not Found", 0)} | D46: {=_xlfn.XLOOKUP(MIN(ABS($AY$7:$AY$27 - MEDIAN(MIN($AY$7:$AY$27), MAX($AY$7:$AY$27), D17))), ABS($AY$7:$AY$27 - MEDIAN(MIN($AY$7:$AY$27), MAX($AY$7:$AY$27), D17)), $AZ$7:$AZ$27, "Not Found", 0)} | E46: {=_xlfn.XLOOKUP(MIN(ABS($AY$7:$AY$27 - MEDIAN(MIN($AY$7:$AY$27), MAX($AY$7:$AY$27), E17))), ABS($AY$7:$AY$27 - MEDIAN(MIN($AY$7:$AY$27), MAX($AY$7:$AY$27), E17)), $AZ$7:$AZ$27, "Not Found", 0)} | F46: {=_xlfn.XLOOKUP(MIN(ABS($AY$7:$AY$27 - MEDIAN(MIN($AY$7:$AY$27), MAX($AY$7:$AY$27), F17))), ABS($AY$7:$AY$27 - MEDIAN(MIN($AY$7:$AY$27), MAX($AY$7:$AY$27), F17)), $AZ$7:$AZ$27, "Not Found", 0)} | G46: {=_xlfn.XLOOKUP(MIN(ABS($AY$7:$AY$27 - MEDIAN(MIN($AY$7:$AY$27), MAX($AY$7:$AY$27), G17))), ABS($AY$7:$AY$27 - MEDIAN(MIN($AY$7:$AY$27), MAX($AY$7:$AY$27), G17)), $AZ$7:$AZ$27, "Not Found", 0)} | H46: {=_xlfn.XLOOKUP(MIN(ABS($AY$7:$AY$27 - MEDIAN(MIN($AY$7:$AY$27), MAX($AY$7:$AY$27), H17))), ABS($AY$7:$AY$27 - MEDIAN(MIN($AY$7:$AY$27), MAX($AY$7:$AY$27), H17)), $AZ$7:$AZ$27, "Not Found", 0)} | I46: {=_xlfn.XLOOKUP(MIN(ABS($AY$7:$AY$27 - MEDIAN(MIN($AY$7:$AY$27), MAX($AY$7:$AY$27), I17))), ABS($AY$7:$AY$27 - MEDIAN(MIN($AY$7:$AY$27), MAX($AY$7:$AY$27), I17)), $AZ$7:$AZ$27, "Not Found", 0)} | ... AW46: {=_xlfn.XLOOKUP(MIN(ABS($AY$7:$AY$27 - MEDIAN(MIN($AY$7:$AY$27), MAX($AY$7:$AY$27), AW17))), ABS($AY$7:$AY$27 - MEDIAN(MIN($AY$7:$AY$27), MAX($AY$7:$AY$27), AW17)), $AZ$7:$AZ$27, "Not Found", 0)}
A47: EUR USD | B47: {=_xlfn.XLOOKUP(MIN(ABS($AY$7:$AY$27 - MEDIAN(MIN($AY$7:$AY$27), MAX($AY$7:$AY$27), B18))), ABS($AY$7:$AY$27 - MEDIAN(MIN($AY$7:$AY$27), MAX($AY$7:$AY$27), B18)), $AZ$7:$AZ$27, "Not Found", 0)} | C47: {=_xlfn.XLOOKUP(MIN(ABS($AY$7:$AY$27 - MEDIAN(MIN($AY$7:$AY$27), MAX($AY$7:$AY$27), C18))), ABS($AY$7:$AY$27 - MEDIAN(MIN($AY$7:$AY$27), MAX($AY$7:$AY$27), C18)), $AZ$7:$AZ$27, "Not Found", 0)} | D47: {=_xlfn.XLOOKUP(MIN(ABS($AY$7:$AY$27 - MEDIAN(MIN($AY$7:$AY$27), MAX($AY$7:$AY$27), D18))), ABS($AY$7:$AY$27 - MEDIAN(MIN($AY$7:$AY$27), MAX($AY$7:$AY$27), D18)), $AZ$7:$AZ$27, "Not Found", 0)} | E47: {=_xlfn.XLOOKUP(MIN(ABS($AY$7:$AY$27 - MEDIAN(MIN($AY$7:$AY$27), MAX($AY$7:$AY$27), E18))), ABS($AY$7:$AY$27 - MEDIAN(MIN($AY$7:$AY$27), MAX($AY$7:$AY$27), E18)), $AZ$7:$AZ$27, "Not Found", 0)} | F47: {=_xlfn.XLOOKUP(MIN(ABS($AY$7:$AY$27 - MEDIAN(MIN($AY$7:$AY$27), MAX($AY$7:$AY$27), F18))), ABS($AY$7:$AY$27 - MEDIAN(MIN($AY$7:$AY$27), MAX($AY$7:$AY$27), F18)), $AZ$7:$AZ$27, "Not Found", 0)} | G47: {=_xlfn.XLOOKUP(MIN(ABS($AY$7:$AY$27 - MEDIAN(MIN($AY$7:$AY$27), MAX($AY$7:$AY$27), G18))), ABS($AY$7:$AY$27 - MEDIAN(MIN($AY$7:$AY$27), MAX($AY$7:$AY$27), G18)), $AZ$7:$AZ$27, "Not Found", 0)} | H47: {=_xlfn.XLOOKUP(MIN(ABS($AY$7:$AY$27 - MEDIAN(MIN($AY$7:$AY$27), MAX($AY$7:$AY$27), H18))), ABS($AY$7:$AY$27 - MEDIAN(MIN($AY$7:$AY$27), MAX($AY$7:$AY$27), H18)), $AZ$7:$AZ$27, "Not Found", 0)} | I47: {=_xlfn.XLOOKUP(MIN(ABS($AY$7:$AY$27 - MEDIAN(MIN($AY$7:$AY$27), MAX($AY$7:$AY$27), I18))), ABS($AY$7:$AY$27 - MEDIAN(MIN($AY$7:$AY$27), MAX($AY$7:$AY$27), I18)), $AZ$7:$AZ$27, "Not Found", 0)} | ... AW47: {=_xlfn.XLOOKUP(MIN(ABS($AY$7:$AY$27 - MEDIAN(MIN($AY$7:$AY$27), MAX($AY$7:$AY$27), AW18))), ABS($AY$7:$AY$27 - MEDIAN(MIN($AY$7:$AY$27), MAX($AY$7:$AY$27), AW18)), $AZ$7:$AZ$27, "Not Found", 0)}
A48: EUR JPY | B48: {=_xlfn.XLOOKUP(MIN(ABS($AY$7:$AY$27 - MEDIAN(MIN($AY$7:$AY$27), MAX($AY$7:$AY$27), B19))), ABS($AY$7:$AY$27 - MEDIAN(MIN($AY$7:$AY$27), MAX($AY$7:$AY$27), B19)), $AZ$7:$AZ$27, "Not Found", 0)} | C48: {=_xlfn.XLOOKUP(MIN(ABS($AY$7:$AY$27 - MEDIAN(MIN($AY$7:$AY$27), MAX($AY$7:$AY$27), C19))), ABS($AY$7:$AY$27 - MEDIAN(MIN($AY$7:$AY$27), MAX($AY$7:$AY$27), C19)), $AZ$7:$AZ$27, "Not Found", 0)} | D48: {=_xlfn.XLOOKUP(MIN(ABS($AY$7:$AY$27 - MEDIAN(MIN($AY$7:$AY$27), MAX($AY$7:$AY$27), D19))), ABS($AY$7:$AY$27 - MEDIAN(MIN($AY$7:$AY$27), MAX($AY$7:$AY$27), D19)), $AZ$7:$AZ$27, "Not Found", 0)} | E48: {=_xlfn.XLOOKUP(MIN(ABS($AY$7:$AY$27 - MEDIAN(MIN($AY$7:$AY$27), MAX($AY$7:$AY$27), E19))), ABS($AY$7:$AY$27 - MEDIAN(MIN($AY$7:$AY$27), MAX($AY$7:$AY$27), E19)), $AZ$7:$AZ$27, "Not Found", 0)} | F48: {=_xlfn.XLOOKUP(MIN(ABS($AY$7:$AY$27 - MEDIAN(MIN($AY$7:$AY$27), MAX($AY$7:$AY$27), F19))), ABS($AY$7:$AY$27 - MEDIAN(MIN($AY$7:$AY$27), MAX($AY$7:$AY$27), F19)), $AZ$7:$AZ$27, "Not Found", 0)} | G48: {=_xlfn.XLOOKUP(MIN(ABS($AY$7:$AY$27 - MEDIAN(MIN($AY$7:$AY$27), MAX($AY$7:$AY$27), G19))), ABS($AY$7:$AY$27 - MEDIAN(MIN($AY$7:$AY$27), MAX($AY$7:$AY$27), G19)), $AZ$7:$AZ$27, "Not Found", 0)} | H48: {=_xlfn.XLOOKUP(MIN(ABS($AY$7:$AY$27 - MEDIAN(MIN($AY$7:$AY$27), MAX($AY$7:$AY$27), H19))), ABS($AY$7:$AY$27 - MEDIAN(MIN($AY$7:$AY$27), MAX($AY$7:$AY$27), H19)), $AZ$7:$AZ$27, "Not Found", 0)} | I48: {=_xlfn.XLOOKUP(MIN(ABS($AY$7:$AY$27 - MEDIAN(MIN($AY$7:$AY$27), MAX($AY$7:$AY$27), I19))), ABS($AY$7:$AY$27 - MEDIAN(MIN($AY$7:$AY$27), MAX($AY$7:$AY$27), I19)), $AZ$7:$AZ$27, "Not Found", 0)} | ... AW48: {=_xlfn.XLOOKUP(MIN(ABS($AY$7:$AY$27 - MEDIAN(MIN($AY$7:$AY$27), MAX($AY$7:$AY$27), AW19))), ABS($AY$7:$AY$27 - MEDIAN(MIN($AY$7:$AY$27), MAX($AY$7:$AY$27), AW19)), $AZ$7:$AZ$27, "Not Found", 0)}
A49: EUR CHF | B49: {=_xlfn.XLOOKUP(MIN(ABS($AY$7:$AY$27 - MEDIAN(MIN($AY$7:$AY$27), MAX($AY$7:$AY$27), B20))), ABS($AY$7:$AY$27 - MEDIAN(MIN($AY$7:$AY$27), MAX($AY$7:$AY$27), B20)), $AZ$7:$AZ$27, "Not Found", 0)} | C49: {=_xlfn.XLOOKUP(MIN(ABS($AY$7:$AY$27 - MEDIAN(MIN($AY$7:$AY$27), MAX($AY$7:$AY$27), C20))), ABS($AY$7:$AY$27 - MEDIAN(MIN($AY$7:$AY$27), MAX($AY$7:$AY$27), C20)), $AZ$7:$AZ$27, "Not Found", 0)} | D49: {=_xlfn.XLOOKUP(MIN(ABS($AY$7:$AY$27 - MEDIAN(MIN($AY$7:$AY$27), MAX($AY$7:$AY$27), D20))), ABS($AY$7:$AY$27 - MEDIAN(MIN($AY$7:$AY$27), MAX($AY$7:$AY$27), D20)), $AZ$7:$AZ$27, "Not Found", 0)} | E49: {=_xlfn.XLOOKUP(MIN(ABS($AY$7:$AY$27 - MEDIAN(MIN($AY$7:$AY$27), MAX($AY$7:$AY$27), E20))), ABS($AY$7:$AY$27 - MEDIAN(MIN($AY$7:$AY$27), MAX($AY$7:$AY$27), E20)), $AZ$7:$AZ$27, "Not Found", 0)} | F49: {=_xlfn.XLOOKUP(MIN(ABS($AY$7:$AY$27 - MEDIAN(MIN($AY$7:$AY$27), MAX($AY$7:$AY$27), F20))), ABS($AY$7:$AY$27 - MEDIAN(MIN($AY$7:$AY$27), MAX($AY$7:$AY$27), F20)), $AZ$7:$AZ$27, "Not Found", 0)} | G49: {=_xlfn.XLOOKUP(MIN(ABS($AY$7:$AY$27 - MEDIAN(MIN($AY$7:$AY$27), MAX($AY$7:$AY$27), G20))), ABS($AY$7:$AY$27 - MEDIAN(MIN($AY$7:$AY$27), MAX($AY$7:$AY$27), G20)), $AZ$7:$AZ$27, "Not Found", 0)} | H49: {=_xlfn.XLOOKUP(MIN(ABS($AY$7:$AY$27 - MEDIAN(MIN($AY$7:$AY$27), MAX($AY$7:$AY$27), H20))), ABS($AY$7:$AY$27 - MEDIAN(MIN($AY$7:$AY$27), MAX($AY$7:$AY$27), H20)), $AZ$7:$AZ$27, "Not Found", 0)} | I49: {=_xlfn.XLOOKUP(MIN(ABS($AY$7:$AY$27 - MEDIAN(MIN($AY$7:$AY$27), MAX($AY$7:$AY$27), I20))), ABS($AY$7:$AY$27 - MEDIAN(MIN($AY$7:$AY$27), MAX($AY$7:$AY$27), I20)), $AZ$7:$AZ$27, "Not Found", 0)} | ... AW49: {=_xlfn.XLOOKUP(MIN(ABS($AY$7:$AY$27 - MEDIAN(MIN($AY$7:$AY$27), MAX($AY$7:$AY$27), AW20))), ABS($AY$7:$AY$27 - MEDIAN(MIN($AY$7:$AY$27), MAX($AY$7:$AY$27), AW20)), $AZ$7:$AZ$27, "Not Found", 0)}
A50: EUR GBP | B50: {=_xlfn.XLOOKUP(MIN(ABS($AY$7:$AY$27 - MEDIAN(MIN($AY$7:$AY$27), MAX($AY$7:$AY$27), B21))), ABS($AY$7:$AY$27 - MEDIAN(MIN($AY$7:$AY$27), MAX($AY$7:$AY$27), B21)), $AZ$7:$AZ$27, "Not Found", 0)} | C50: {=_xlfn.XLOOKUP(MIN(ABS($AY$7:$AY$27 - MEDIAN(MIN($AY$7:$AY$27), MAX($AY$7:$AY$27), C21))), ABS($AY$7:$AY$27 - MEDIAN(MIN($AY$7:$AY$27), MAX($AY$7:$AY$27), C21)), $AZ$7:$AZ$27, "Not Found", 0)} | D50: {=_xlfn.XLOOKUP(MIN(ABS($AY$7:$AY$27 - MEDIAN(MIN($AY$7:$AY$27), MAX($AY$7:$AY$27), D21))), ABS($AY$7:$AY$27 - MEDIAN(MIN($AY$7:$AY$27), MAX($AY$7:$AY$27), D21)), $AZ$7:$AZ$27, "Not Found", 0)} | E50: {=_xlfn.XLOOKUP(MIN(ABS($AY$7:$AY$27 - MEDIAN(MIN($AY$7:$AY$27), MAX($AY$7:$AY$27), E21))), ABS($AY$7:$AY$27 - MEDIAN(MIN($AY$7:$AY$27), MAX($AY$7:$AY$27), E21)), $AZ$7:$AZ$27, "Not Found", 0)} | F50: {=_xlfn.XLOOKUP(MIN(ABS($AY$7:$AY$27 - MEDIAN(MIN($AY$7:$AY$27), MAX($AY$7:$AY$27), F21))), ABS($AY$7:$AY$27 - MEDIAN(MIN($AY$7:$AY$27), MAX($AY$7:$AY$27), F21)), $AZ$7:$AZ$27, "Not Found", 0)} | G50: {=_xlfn.XLOOKUP(MIN(ABS($AY$7:$AY$27 - MEDIAN(MIN($AY$7:$AY$27), MAX($AY$7:$AY$27), G21))), ABS($AY$7:$AY$27 - MEDIAN(MIN($AY$7:$AY$27), MAX($AY$7:$AY$27), G21)), $AZ$7:$AZ$27, "Not Found", 0)} | H50: {=_xlfn.XLOOKUP(MIN(ABS($AY$7:$AY$27 - MEDIAN(MIN($AY$7:$AY$27), MAX($AY$7:$AY$27), H21))), ABS($AY$7:$AY$27 - MEDIAN(MIN($AY$7:$AY$27), MAX($AY$7:$AY$27), H21)), $AZ$7:$AZ$27, "Not Found", 0)} | I50: {=_xlfn.XLOOKUP(MIN(ABS($AY$7:$AY$27 - MEDIAN(MIN($AY$7:$AY$27), MAX($AY$7:$AY$27), I21))), ABS($AY$7:$AY$27 - MEDIAN(MIN($AY$7:$AY$27), MAX($AY$7:$AY$27), I21)), $AZ$7:$AZ$27, "Not Found", 0)} | ... AW50: {=_xlfn.XLOOKUP(MIN(ABS($AY$7:$AY$27 - MEDIAN(MIN($AY$7:$AY$27), MAX($AY$7:$AY$27), AW21))), ABS($AY$7:$AY$27 - MEDIAN(MIN($AY$7:$AY$27), MAX($AY$7:$AY$27), AW21)), $AZ$7:$AZ$27, "Not Found", 0)}
A51: EUR CAD | B51: {=_xlfn.XLOOKUP(MIN(ABS($AY$7:$AY$27 - MEDIAN(MIN($AY$7:$AY$27), MAX($AY$7:$AY$27), B22))), ABS($AY$7:$AY$27 - MEDIAN(MIN($AY$7:$AY$27), MAX($AY$7:$AY$27), B22)), $AZ$7:$AZ$27, "Not Found", 0)} | C51: {=_xlfn.XLOOKUP(MIN(ABS($AY$7:$AY$27 - MEDIAN(MIN($AY$7:$AY$27), MAX($AY$7:$AY$27), C22))), ABS($AY$7:$AY$27 - MEDIAN(MIN($AY$7:$AY$27), MAX($AY$7:$AY$27), C22)), $AZ$7:$AZ$27, "Not Found", 0)} | D51: {=_xlfn.XLOOKUP(MIN(ABS($AY$7:$AY$27 - MEDIAN(MIN($AY$7:$AY$27), MAX($AY$7:$AY$27), D22))), ABS($AY$7:$AY$27 - MEDIAN(MIN($AY$7:$AY$27), MAX($AY$7:$AY$27), D22)), $AZ$7:$AZ$27, "Not Found", 0)} | E51: {=_xlfn.XLOOKUP(MIN(ABS($AY$7:$AY$27 - MEDIAN(MIN($AY$7:$AY$27), MAX($AY$7:$AY$27), E22))), ABS($AY$7:$AY$27 - MEDIAN(MIN($AY$7:$AY$27), MAX($AY$7:$AY$27), E22)), $AZ$7:$AZ$27, "Not Found", 0)} | F51: {=_xlfn.XLOOKUP(MIN(ABS($AY$7:$AY$27 - MEDIAN(MIN($AY$7:$AY$27), MAX($AY$7:$AY$27), F22))), ABS($AY$7:$AY$27 - MEDIAN(MIN($AY$7:$AY$27), MAX($AY$7:$AY$27), F22)), $AZ$7:$AZ$27, "Not Found", 0)} | G51: {=_xlfn.XLOOKUP(MIN(ABS($AY$7:$AY$27 - MEDIAN(MIN($AY$7:$AY$27), MAX($AY$7:$AY$27), G22))), ABS($AY$7:$AY$27 - MEDIAN(MIN($AY$7:$AY$27), MAX($AY$7:$AY$27), G22)), $AZ$7:$AZ$27, "Not Found", 0)} | H51: {=_xlfn.XLOOKUP(MIN(ABS($AY$7:$AY$27 - MEDIAN(MIN($AY$7:$AY$27), MAX($AY$7:$AY$27), H22))), ABS($AY$7:$AY$27 - MEDIAN(MIN($AY$7:$AY$27), MAX($AY$7:$AY$27), H22)), $AZ$7:$AZ$27, "Not Found", 0)} | I51: {=_xlfn.XLOOKUP(MIN(ABS($AY$7:$AY$27 - MEDIAN(MIN($AY$7:$AY$27), MAX($AY$7:$AY$27), I22))), ABS($AY$7:$AY$27 - MEDIAN(MIN($AY$7:$AY$27), MAX($AY$7:$AY$27), I22)), $AZ$7:$AZ$27, "Not Found", 0)} | ... AW51: {=_xlfn.XLOOKUP(MIN(ABS($AY$7:$AY$27 - MEDIAN(MIN($AY$7:$AY$27), MAX($AY$7:$AY$27), AW22))), ABS($AY$7:$AY$27 - MEDIAN(MIN($AY$7:$AY$27), MAX($AY$7:$AY$27), AW22)), $AZ$7:$AZ$27, "Not Found", 0)}
A52: EUR AUD | B52: {=_xlfn.XLOOKUP(MIN(ABS($AY$7:$AY$27 - MEDIAN(MIN($AY$7:$AY$27), MAX($AY$7:$AY$27), B23))), ABS($AY$7:$AY$27 - MEDIAN(MIN($AY$7:$AY$27), MAX($AY$7:$AY$27), B23)), $AZ$7:$AZ$27, "Not Found", 0)} | C52: {=_xlfn.XLOOKUP(MIN(ABS($AY$7:$AY$27 - MEDIAN(MIN($AY$7:$AY$27), MAX($AY$7:$AY$27), C23))), ABS($AY$7:$AY$27 - MEDIAN(MIN($AY$7:$AY$27), MAX($AY$7:$AY$27), C23)), $AZ$7:$AZ$27, "Not Found", 0)} | D52: {=_xlfn.XLOOKUP(MIN(ABS($AY$7:$AY$27 - MEDIAN(MIN($AY$7:$AY$27), MAX($AY$7:$AY$27), D23))), ABS($AY$7:$AY$27 - MEDIAN(MIN($AY$7:$AY$27), MAX($AY$7:$AY$27), D23)), $AZ$7:$AZ$27, "Not Found", 0)} | E52: {=_xlfn.XLOOKUP(MIN(ABS($AY$7:$AY$27 - MEDIAN(MIN($AY$7:$AY$27), MAX($AY$7:$AY$27), E23))), ABS($AY$7:$AY$27 - MEDIAN(MIN($AY$7:$AY$27), MAX($AY$7:$AY$27), E23)), $AZ$7:$AZ$27, "Not Found", 0)} | F52: {=_xlfn.XLOOKUP(MIN(ABS($AY$7:$AY$27 - MEDIAN(MIN($AY$7:$AY$27), MAX($AY$7:$AY$27), F23))), ABS($AY$7:$AY$27 - MEDIAN(MIN($AY$7:$AY$27), MAX($AY$7:$AY$27), F23)), $AZ$7:$AZ$27, "Not Found", 0)} | G52: {=_xlfn.XLOOKUP(MIN(ABS($AY$7:$AY$27 - MEDIAN(MIN($AY$7:$AY$27), MAX($AY$7:$AY$27), G23))), ABS($AY$7:$AY$27 - MEDIAN(MIN($AY$7:$AY$27), MAX($AY$7:$AY$27), G23)), $AZ$7:$AZ$27, "Not Found", 0)} | H52: {=_xlfn.XLOOKUP(MIN(ABS($AY$7:$AY$27 - MEDIAN(MIN($AY$7:$AY$27), MAX($AY$7:$AY$27), H23))), ABS($AY$7:$AY$27 - MEDIAN(MIN($AY$7:$AY$27), MAX($AY$7:$AY$27), H23)), $AZ$7:$AZ$27, "Not Found", 0)} | I52: {=_xlfn.XLOOKUP(MIN(ABS($AY$7:$AY$27 - MEDIAN(MIN($AY$7:$AY$27), MAX($AY$7:$AY$27), I23))), ABS($AY$7:$AY$27 - MEDIAN(MIN($AY$7:$AY$27), MAX($AY$7:$AY$27), I23)), $AZ$7:$AZ$27, "Not Found", 0)} | ... AW52: {=_xlfn.XLOOKUP(MIN(ABS($AY$7:$AY$27 - MEDIAN(MIN($AY$7:$AY$27), MAX($AY$7:$AY$27), AW23))), ABS($AY$7:$AY$27 - MEDIAN(MIN($AY$7:$AY$27), MAX($AY$7:$AY$27), AW23)), $AZ$7:$AZ$27, "Not Found", 0)}
A53: EUR NZD | B53: {=_xlfn.XLOOKUP(MIN(ABS($AY$7:$AY$27 - MEDIAN(MIN($AY$7:$AY$27), MAX($AY$7:$AY$27), B24))), ABS($AY$7:$AY$27 - MEDIAN(MIN($AY$7:$AY$27), MAX($AY$7:$AY$27), B24)), $AZ$7:$AZ$27, "Not Found", 0)} | C53: {=_xlfn.XLOOKUP(MIN(ABS($AY$7:$AY$27 - MEDIAN(MIN($AY$7:$AY$27), MAX($AY$7:$AY$27), C24))), ABS($AY$7:$AY$27 - MEDIAN(MIN($AY$7:$AY$27), MAX($AY$7:$AY$27), C24)), $AZ$7:$AZ$27, "Not Found", 0)} | D53: {=_xlfn.XLOOKUP(MIN(ABS($AY$7:$AY$27 - MEDIAN(MIN($AY$7:$AY$27), MAX($AY$7:$AY$27), D24))), ABS($AY$7:$AY$27 - MEDIAN(MIN($AY$7:$AY$27), MAX($AY$7:$AY$27), D24)), $AZ$7:$AZ$27, "Not Found", 0)} | E53: {=_xlfn.XLOOKUP(MIN(ABS($AY$7:$AY$27 - MEDIAN(MIN($AY$7:$AY$27), MAX($AY$7:$AY$27), E24))), ABS($AY$7:$AY$27 - MEDIAN(MIN($AY$7:$AY$27), MAX($AY$7:$AY$27), E24)), $AZ$7:$AZ$27, "Not Found", 0)} | F53: {=_xlfn.XLOOKUP(MIN(ABS($AY$7:$AY$27 - MEDIAN(MIN($AY$7:$AY$27), MAX($AY$7:$AY$27), F24))), ABS($AY$7:$AY$27 - MEDIAN(MIN($AY$7:$AY$27), MAX($AY$7:$AY$27), F24)), $AZ$7:$AZ$27, "Not Found", 0)} | G53: {=_xlfn.XLOOKUP(MIN(ABS($AY$7:$AY$27 - MEDIAN(MIN($AY$7:$AY$27), MAX($AY$7:$AY$27), G24))), ABS($AY$7:$AY$27 - MEDIAN(MIN($AY$7:$AY$27), MAX($AY$7:$AY$27), G24)), $AZ$7:$AZ$27, "Not Found", 0)} | H53: {=_xlfn.XLOOKUP(MIN(ABS($AY$7:$AY$27 - MEDIAN(MIN($AY$7:$AY$27), MAX($AY$7:$AY$27), H24))), ABS($AY$7:$AY$27 - MEDIAN(MIN($AY$7:$AY$27), MAX($AY$7:$AY$27), H24)), $AZ$7:$AZ$27, "Not Found", 0)} | I53: {=_xlfn.XLOOKUP(MIN(ABS($AY$7:$AY$27 - MEDIAN(MIN($AY$7:$AY$27), MAX($AY$7:$AY$27), I24))), ABS($AY$7:$AY$27 - MEDIAN(MIN($AY$7:$AY$27), MAX($AY$7:$AY$27), I24)), $AZ$7:$AZ$27, "Not Found", 0)} | ... AW53: {=_xlfn.XLOOKUP(MIN(ABS($AY$7:$AY$27 - MEDIAN(MIN($AY$7:$AY$27), MAX($AY$7:$AY$27), AW24))), ABS($AY$7:$AY$27 - MEDIAN(MIN($AY$7:$AY$27), MAX($AY$7:$AY$27), AW24)), $AZ$7:$AZ$27, "Not Found", 0)}
A54: GBP USD | B54: {=_xlfn.XLOOKUP(MIN(ABS($AY$7:$AY$27 - MEDIAN(MIN($AY$7:$AY$27), MAX($AY$7:$AY$27), B25))), ABS($AY$7:$AY$27 - MEDIAN(MIN($AY$7:$AY$27), MAX($AY$7:$AY$27), B25)), $AZ$7:$AZ$27, "Not Found", 0)} | C54: {=_xlfn.XLOOKUP(MIN(ABS($AY$7:$AY$27 - MEDIAN(MIN($AY$7:$AY$27), MAX($AY$7:$AY$27), C25))), ABS($AY$7:$AY$27 - MEDIAN(MIN($AY$7:$AY$27), MAX($AY$7:$AY$27), C25)), $AZ$7:$AZ$27, "Not Found", 0)} | D54: {=_xlfn.XLOOKUP(MIN(ABS($AY$7:$AY$27 - MEDIAN(MIN($AY$7:$AY$27), MAX($AY$7:$AY$27), D25))), ABS($AY$7:$AY$27 - MEDIAN(MIN($AY$7:$AY$27), MAX($AY$7:$AY$27), D25)), $AZ$7:$AZ$27, "Not Found", 0)} | E54: {=_xlfn.XLOOKUP(MIN(ABS($AY$7:$AY$27 - MEDIAN(MIN($AY$7:$AY$27), MAX($AY$7:$AY$27), E25))), ABS($AY$7:$AY$27 - MEDIAN(MIN($AY$7:$AY$27), MAX($AY$7:$AY$27), E25)), $AZ$7:$AZ$27, "Not Found", 0)} | F54: {=_xlfn.XLOOKUP(MIN(ABS($AY$7:$AY$27 - MEDIAN(MIN($AY$7:$AY$27), MAX($AY$7:$AY$27), F25))), ABS($AY$7:$AY$27 - MEDIAN(MIN($AY$7:$AY$27), MAX($AY$7:$AY$27), F25)), $AZ$7:$AZ$27, "Not Found", 0)} | G54: {=_xlfn.XLOOKUP(MIN(ABS($AY$7:$AY$27 - MEDIAN(MIN($AY$7:$AY$27), MAX($AY$7:$AY$27), G25))), ABS($AY$7:$AY$27 - MEDIAN(MIN($AY$7:$AY$27), MAX($AY$7:$AY$27), G25)), $AZ$7:$AZ$27, "Not Found", 0)} | H54: {=_xlfn.XLOOKUP(MIN(ABS($AY$7:$AY$27 - MEDIAN(MIN($AY$7:$AY$27), MAX($AY$7:$AY$27), H25))), ABS($AY$7:$AY$27 - MEDIAN(MIN($AY$7:$AY$27), MAX($AY$7:$AY$27), H25)), $AZ$7:$AZ$27, "Not Found", 0)} | I54: {=_xlfn.XLOOKUP(MIN(ABS($AY$7:$AY$27 - MEDIAN(MIN($AY$7:$AY$27), MAX($AY$7:$AY$27), I25))), ABS($AY$7:$AY$27 - MEDIAN(MIN($AY$7:$AY$27), MAX($AY$7:$AY$27), I25)), $AZ$7:$AZ$27, "Not Found", 0)} | ... AW54: {=_xlfn.XLOOKUP(MIN(ABS($AY$7:$AY$27 - MEDIAN(MIN($AY$7:$AY$27), MAX($AY$7:$AY$27), AW25))), ABS($AY$7:$AY$27 - MEDIAN(MIN($AY$7:$AY$27), MAX($AY$7:$AY$27), AW25)), $AZ$7:$AZ$27, "Not Found", 0)}
A55: GBP JPY | B55: {=_xlfn.XLOOKUP(MIN(ABS($AY$7:$AY$27 - MEDIAN(MIN($AY$7:$AY$27), MAX($AY$7:$AY$27), B26))), ABS($AY$7:$AY$27 - MEDIAN(MIN($AY$7:$AY$27), MAX($AY$7:$AY$27), B26)), $AZ$7:$AZ$27, "Not Found", 0)} | C55: {=_xlfn.XLOOKUP(MIN(ABS($AY$7:$AY$27 - MEDIAN(MIN($AY$7:$AY$27), MAX($AY$7:$AY$27), C26))), ABS($AY$7:$AY$27 - MEDIAN(MIN($AY$7:$AY$27), MAX($AY$7:$AY$27), C26)), $AZ$7:$AZ$27, "Not Found", 0)} | D55: {=_xlfn.XLOOKUP(MIN(ABS($AY$7:$AY$27 - MEDIAN(MIN($AY$7:$AY$27), MAX($AY$7:$AY$27), D26))), ABS($AY$7:$AY$27 - MEDIAN(MIN($AY$7:$AY$27), MAX($AY$7:$AY$27), D26)), $AZ$7:$AZ$27, "Not Found", 0)} | E55: {=_xlfn.XLOOKUP(MIN(ABS($AY$7:$AY$27 - MEDIAN(MIN($AY$7:$AY$27), MAX($AY$7:$AY$27), E26))), ABS($AY$7:$AY$27 - MEDIAN(MIN($AY$7:$AY$27), MAX($AY$7:$AY$27), E26)), $AZ$7:$AZ$27, "Not Found", 0)} | F55: {=_xlfn.XLOOKUP(MIN(ABS($AY$7:$AY$27 - MEDIAN(MIN($AY$7:$AY$27), MAX($AY$7:$AY$27), F26))), ABS($AY$7:$AY$27 - MEDIAN(MIN($AY$7:$AY$27), MAX($AY$7:$AY$27), F26)), $AZ$7:$AZ$27, "Not Found", 0)} | G55: {=_xlfn.XLOOKUP(MIN(ABS($AY$7:$AY$27 - MEDIAN(MIN($AY$7:$AY$27), MAX($AY$7:$AY$27), G26))), ABS($AY$7:$AY$27 - MEDIAN(MIN($AY$7:$AY$27), MAX($AY$7:$AY$27), G26)), $AZ$7:$AZ$27, "Not Found", 0)} | H55: {=_xlfn.XLOOKUP(MIN(ABS($AY$7:$AY$27 - MEDIAN(MIN($AY$7:$AY$27), MAX($AY$7:$AY$27), H26))), ABS($AY$7:$AY$27 - MEDIAN(MIN($AY$7:$AY$27), MAX($AY$7:$AY$27), H26)), $AZ$7:$AZ$27, "Not Found", 0)} | I55: {=_xlfn.XLOOKUP(MIN(ABS($AY$7:$AY$27 - MEDIAN(MIN($AY$7:$AY$27), MAX($AY$7:$AY$27), I26))), ABS($AY$7:$AY$27 - MEDIAN(MIN($AY$7:$AY$27), MAX($AY$7:$AY$27), I26)), $AZ$7:$AZ$27, "Not Found", 0)} | ... AW55: {=_xlfn.XLOOKUP(MIN(ABS($AY$7:$AY$27 - MEDIAN(MIN($AY$7:$AY$27), MAX($AY$7:$AY$27), AW26))), ABS($AY$7:$AY$27 - MEDIAN(MIN($AY$7:$AY$27), MAX($AY$7:$AY$27), AW26)), $AZ$7:$AZ$27, "Not Found", 0)}
... A66: CAD JPY | B66: {=_xlfn.XLOOKUP(MIN(ABS($AY$7:$AY$27 - MEDIAN(MIN($AY$7:$AY$27), MAX($AY$7:$AY$27), B37))), ABS($AY$7:$AY$27 - MEDIAN(MIN($AY$7:$AY$27), MAX($AY$7:$AY$27), B37)), $AZ$7:$AZ$27, "Not Found", 0)} | C66: {=_xlfn.XLOOKUP(MIN(ABS($AY$7:$AY$27 - MEDIAN(MIN($AY$7:$AY$27), MAX($AY$7:$AY$27), C37))), ABS($AY$7:$AY$27 - MEDIAN(MIN($AY$7:$AY$27), MAX($AY$7:$AY$27), C37)), $AZ$7:$AZ$27, "Not Found", 0)} | D66: {=_xlfn.XLOOKUP(MIN(ABS($AY$7:$AY$27 - MEDIAN(MIN($AY$7:$AY$27), MAX($AY$7:$AY$27), D37))), ABS($AY$7:$AY$27 - MEDIAN(MIN($AY$7:$AY$27), MAX($AY$7:$AY$27), D37)), $AZ$7:$AZ$27, "Not Found", 0)} | E66: {=_xlfn.XLOOKUP(MIN(ABS($AY$7:$AY$27 - MEDIAN(MIN($AY$7:$AY$27), MAX($AY$7:$AY$27), E37))), ABS($AY$7:$AY$27 - MEDIAN(MIN($AY$7:$AY$27), MAX($AY$7:$AY$27), E37)), $AZ$7:$AZ$27, "Not Found", 0)} | F66: {=_xlfn.XLOOKUP(MIN(ABS($AY$7:$AY$27 - MEDIAN(MIN($AY$7:$AY$27), MAX($AY$7:$AY$27), F37))), ABS($AY$7:$AY$27 - MEDIAN(MIN($AY$7:$AY$27), MAX($AY$7:$AY$27), F37)), $AZ$7:$AZ$27, "Not Found", 0)} | G66: {=_xlfn.XLOOKUP(MIN(ABS($AY$7:$AY$27 - MEDIAN(MIN($AY$7:$AY$27), MAX($AY$7:$AY$27), G37))), ABS($AY$7:$AY$27 - MEDIAN(MIN($AY$7:$AY$27), MAX($AY$7:$AY$27), G37)), $AZ$7:$AZ$27, "Not Found", 0)} | H66: {=_xlfn.XLOOKUP(MIN(ABS($AY$7:$AY$27 - MEDIAN(MIN($AY$7:$AY$27), MAX($AY$7:$AY$27), H37))), ABS($AY$7:$AY$27 - MEDIAN(MIN($AY$7:$AY$27), MAX($AY$7:$AY$27), H37)), $AZ$7:$AZ$27, "Not Found", 0)} | I66: {=_xlfn.XLOOKUP(MIN(ABS($AY$7:$AY$27 - MEDIAN(MIN($AY$7:$AY$27), MAX($AY$7:$AY$27), I37))), ABS($AY$7:$AY$27 - MEDIAN(MIN($AY$7:$AY$27), MAX($AY$7:$AY$27), I37)), $AZ$7:$AZ$27, "Not Found", 0)} | ... AW66: {=_xlfn.XLOOKUP(MIN(ABS($AY$7:$AY$27 - MEDIAN(MIN($AY$7:$AY$27), MAX($AY$7:$AY$27), AW37))), ABS($AY$7:$AY$27 - MEDIAN(MIN($AY$7:$AY$27), MAX($AY$7:$AY$27), AW37)), $AZ$7:$AZ$27, "Not Found", 0)}

Sheet CPI data
A2: CPI %YoY - source : IMF | B2: 44927 | C2: 44958 | D2: 44986 | E2: 45017 | F2: 45047 | G2: 45078 | H2: 45108 | I2: 45139 | J2: 45170 | K2: 45200 | L2: 45231 | M2: 45261 | N2: 45292 | O2: 45323 | P2: 45352 | Q2: 45383 | R2: 45413 | S2: 45444 | T2: 45474 | U2: 45505 | V2: 45536 | W2: 45566 | X2: 45597 | Y2: 45627 | Z2: 45658 | AA2: 45689 | AB2: 45717 | AC2: 45748 | AD2: 45778 | AE2: 45809 | AF2: 45839 | AG2: 45870 | AH2: 45901 | AI2: 45931 | AJ2: 45962 | AK2: 45992 | AL2: 46023 | AM2: 46054 | AN2: 46082 | AO2: 46113 | AP2: 46143 | AQ2: 46174 | AR2: 46204 | AS2: 46235 | AT2: 46266 | AU2: 46296 | AV2: 46327 | AW2: 46357
A3: Australia | B3: 7.5 | C3: 6.8 | D3: 6.3 | E3: 6.7 | F3: 5.5 | G3: 5.4 | H3: 4.9 | I3: 5.2 | J3: 5.6 | K3: 4.9 | L3: 4.3 | M3: 3.4 | N3: 3.4 | O3: 3.4 | P3: 3.5 | Q3: 3.6 | R3: 4 | S3: 3.8 | T3: 3.5 | U3: 2.7 | V3: 2.1 | W3: 2.1 | X3: 2.4 | Y3: 2.4 | Z3: 2.4 | AA3: 2.4 | AB3: 2.4 | AC3: 2.4 | AD3: 2.1 | AE3: 1.9 | AF3: 3 | AG3: 3.2 | AH3: 3.6 | AI3: 3.8 | AJ3: 3.4 | AK3: 3.8 | AL3: 3.8 | AM3: 3.7 | AN3: 4.6 | AO3: 4.2 | AP3: 4 | AQ3: 3.8 | AR3: 3.5 | AS3: 4 | AT3: 4.1 | AU3: 4.2
A4: Canada | B4: 5.9 | C4: 5.2 | D4: 4.3 | E4: 4.4 | F4: 3.4 | G4: 2.8 | H4: 3.3 | I4: 4 | J4: 3.8 | K4: 3.1 | L4: 3.1 | M4: 3.4 | N4: 2.9 | O4: 2.8 | P4: 2.9 | Q4: 2.7 | R4: 2.9 | S4: 2.7 | T4: 2.5 | U4: 2 | V4: 1.6 | W4: 2 | X4: 1.9 | Y4: 1.8 | Z4: 1.9 | AA4: 2.6 | AB4: 2.3 | AC4: 1.7 | AD4: 1.7 | AE4: 1.9 | AF4: 1.7 | AG4: 1.9 | AH4: 2.4 | AI4: 2.2 | AJ4: 2.2 | AK4: 2.4 | AL4: 2.3 | AM4: 1.8 | AN4: 2.4 | AO4: 2.8 | AP4: 3.2 | AQ4: 2.8 | AR4: 3 | AS4: 2.9 | AT4: 2.9 | AU4: 2.6
A5: Japan | B5: 4.3 | C5: 3.3 | D5: 3.2 | E5: 3.5 | F5: 3.2 | G5: 3.3 | H5: 3.3 | I5: 3.2 | J5: 3 | K5: 3.3 | L5: 2.8 | M5: 2.6 | N5: 2.2 | O5: 2.8 | P5: 2.7 | Q5: 2.5 | R5: 2.8 | S5: 2.8 | T5: 2.8 | U5: 3 | V5: 2.5 | W5: 2.3 | X5: 2.9 | Y5: 3.6 | Z5: 4 | AA5: 3.7 | AB5: 3.6 | AC5: 3.6 | AD5: 3.5 | AE5: 3.3 | AF5: 3.1 | AG5: 2.7 | AH5: 2.9 | AI5: 3 | AJ5: 2.9 | AK5: 2.1 | AL5: 1.5 | AM5: 1.3 | AN5: 1.5 | AO5: 1.4 | AP5: 1.5 | AQ5: 1.6 | AR5: 1.9 | AS5: 1.8 | AT5: 1.8 | AU5: 1.8
A6: Switzerland | B6: 3.3 | C6: 3.4 | D6: 2.9 | E6: 2.6 | F6: 2.2 | G6: 1.7 | H6: 1.6 | I6: 1.6 | J6: 1.7 | K6: 1.7 | L6: 1.4 | M6: 1.7 | N6: 1.3 | O6: 1.2 | P6: 1 | Q6: 1.4 | R6: 1.4 | S6: 1.3 | T6: 1.3 | U6: 1.1 | V6: 0.8 | W6: 0.6 | X6: 0.7 | Y6: 0.6 | Z6: 0.4 | AA6: 0.3 | AB6: 0.3 | AC6: 0 | AD6: -0.1 | AE6: 0.1 | AF6: 0.2 | AG6: 0.2 | AH6: 0.2 | AI6: 0.1 | AJ6: 0 | AK6: 0.1 | AL6: 0.1 | AM6: 0.1 | AN6: 0.3 | AO6: 0.6 | AP6: 0.6 | AQ6: 0.5 | AR6: 0.4 | AS6: 0.8 | AT6: 0.8 | AU6: 0.7 | AY6: -2 | AZ6: 2 | BB6: fx pair | BC6: data | BD6: rating | BF6: -0.02 | BG6: 2
A7: New Zealand | B7: 6.7 | C7: 6.7 | D7: 6.7 | E7: 6 | F7: 6 | G7: 6 | H7: 5.6 | I7: 5.6 | J7: 5.6 | K7: 4.7 | L7: 4.7 | M7: 4.7 | N7: 4 | O7: 4 | P7: 4 | Q7: 3.3 | R7: 3.3 | S7: 3.3 | T7: 2.2 | U7: 2.2 | V7: 2.2 | W7: 2.2 | X7: 2.2 | Y7: 2.2 | Z7: 2.5 | AA7: 2.5 | AB7: 2.5 | AC7: 2.7 | AD7: 2.7 | AE7: 2.7 | AF7: 3 | AG7: 3 | AH7: 3 | AI7: 3.1 | AJ7: 3.1 | AK7: 3.1 | AL7: 3.1 | AM7: 3.1 | AN7: 3.1 | AO7: 4.1 | AP7: 4.1 | AQ7: 4.1 | AR7: 3.7 | AS7: 3.7 | AT7: 3.7 | AU7: 3.5 | AY7: -1.75 | AZ7: 3 | BB7: USD JPY | BC7: =AL15 | BD7: -10 | BE7: {=_xlfn.XLOOKUP(MIN(ABS($AY$6:$AY$22 - MEDIAN(-2, 2, BC7))), ABS($AY$6:$AY$22 - MEDIAN(-2, 2, BC7)), $AZ$6:$AZ$22, "Error", 0)} | BF7: -0.0175 | BG7: 3 | BH7: =BD7-BE7
A8: United Kingdom | B8: 10.1 | C8: 10.4 | D8: 10.1 | E8: 8.7 | F8: 8.7 | G8: 7.9 | H8: 6.8 | I8: 6.7 | J8: 6.7 | K8: 4.6 | L8: 3.9 | M8: 4 | N8: 4 | O8: 3.4 | P8: 3.2 | Q8: 2.3 | R8: 2 | S8: 2 | T8: 2.2 | U8: 2.2 | V8: 1.7 | W8: 2.3 | X8: 2.6 | Y8: 2.5 | Z8: 3 | AA8: 2.8 | AB8: 2.6 | AC8: 3.5 | AD8: 3.4 | AE8: 3.6 | AF8: 3.8 | AG8: 3.8 | AH8: 3.8 | AI8: 3.6 | AJ8: 3.2 | AK8: 3.4 | AL8: 3 | AM8: 3 | AN8: 3.3 | AO8: 2.8 | AP8: 2.8 | AQ8: 2.6 | AR8: 2.9 | AS8: 2.9 | AT8: 3.6 | AU8: 3.5 | AY8: -1.5 | AZ8: 4 | BB8: USD CHF | BC8: =AL16 | BD8: 10 | BE8: {=_xlfn.XLOOKUP(MIN(ABS($AY$6:$AY$22 - MEDIAN(-2, 2, BC8))), ABS($AY$6:$AY$22 - MEDIAN(-2, 2, BC8)), $AZ$6:$AZ$22, "Error", 0)} | BF8: -0.015 | BG8: 4 | BH8: =BD8-BE8
A9: United States | B9: 6.4 | C9: 6 | D9: 5 | E9: 4.9 | F9: 4.1 | G9: 3 | H9: 3.2 | I9: 3.7 | J9: 3.7 | K9: 3.2 | L9: 3.1 | M9: 3.4 | N9: 3.1 | O9: 3.2 | P9: 3.5 | Q9: 3.4 | R9: 3.3 | S9: 3 | T9: 2.9 | U9: 2.5 | V9: 2.4 | W9: 2.6 | X9: 2.7 | Y9: 2.9 | Z9: 3 | AA9: 2.8 | AB9: 2.4 | AC9: 2.3 | AD9: 2.4 | AE9: 2.7 | AF9: 2.7 | AG9: 2.9 | AH9: 3 | AI9: 2.7 | AJ9: 2.7 | AK9: 2.7 | AL9: 2.4 | AM9: 2.4 | AN9: 3.3 | AO9: 3.8 | AP9: 4.2 | AQ9: 3.5 | AR9: 3.4 | AS9: 3.7 | AT9: 3.7 | AU9: 3.4 | AY9: -1.25 | AZ9: 6 | BB9: USD CAD | BC9: =AL17 | BD9: 0 | BE9: {=_xlfn.XLOOKUP(MIN(ABS($AY$6:$AY$22 - MEDIAN(-2, 2, BC9))), ABS($AY$6:$AY$22 - MEDIAN(-2, 2, BC9)), $AZ$6:$AZ$22, "Error", 0)} | BF9: -0.0125 | BG9: 6 | BH9: =BD9-BE9
A10: EURO AREA | B10: 8.7 | C10: 8.5 | D10: 6.9 | E10: 7 | F10: 6.1 | G10: 5.5 | H10: 5.3 | I10: 5.2 | J10: 4.3 | K10: 2.9 | L10: 2.4 | M10: 2.9 | N10: 2.8 | O10: 2.6 | P10: 2.4 | Q10: 2.4 | R10: 2.6 | S10: 2.5 | T10: 2.6 | U10: 2.2 | V10: 1.7 | W10: 2 | X10: 2.2 | Y10: 2.4 | Z10: 2.5 | AA10: 2.3 | AB10: 2.2 | AC10: 2.2 | AD10: 1.9 | AE10: 2 | AF10: 2 | AG10: 2 | AH10: 2.2 | AI10: 2.1 | AJ10: 2.1 | AK10: 2 | AL10: 1.7 | AM10: 1.9 | AN10: 2.6 | AO10: 3 | AP10: 3.2 | AQ10: 2.8 | AR10: 2.9 | AS10: 3.3 | AT10: 3.5 | AU10: 3.3 | AY10: -1 | AZ10: 10 | BB10: EUR USD | BC10: =AL18 | BD10: 8 | BE10: {=_xlfn.XLOOKUP(MIN(ABS($AY$6:$AY$22 - MEDIAN(-2, 2, BC10))), ABS($AY$6:$AY$22 - MEDIAN(-2, 2, BC10)), $AZ$6:$AZ$22, "Error", 0)} | BF10: -0.01 | BG10: 10 | BH10: =BD10-BE10
AY11: -0.75 | AZ11: 8 | BB11: EUR JPY | BC11: =AL19 | BD11: -4 | BE11: {=_xlfn.XLOOKUP(MIN(ABS($AY$6:$AY$22 - MEDIAN(-2, 2, BC11))), ABS($AY$6:$AY$22 - MEDIAN(-2, 2, BC11)), $AZ$6:$AZ$22, "Error", 0)} | BF11: -0.0075 | BG11: 8 | BH11: =BD11-BE11
AY12: -0.5 | AZ12: 6 | BB12: EUR CHF | BC12: =AL20 | BD12: 8 | BE12: {=_xlfn.XLOOKUP(MIN(ABS($AY$6:$AY$22 - MEDIAN(-2, 2, BC12))), ABS($AY$6:$AY$22 - MEDIAN(-2, 2, BC12)), $AZ$6:$AZ$22, "Error", 0)} | BF12: -0.005 | BG12: 6 | BH12: =BD12-BE12 | BK12: 8
AY13: -0.25 | AZ13: 4 | BB13: EUR GBP | BC13: =AL21 | BD13: 6 | BE13: {=_xlfn.XLOOKUP(MIN(ABS($AY$6:$AY$22 - MEDIAN(-2, 2, BC13))), ABS($AY$6:$AY$22 - MEDIAN(-2, 2, BC13)), $AZ$6:$AZ$22, "Error", 0)} | BF13: -0.0025 | BG13: 4 | BH13: =BD13-BE13
A14: Paire | B14: 44927 | C14: 44958 | D14: 44986 | E14: 45017 | F14: 45047 | G14: 45078 | H14: 45108 | I14: 45139 | J14: 45170 | K14: 45200 | L14: 45231 | M14: 45261 | N14: 45292 | O14: 45323 | P14: 45352 | Q14: 45383 | R14: 45413 | S14: 45444 | T14: 45474 | U14: 45505 | V14: 45536 | W14: 45566 | X14: 45597 | Y14: 45627 | Z14: 45658 | AA14: 45689 | AB14: 45717 | AC14: 45748 | AD14: 45778 | AE14: 45809 | AF14: 45839 | AG14: 45870 | AH14: 45901 | AI14: 45931 | AJ14: 45962 | AK14: 45992 | AL14: 46023 | AM14: 46054 | AN14: 46082 | AO14: 46113 | AP14: 46143 | AQ14: 46174 | AR14: 46204 | AS14: 46235 | AT14: 46266 | AU14: 46296 | AV14: 46327 | AW14: 46357 | AY14: 0 | AZ14: 0 | BB14: EUR CAD | BC14: =AL22 | BD14: 6 | BE14: {=_xlfn.XLOOKUP(MIN(ABS($AY$6:$AY$22 - MEDIAN(-2, 2, BC14))), ABS($AY$6:$AY$22 - MEDIAN(-2, 2, BC14)), $AZ$6:$AZ$22, "Error", 0)} | BF14: 0 | BG14: 0 | BH14: =BD14-BE14
A15: USD JPY | B15: =B9-B5 | C15: =C9-C5 | D15: =D9-D5 | E15: =E9-E5 | F15: =F9-F5 | G15: =G9-G5 | H15: =H9-H5 | I15: =I9-I5 | ... AW15: =AW9-AW5 | AY15: 0.25 | AZ15: -4 | BB15: EUR AUD | BC15: =AL23 | BD15: 2 | BE15: {=_xlfn.XLOOKUP(MIN(ABS($AY$6:$AY$22 - MEDIAN(-2, 2, BC15))), ABS($AY$6:$AY$22 - MEDIAN(-2, 2, BC15)), $AZ$6:$AZ$22, "Error", 0)} | BF15: 0.0025 | BG15: -4 | BH15: =BD15-BE15
A16: USD CHF | B16: =B9-B6 | C16: =C9-C6 | D16: =D9-D6 | E16: =E9-E6 | F16: =F9-F6 | G16: =G9-G6 | H16: =H9-H6 | I16: =I9-I6 | ... AW16: =AW9-AW6 | AY16: 0.5 | AZ16: -6 | BB16: EUR NZD | BC16: =AL24 | BD16: 8 | BE16: {=_xlfn.XLOOKUP(MIN(ABS($AY$6:$AY$22 - MEDIAN(-2, 2, BC16))), ABS($AY$6:$AY$22 - MEDIAN(-2, 2, BC16)), $AZ$6:$AZ$22, "Error", 0)} | BF16: 0.005 | BG16: -6 | BH16: =BD16-BE16
A17: USD CAD | B17: =B9-B4 | C17: =C9-C4 | D17: =D9-D4 | E17: =E9-E4 | F17: =F9-F4 | G17: =G9-G4 | H17: =H9-H4 | I17: =I9-I4 | ... AW17: =AW9-AW4 | AY17: 0.75 | AZ17: -8 | BB17: GBP USD | BC17: =AL25 | BD17: -6 | BE17: {=_xlfn.XLOOKUP(MIN(ABS($AY$6:$AY$22 - MEDIAN(-2, 2, BC17))), ABS($AY$6:$AY$22 - MEDIAN(-2, 2, BC17)), $AZ$6:$AZ$22, "Error", 0)} | BF17: 0.0075 | BG17: -8 | BH17: =BD17-BE17
A18: EUR USD | B18: =B10-B9 | C18: =C10-C9 | D18: =D10-D9 | E18: =E10-E9 | F18: =F10-F9 | G18: =G10-G9 | H18: =H10-H9 | I18: =I10-I9 | ... AW18: =AW10-AW9 | AY18: 1 | AZ18: -10 | BB18: GBP JPY | BC18: =AL26 | BD18: 8 | BE18: {=_xlfn.XLOOKUP(MIN(ABS($AY$6:$AY$22 - MEDIAN(-2, 2, BC18))), ABS($AY$6:$AY$22 - MEDIAN(-2, 2, BC18)), $AZ$6:$AZ$22, "Error", 0)} | BF18: 0.01 | BG18: -10 | BH18: =BD18-BE18
A19: EUR JPY | B19: =B10-B5 | C19: =C10-C5 | D19: =D10-D5 | E19: =E10-E5 | F19: =F10-F5 | G19: =G10-G5 | H19: =H10-H5 | I19: =I10-I5 | ... AW19: =AW10-AW5 | AY19: 1.25 | AZ19: 6 | BB19: GBP CHF | BC19: =AL27 | BD19: 10 | BE19: {=_xlfn.XLOOKUP(MIN(ABS($AY$6:$AY$22 - MEDIAN(-2, 2, BC19))), ABS($AY$6:$AY$22 - MEDIAN(-2, 2, BC19)), $AZ$6:$AZ$22, "Error", 0)} | BF19: 0.0125 | BG19: 6 | BH19: =BD19-BE19
A20: EUR CHF | B20: =B10-B6 | C20: =C10-C6 | D20: =D10-D6 | E20: =E10-E6 | F20: =F10-F6 | G20: =G10-G6 | H20: =H10-H6 | I20: =I10-I6 | ... AW20: =AW10-AW6 | AY20: 1.5 | AZ20: 8 | BB20: GBP CAD | BC20: =AL28 | BD20: -8 | BE20: {=_xlfn.XLOOKUP(MIN(ABS($AY$6:$AY$22 - MEDIAN(-2, 2, BC20))), ABS($AY$6:$AY$22 - MEDIAN(-2, 2, BC20)), $AZ$6:$AZ$22, "Error", 0)} | BF20: 0.015 | BG20: 8 | BH20: =BD20-BE20
A21: EUR GBP | B21: =B10-B8 | C21: =C10-C8 | D21: =D10-D8 | E21: =E10-E8 | F21: =F10-F8 | G21: =G10-G8 | H21: =H10-H8 | I21: =I10-I8 | ... AW21: =AW10-AW8 | AY21: 1.75 | AZ21: 9 | BB21: GBP AUD | BC21: =AL29 | BD21: 8 | BE21: {=_xlfn.XLOOKUP(MIN(ABS($AY$6:$AY$22 - MEDIAN(-2, 2, BC21))), ABS($AY$6:$AY$22 - MEDIAN(-2, 2, BC21)), $AZ$6:$AZ$22, "Error", 0)} | BF21: 0.0175 | BG21: 9 | BH21: =BD21-BE21
A22: EUR CAD | B22: =B10-B4 | C22: =C10-C4 | D22: =D10-D4 | E22: =E10-E4 | F22: =F10-F4 | G22: =G10-G4 | H22: =H10-H4 | I22: =I10-I4 | ... AW22: =AW10-AW4 | AY22: 2 | AZ22: 10 | BB22: GBP NZD | BC22: =AL30 | BD22: -6 | BE22: {=_xlfn.XLOOKUP(MIN(ABS($AY$6:$AY$22 - MEDIAN(-2, 2, BC22))), ABS($AY$6:$AY$22 - MEDIAN(-2, 2, BC22)), $AZ$6:$AZ$22, "Error", 0)} | BF22: 0.02 | BG22: 10 | BH22: =BD22-BE22
A23: EUR AUD | B23: 0 | C23: 0 | D23: 0 | E23: 0 | F23: 0 | G23: 0 | H23: 0 | I23: 0 | J23: 0 | K23: 0 | L23: 0 | M23: 0 | N23: 0 | O23: 0 | P23: 0 | Q23: 0 | R23: 0 | S23: 0 | T23: 0 | U23: 0 | V23: 0 | W23: 0 | X23: 0 | Y23: 0 | Z23: 0 | AA23: 0 | AB23: 0 | AC23: =AC10-AC3 | AD23: =AD10-AD3 | AE23: =AE10-AE3 | AF23: =AF10-AF3 | AG23: =AG10-AG3 | AH23: =AH10-AH3 | AI23: =AI10-AI3 | AJ23: =AJ10-AJ3 | ... AW23: =AW10-AW3 | BB23: CHF JPY | BC23: =AL31 | BD23: 4 | BE23: {=_xlfn.XLOOKUP(MIN(ABS($AY$6:$AY$22 - MEDIAN(-2, 2, BC23))), ABS($AY$6:$AY$22 - MEDIAN(-2, 2, BC23)), $AZ$6:$AZ$22, "Error", 0)} | BH23: =BD23-BE23
A24: EUR NZD | B24: =B10-B7 | C24: =C10-C7 | D24: =D10-D7 | E24: =E10-E7 | F24: =F10-F7 | G24: =G10-G7 | H24: =H10-H7 | I24: =I10-I7 | ... AW24: =AW10-AW7 | BB24: AUD USD | BC24: =AL32 | BD24: 8 | BE24: {=_xlfn.XLOOKUP(MIN(ABS($AY$6:$AY$22 - MEDIAN(-2, 2, BC24))), ABS($AY$6:$AY$22 - MEDIAN(-2, 2, BC24)), $AZ$6:$AZ$22, "Error", 0)} | BH24: =BD24-BE24
A25: GBP USD | B25: =B8-B9 | C25: =C8-C9 | D25: =D8-D9 | E25: =E8-E9 | F25: =F8-F9 | G25: =G8-G9 | H25: =H8-H9 | I25: =I8-I9 | ... AW25: =AW8-AW9 | BB25: AUD CHF | BC25: =AL33 | BD25: 10 | BE25: {=_xlfn.XLOOKUP(MIN(ABS($AY$6:$AY$22 - MEDIAN(-2, 2, BC25))), ABS($AY$6:$AY$22 - MEDIAN(-2, 2, BC25)), $AZ$6:$AZ$22, "Error", 0)} | BH25: =BD25-BE25
A26: GBP JPY | B26: =B8-B5 | C26: =C8-C5 | D26: =D8-D5 | E26: =E8-E5 | F26: =F8-F5 | G26: =G8-G5 | H26: =H8-H5 | I26: =I8-I5 | ... AW26: =AW8-AW5 | BB26: AUD JPY | BC26: =AL34 | BD26: 10 | BE26: {=_xlfn.XLOOKUP(MIN(ABS($AY$6:$AY$22 - MEDIAN(-2, 2, BC26))), ABS($AY$6:$AY$22 - MEDIAN(-2, 2, BC26)), $AZ$6:$AZ$22, "Error", 0)} | BH26: =BD26-BE26
A27: GBP CHF | B27: =B8-B6 | C27: =C8-C6 | D27: =D8-D6 | E27: =E8-E6 | F27: =F8-F6 | G27: =G8-G6 | H27: =H8-H6 | I27: =I8-I6 | ... AW27: =AW8-AW6 | BB27: AUD NZD | BC27: =AL35 | BD27: 6 | BE27: {=_xlfn.XLOOKUP(MIN(ABS($AY$6:$AY$22 - MEDIAN(-2, 2, BC27))), ABS($AY$6:$AY$22 - MEDIAN(-2, 2, BC27)), $AZ$6:$AZ$22, "Error", 0)} | BH27: =BD27-BE27
A28: GBP CAD | B28: =B8-B4 | C28: =C8-C4 | D28: =D8-D4 | E28: =E8-E4 | F28: =F8-F4 | G28: =G8-G4 | H28: =H8-H4 | I28: =I8-I4 | ... AW28: =AW8-AW4 | BB28: AUD CAD | BC28: =AL36 | BD28: 8 | BE28: {=_xlfn.XLOOKUP(MIN(ABS($AY$6:$AY$22 - MEDIAN(-2, 2, BC28))), ABS($AY$6:$AY$22 - MEDIAN(-2, 2, BC28)), $AZ$6:$AZ$22, "Error", 0)} | BH28: =BD28-BE28
A29: GBP AUD | B29: =B8-B3 | C29: =C8-C3 | D29: =D8-D3 | E29: =E8-E3 | F29: =F8-F3 | G29: =G8-G3 | H29: =H8-H3 | I29: =I8-I3 | ... AW29: =AW8-AW3 | BB29: CAD JPY | BC29: =AL37 | BD29: -8 | BE29: {=_xlfn.XLOOKUP(MIN(ABS($AY$6:$AY$22 - MEDIAN(-2, 2, BC29))), ABS($AY$6:$AY$22 - MEDIAN(-2, 2, BC29)), $AZ$6:$AZ$22, "Error", 0)} | BH29: =BD29-BE29
A30: GBP NZD | B30: =B8-B7 | C30: =C8-C7 | D30: =D8-D7 | E30: =E8-E7 | F30: =F8-F7 | G30: =G8-G7 | H30: =H8-H7 | I30: =I8-I7 | ... AW30: =AW8-AW7 | BC30: 0.7 | BD30: -8 | BE30: {=_xlfn.XLOOKUP(MIN(ABS($AY$6:$AY$22 - MEDIAN(-2, 2, BC30))), ABS($AY$6:$AY$22 - MEDIAN(-2, 2, BC30)), $AZ$6:$AZ$22, "Error", 0)} | BH30: =BD30-BE30
A31: CHF JPY | B31: =B6-B5 | C31: =C6-C5 | D31: =D6-D5 | E31: =E6-E5 | F31: =F6-F5 | G31: =G6-G5 | H31: =H6-H5 | I31: =I6-I5 | ... AW31: =AW6-AW5 | BC31: 0.6 | BD31: -6 | BE31: {=_xlfn.XLOOKUP(MIN(ABS($AY$6:$AY$22 - MEDIAN(-2, 2, BC31))), ABS($AY$6:$AY$22 - MEDIAN(-2, 2, BC31)), $AZ$6:$AZ$22, "Error", 0)} | BH31: =BD31-BE31
A32: AUD USD | B32: =B3-B9 | C32: =C3-C9 | D32: =D3-D9 | E32: =E3-E9 | F32: =F3-F9 | G32: =G3-G9 | H32: =H3-H9 | I32: =I3-I9 | ... AW32: =AW3-AW9
A33: AUD CHF | B33: =B3-B6 | C33: =C3-C6 | D33: =D3-D6 | E33: =E3-E6 | F33: =F3-F6 | G33: =G3-G6 | H33: =H3-H6 | I33: =I3-I6 | ... AW33: =AW3-AW6
A34: AUD JPY | B34: =B3-B5 | C34: =C3-C5 | D34: =D3-D5 | E34: =E3-E5 | F34: =F3-F5 | G34: =G3-G5 | H34: =H3-H5 | I34: =I3-I5 | ... AW34: =AW3-AW5
A35: AUD NZD | B35: =B3-B7 | C35: =C3-C7 | D35: =D3-D7 | E35: =E3-E7 | F35: =F3-F7 | G35: =G3-G7 | H35: =H3-H7 | I35: =I3-I7 | ... AW35: =AW3-AW7
A36: AUD CAD | B36: =B3-B4 | C36: =C3-C4 | D36: =D3-D4 | E36: =E3-E4 | F36: =F3-F4 | G36: =G3-G4 | H36: =H3-H4 | I36: =I3-I4 | ... AW36: =AW3-AW4
A37: CAD JPY | B37: =B4-B5 | C37: =C4-C5 | D37: =D4-D5 | E37: =E4-E5 | F37: =F4-F5 | G37: =G4-G5 | H37: =H4-H5 | I37: =I4-I5 | ... AW37: =AW4-AW5
A43: Paire | B43: 44927 | C43: 44958 | D43: 44986 | E43: 45017 | F43: 45047 | G43: 45078 | H43: 45108 | I43: 45139 | J43: 45170 | K43: 45200 | L43: 45231 | M43: 45261 | N43: 45292 | O43: 45323 | P43: 45352 | Q43: 45383 | R43: 45413 | S43: 45444 | T43: 45474 | U43: 45505 | V43: 45536 | W43: 45566 | X43: 45597 | Y43: 45627 | Z43: 45658 | AA43: 45689 | AB43: 45717 | AC43: 45748 | AD43: 45778 | AE43: 45809 | AF43: 45839 | AG43: 45870 | AH43: 45901 | AI43: 45931 | AJ43: 45962 | AK43: 45992 | AL43: 46023 | AM43: 46054 | AN43: 46082 | AO43: 46113 | AP43: 46143 | AQ43: 46174 | AR43: 46204 | AS43: 46235 | AT43: 46266 | AU43: 46296 | AV43: 46327 | AW43: 46357
A44: USD JPY | B44: {=_xlfn.XLOOKUP(MIN(ABS($AY$6:$AY$22 - MEDIAN(-2, 2, B15))), ABS($AY$6:$AY$22 - MEDIAN(-2, 2, B15)), $AZ$6:$AZ$22, "Error", 0)} | C44: {=_xlfn.XLOOKUP(MIN(ABS($AY$6:$AY$22 - MEDIAN(-2, 2, C15))), ABS($AY$6:$AY$22 - MEDIAN(-2, 2, C15)), $AZ$6:$AZ$22, "Error", 0)} | D44: {=_xlfn.XLOOKUP(MIN(ABS($AY$6:$AY$22 - MEDIAN(-2, 2, D15))), ABS($AY$6:$AY$22 - MEDIAN(-2, 2, D15)), $AZ$6:$AZ$22, "Error", 0)} | E44: {=_xlfn.XLOOKUP(MIN(ABS($AY$6:$AY$22 - MEDIAN(-2, 2, E15))), ABS($AY$6:$AY$22 - MEDIAN(-2, 2, E15)), $AZ$6:$AZ$22, "Error", 0)} | F44: {=_xlfn.XLOOKUP(MIN(ABS($AY$6:$AY$22 - MEDIAN(-2, 2, F15))), ABS($AY$6:$AY$22 - MEDIAN(-2, 2, F15)), $AZ$6:$AZ$22, "Error", 0)} | G44: {=_xlfn.XLOOKUP(MIN(ABS($AY$6:$AY$22 - MEDIAN(-2, 2, G15))), ABS($AY$6:$AY$22 - MEDIAN(-2, 2, G15)), $AZ$6:$AZ$22, "Error", 0)} | H44: {=_xlfn.XLOOKUP(MIN(ABS($AY$6:$AY$22 - MEDIAN(-2, 2, H15))), ABS($AY$6:$AY$22 - MEDIAN(-2, 2, H15)), $AZ$6:$AZ$22, "Error", 0)} | I44: {=_xlfn.XLOOKUP(MIN(ABS($AY$6:$AY$22 - MEDIAN(-2, 2, I15))), ABS($AY$6:$AY$22 - MEDIAN(-2, 2, I15)), $AZ$6:$AZ$22, "Error", 0)} | ... AW44: {=_xlfn.XLOOKUP(MIN(ABS($AY$6:$AY$22 - MEDIAN(-2, 2, AW15))), ABS($AY$6:$AY$22 - MEDIAN(-2, 2, AW15)), $AZ$6:$AZ$22, "Error", 0)}
A45: USD CHF | B45: {=_xlfn.XLOOKUP(MIN(ABS($AY$6:$AY$22 - MEDIAN(-2, 2, B16))), ABS($AY$6:$AY$22 - MEDIAN(-2, 2, B16)), $AZ$6:$AZ$22, "Error", 0)} | C45: {=_xlfn.XLOOKUP(MIN(ABS($AY$6:$AY$22 - MEDIAN(-2, 2, C16))), ABS($AY$6:$AY$22 - MEDIAN(-2, 2, C16)), $AZ$6:$AZ$22, "Error", 0)} | D45: {=_xlfn.XLOOKUP(MIN(ABS($AY$6:$AY$22 - MEDIAN(-2, 2, D16))), ABS($AY$6:$AY$22 - MEDIAN(-2, 2, D16)), $AZ$6:$AZ$22, "Error", 0)} | E45: {=_xlfn.XLOOKUP(MIN(ABS($AY$6:$AY$22 - MEDIAN(-2, 2, E16))), ABS($AY$6:$AY$22 - MEDIAN(-2, 2, E16)), $AZ$6:$AZ$22, "Error", 0)} | F45: {=_xlfn.XLOOKUP(MIN(ABS($AY$6:$AY$22 - MEDIAN(-2, 2, F16))), ABS($AY$6:$AY$22 - MEDIAN(-2, 2, F16)), $AZ$6:$AZ$22, "Error", 0)} | G45: {=_xlfn.XLOOKUP(MIN(ABS($AY$6:$AY$22 - MEDIAN(-2, 2, G16))), ABS($AY$6:$AY$22 - MEDIAN(-2, 2, G16)), $AZ$6:$AZ$22, "Error", 0)} | H45: {=_xlfn.XLOOKUP(MIN(ABS($AY$6:$AY$22 - MEDIAN(-2, 2, H16))), ABS($AY$6:$AY$22 - MEDIAN(-2, 2, H16)), $AZ$6:$AZ$22, "Error", 0)} | I45: {=_xlfn.XLOOKUP(MIN(ABS($AY$6:$AY$22 - MEDIAN(-2, 2, I16))), ABS($AY$6:$AY$22 - MEDIAN(-2, 2, I16)), $AZ$6:$AZ$22, "Error", 0)} | ... AW45: {=_xlfn.XLOOKUP(MIN(ABS($AY$6:$AY$22 - MEDIAN(-2, 2, AW16))), ABS($AY$6:$AY$22 - MEDIAN(-2, 2, AW16)), $AZ$6:$AZ$22, "Error", 0)}
A46: USD CAD | B46: {=_xlfn.XLOOKUP(MIN(ABS($AY$6:$AY$22 - MEDIAN(-2, 2, B17))), ABS($AY$6:$AY$22 - MEDIAN(-2, 2, B17)), $AZ$6:$AZ$22, "Error", 0)} | C46: {=_xlfn.XLOOKUP(MIN(ABS($AY$6:$AY$22 - MEDIAN(-2, 2, C17))), ABS($AY$6:$AY$22 - MEDIAN(-2, 2, C17)), $AZ$6:$AZ$22, "Error", 0)} | D46: {=_xlfn.XLOOKUP(MIN(ABS($AY$6:$AY$22 - MEDIAN(-2, 2, D17))), ABS($AY$6:$AY$22 - MEDIAN(-2, 2, D17)), $AZ$6:$AZ$22, "Error", 0)} | E46: {=_xlfn.XLOOKUP(MIN(ABS($AY$6:$AY$22 - MEDIAN(-2, 2, E17))), ABS($AY$6:$AY$22 - MEDIAN(-2, 2, E17)), $AZ$6:$AZ$22, "Error", 0)} | F46: {=_xlfn.XLOOKUP(MIN(ABS($AY$6:$AY$22 - MEDIAN(-2, 2, F17))), ABS($AY$6:$AY$22 - MEDIAN(-2, 2, F17)), $AZ$6:$AZ$22, "Error", 0)} | G46: {=_xlfn.XLOOKUP(MIN(ABS($AY$6:$AY$22 - MEDIAN(-2, 2, G17))), ABS($AY$6:$AY$22 - MEDIAN(-2, 2, G17)), $AZ$6:$AZ$22, "Error", 0)} | H46: {=_xlfn.XLOOKUP(MIN(ABS($AY$6:$AY$22 - MEDIAN(-2, 2, H17))), ABS($AY$6:$AY$22 - MEDIAN(-2, 2, H17)), $AZ$6:$AZ$22, "Error", 0)} | I46: {=_xlfn.XLOOKUP(MIN(ABS($AY$6:$AY$22 - MEDIAN(-2, 2, I17))), ABS($AY$6:$AY$22 - MEDIAN(-2, 2, I17)), $AZ$6:$AZ$22, "Error", 0)} | ... AW46: {=_xlfn.XLOOKUP(MIN(ABS($AY$6:$AY$22 - MEDIAN(-2, 2, AW17))), ABS($AY$6:$AY$22 - MEDIAN(-2, 2, AW17)), $AZ$6:$AZ$22, "Error", 0)}
A47: EUR USD | B47: {=_xlfn.XLOOKUP(MIN(ABS($AY$6:$AY$22 - MEDIAN(-2, 2, B18))), ABS($AY$6:$AY$22 - MEDIAN(-2, 2, B18)), $AZ$6:$AZ$22, "Error", 0)} | C47: {=_xlfn.XLOOKUP(MIN(ABS($AY$6:$AY$22 - MEDIAN(-2, 2, C18))), ABS($AY$6:$AY$22 - MEDIAN(-2, 2, C18)), $AZ$6:$AZ$22, "Error", 0)} | D47: {=_xlfn.XLOOKUP(MIN(ABS($AY$6:$AY$22 - MEDIAN(-2, 2, D18))), ABS($AY$6:$AY$22 - MEDIAN(-2, 2, D18)), $AZ$6:$AZ$22, "Error", 0)} | E47: {=_xlfn.XLOOKUP(MIN(ABS($AY$6:$AY$22 - MEDIAN(-2, 2, E18))), ABS($AY$6:$AY$22 - MEDIAN(-2, 2, E18)), $AZ$6:$AZ$22, "Error", 0)} | F47: {=_xlfn.XLOOKUP(MIN(ABS($AY$6:$AY$22 - MEDIAN(-2, 2, F18))), ABS($AY$6:$AY$22 - MEDIAN(-2, 2, F18)), $AZ$6:$AZ$22, "Error", 0)} | G47: {=_xlfn.XLOOKUP(MIN(ABS($AY$6:$AY$22 - MEDIAN(-2, 2, G18))), ABS($AY$6:$AY$22 - MEDIAN(-2, 2, G18)), $AZ$6:$AZ$22, "Error", 0)} | H47: {=_xlfn.XLOOKUP(MIN(ABS($AY$6:$AY$22 - MEDIAN(-2, 2, H18))), ABS($AY$6:$AY$22 - MEDIAN(-2, 2, H18)), $AZ$6:$AZ$22, "Error", 0)} | I47: {=_xlfn.XLOOKUP(MIN(ABS($AY$6:$AY$22 - MEDIAN(-2, 2, I18))), ABS($AY$6:$AY$22 - MEDIAN(-2, 2, I18)), $AZ$6:$AZ$22, "Error", 0)} | ... AW47: {=_xlfn.XLOOKUP(MIN(ABS($AY$6:$AY$22 - MEDIAN(-2, 2, AW18))), ABS($AY$6:$AY$22 - MEDIAN(-2, 2, AW18)), $AZ$6:$AZ$22, "Error", 0)}
A48: EUR JPY | B48: {=_xlfn.XLOOKUP(MIN(ABS($AY$6:$AY$22 - MEDIAN(-2, 2, B19))), ABS($AY$6:$AY$22 - MEDIAN(-2, 2, B19)), $AZ$6:$AZ$22, "Error", 0)} | C48: {=_xlfn.XLOOKUP(MIN(ABS($AY$6:$AY$22 - MEDIAN(-2, 2, C19))), ABS($AY$6:$AY$22 - MEDIAN(-2, 2, C19)), $AZ$6:$AZ$22, "Error", 0)} | D48: {=_xlfn.XLOOKUP(MIN(ABS($AY$6:$AY$22 - MEDIAN(-2, 2, D19))), ABS($AY$6:$AY$22 - MEDIAN(-2, 2, D19)), $AZ$6:$AZ$22, "Error", 0)} | E48: {=_xlfn.XLOOKUP(MIN(ABS($AY$6:$AY$22 - MEDIAN(-2, 2, E19))), ABS($AY$6:$AY$22 - MEDIAN(-2, 2, E19)), $AZ$6:$AZ$22, "Error", 0)} | F48: {=_xlfn.XLOOKUP(MIN(ABS($AY$6:$AY$22 - MEDIAN(-2, 2, F19))), ABS($AY$6:$AY$22 - MEDIAN(-2, 2, F19)), $AZ$6:$AZ$22, "Error", 0)} | G48: {=_xlfn.XLOOKUP(MIN(ABS($AY$6:$AY$22 - MEDIAN(-2, 2, G19))), ABS($AY$6:$AY$22 - MEDIAN(-2, 2, G19)), $AZ$6:$AZ$22, "Error", 0)} | H48: {=_xlfn.XLOOKUP(MIN(ABS($AY$6:$AY$22 - MEDIAN(-2, 2, H19))), ABS($AY$6:$AY$22 - MEDIAN(-2, 2, H19)), $AZ$6:$AZ$22, "Error", 0)} | I48: {=_xlfn.XLOOKUP(MIN(ABS($AY$6:$AY$22 - MEDIAN(-2, 2, I19))), ABS($AY$6:$AY$22 - MEDIAN(-2, 2, I19)), $AZ$6:$AZ$22, "Error", 0)} | ... AW48: {=_xlfn.XLOOKUP(MIN(ABS($AY$6:$AY$22 - MEDIAN(-2, 2, AW19))), ABS($AY$6:$AY$22 - MEDIAN(-2, 2, AW19)), $AZ$6:$AZ$22, "Error", 0)}
A49: EUR CHF | B49: {=_xlfn.XLOOKUP(MIN(ABS($AY$6:$AY$22 - MEDIAN(-2, 2, B20))), ABS($AY$6:$AY$22 - MEDIAN(-2, 2, B20)), $AZ$6:$AZ$22, "Error", 0)} | C49: {=_xlfn.XLOOKUP(MIN(ABS($AY$6:$AY$22 - MEDIAN(-2, 2, C20))), ABS($AY$6:$AY$22 - MEDIAN(-2, 2, C20)), $AZ$6:$AZ$22, "Error", 0)} | D49: {=_xlfn.XLOOKUP(MIN(ABS($AY$6:$AY$22 - MEDIAN(-2, 2, D20))), ABS($AY$6:$AY$22 - MEDIAN(-2, 2, D20)), $AZ$6:$AZ$22, "Error", 0)} | E49: {=_xlfn.XLOOKUP(MIN(ABS($AY$6:$AY$22 - MEDIAN(-2, 2, E20))), ABS($AY$6:$AY$22 - MEDIAN(-2, 2, E20)), $AZ$6:$AZ$22, "Error", 0)} | F49: {=_xlfn.XLOOKUP(MIN(ABS($AY$6:$AY$22 - MEDIAN(-2, 2, F20))), ABS($AY$6:$AY$22 - MEDIAN(-2, 2, F20)), $AZ$6:$AZ$22, "Error", 0)} | G49: {=_xlfn.XLOOKUP(MIN(ABS($AY$6:$AY$22 - MEDIAN(-2, 2, G20))), ABS($AY$6:$AY$22 - MEDIAN(-2, 2, G20)), $AZ$6:$AZ$22, "Error", 0)} | H49: {=_xlfn.XLOOKUP(MIN(ABS($AY$6:$AY$22 - MEDIAN(-2, 2, H20))), ABS($AY$6:$AY$22 - MEDIAN(-2, 2, H20)), $AZ$6:$AZ$22, "Error", 0)} | I49: {=_xlfn.XLOOKUP(MIN(ABS($AY$6:$AY$22 - MEDIAN(-2, 2, I20))), ABS($AY$6:$AY$22 - MEDIAN(-2, 2, I20)), $AZ$6:$AZ$22, "Error", 0)} | ... AW49: {=_xlfn.XLOOKUP(MIN(ABS($AY$6:$AY$22 - MEDIAN(-2, 2, AW20))), ABS($AY$6:$AY$22 - MEDIAN(-2, 2, AW20)), $AZ$6:$AZ$22, "Error", 0)}
A50: EUR GBP | B50: {=_xlfn.XLOOKUP(MIN(ABS($AY$6:$AY$22 - MEDIAN(-2, 2, B21))), ABS($AY$6:$AY$22 - MEDIAN(-2, 2, B21)), $AZ$6:$AZ$22, "Error", 0)} | C50: {=_xlfn.XLOOKUP(MIN(ABS($AY$6:$AY$22 - MEDIAN(-2, 2, C21))), ABS($AY$6:$AY$22 - MEDIAN(-2, 2, C21)), $AZ$6:$AZ$22, "Error", 0)} | D50: {=_xlfn.XLOOKUP(MIN(ABS($AY$6:$AY$22 - MEDIAN(-2, 2, D21))), ABS($AY$6:$AY$22 - MEDIAN(-2, 2, D21)), $AZ$6:$AZ$22, "Error", 0)} | E50: {=_xlfn.XLOOKUP(MIN(ABS($AY$6:$AY$22 - MEDIAN(-2, 2, E21))), ABS($AY$6:$AY$22 - MEDIAN(-2, 2, E21)), $AZ$6:$AZ$22, "Error", 0)} | F50: {=_xlfn.XLOOKUP(MIN(ABS($AY$6:$AY$22 - MEDIAN(-2, 2, F21))), ABS($AY$6:$AY$22 - MEDIAN(-2, 2, F21)), $AZ$6:$AZ$22, "Error", 0)} | G50: {=_xlfn.XLOOKUP(MIN(ABS($AY$6:$AY$22 - MEDIAN(-2, 2, G21))), ABS($AY$6:$AY$22 - MEDIAN(-2, 2, G21)), $AZ$6:$AZ$22, "Error", 0)} | H50: {=_xlfn.XLOOKUP(MIN(ABS($AY$6:$AY$22 - MEDIAN(-2, 2, H21))), ABS($AY$6:$AY$22 - MEDIAN(-2, 2, H21)), $AZ$6:$AZ$22, "Error", 0)} | I50: {=_xlfn.XLOOKUP(MIN(ABS($AY$6:$AY$22 - MEDIAN(-2, 2, I21))), ABS($AY$6:$AY$22 - MEDIAN(-2, 2, I21)), $AZ$6:$AZ$22, "Error", 0)} | ... AW50: {=_xlfn.XLOOKUP(MIN(ABS($AY$6:$AY$22 - MEDIAN(-2, 2, AW21))), ABS($AY$6:$AY$22 - MEDIAN(-2, 2, AW21)), $AZ$6:$AZ$22, "Error", 0)}
A51: EUR CAD | B51: {=_xlfn.XLOOKUP(MIN(ABS($AY$6:$AY$22 - MEDIAN(-2, 2, B22))), ABS($AY$6:$AY$22 - MEDIAN(-2, 2, B22)), $AZ$6:$AZ$22, "Error", 0)} | C51: {=_xlfn.XLOOKUP(MIN(ABS($AY$6:$AY$22 - MEDIAN(-2, 2, C22))), ABS($AY$6:$AY$22 - MEDIAN(-2, 2, C22)), $AZ$6:$AZ$22, "Error", 0)} | D51: {=_xlfn.XLOOKUP(MIN(ABS($AY$6:$AY$22 - MEDIAN(-2, 2, D22))), ABS($AY$6:$AY$22 - MEDIAN(-2, 2, D22)), $AZ$6:$AZ$22, "Error", 0)} | E51: {=_xlfn.XLOOKUP(MIN(ABS($AY$6:$AY$22 - MEDIAN(-2, 2, E22))), ABS($AY$6:$AY$22 - MEDIAN(-2, 2, E22)), $AZ$6:$AZ$22, "Error", 0)} | F51: {=_xlfn.XLOOKUP(MIN(ABS($AY$6:$AY$22 - MEDIAN(-2, 2, F22))), ABS($AY$6:$AY$22 - MEDIAN(-2, 2, F22)), $AZ$6:$AZ$22, "Error", 0)} | G51: {=_xlfn.XLOOKUP(MIN(ABS($AY$6:$AY$22 - MEDIAN(-2, 2, G22))), ABS($AY$6:$AY$22 - MEDIAN(-2, 2, G22)), $AZ$6:$AZ$22, "Error", 0)} | H51: {=_xlfn.XLOOKUP(MIN(ABS($AY$6:$AY$22 - MEDIAN(-2, 2, H22))), ABS($AY$6:$AY$22 - MEDIAN(-2, 2, H22)), $AZ$6:$AZ$22, "Error", 0)} | I51: {=_xlfn.XLOOKUP(MIN(ABS($AY$6:$AY$22 - MEDIAN(-2, 2, I22))), ABS($AY$6:$AY$22 - MEDIAN(-2, 2, I22)), $AZ$6:$AZ$22, "Error", 0)} | ... AW51: {=_xlfn.XLOOKUP(MIN(ABS($AY$6:$AY$22 - MEDIAN(-2, 2, AW22))), ABS($AY$6:$AY$22 - MEDIAN(-2, 2, AW22)), $AZ$6:$AZ$22, "Error", 0)}
A52: EUR AUD | B52: {=_xlfn.XLOOKUP(MIN(ABS($AY$6:$AY$22 - MEDIAN(-2, 2, B23))), ABS($AY$6:$AY$22 - MEDIAN(-2, 2, B23)), $AZ$6:$AZ$22, "Error", 0)} | C52: {=_xlfn.XLOOKUP(MIN(ABS($AY$6:$AY$22 - MEDIAN(-2, 2, C23))), ABS($AY$6:$AY$22 - MEDIAN(-2, 2, C23)), $AZ$6:$AZ$22, "Error", 0)} | D52: {=_xlfn.XLOOKUP(MIN(ABS($AY$6:$AY$22 - MEDIAN(-2, 2, D23))), ABS($AY$6:$AY$22 - MEDIAN(-2, 2, D23)), $AZ$6:$AZ$22, "Error", 0)} | E52: {=_xlfn.XLOOKUP(MIN(ABS($AY$6:$AY$22 - MEDIAN(-2, 2, E23))), ABS($AY$6:$AY$22 - MEDIAN(-2, 2, E23)), $AZ$6:$AZ$22, "Error", 0)} | F52: {=_xlfn.XLOOKUP(MIN(ABS($AY$6:$AY$22 - MEDIAN(-2, 2, F23))), ABS($AY$6:$AY$22 - MEDIAN(-2, 2, F23)), $AZ$6:$AZ$22, "Error", 0)} | G52: {=_xlfn.XLOOKUP(MIN(ABS($AY$6:$AY$22 - MEDIAN(-2, 2, G23))), ABS($AY$6:$AY$22 - MEDIAN(-2, 2, G23)), $AZ$6:$AZ$22, "Error", 0)} | H52: {=_xlfn.XLOOKUP(MIN(ABS($AY$6:$AY$22 - MEDIAN(-2, 2, H23))), ABS($AY$6:$AY$22 - MEDIAN(-2, 2, H23)), $AZ$6:$AZ$22, "Error", 0)} | I52: {=_xlfn.XLOOKUP(MIN(ABS($AY$6:$AY$22 - MEDIAN(-2, 2, I23))), ABS($AY$6:$AY$22 - MEDIAN(-2, 2, I23)), $AZ$6:$AZ$22, "Error", 0)} | ... AW52: {=_xlfn.XLOOKUP(MIN(ABS($AY$6:$AY$22 - MEDIAN(-2, 2, AW23))), ABS($AY$6:$AY$22 - MEDIAN(-2, 2, AW23)), $AZ$6:$AZ$22, "Error", 0)}
A53: EUR NZD | B53: {=_xlfn.XLOOKUP(MIN(ABS($AY$6:$AY$22 - MEDIAN(-2, 2, B24))), ABS($AY$6:$AY$22 - MEDIAN(-2, 2, B24)), $AZ$6:$AZ$22, "Error", 0)} | C53: {=_xlfn.XLOOKUP(MIN(ABS($AY$6:$AY$22 - MEDIAN(-2, 2, C24))), ABS($AY$6:$AY$22 - MEDIAN(-2, 2, C24)), $AZ$6:$AZ$22, "Error", 0)} | D53: {=_xlfn.XLOOKUP(MIN(ABS($AY$6:$AY$22 - MEDIAN(-2, 2, D24))), ABS($AY$6:$AY$22 - MEDIAN(-2, 2, D24)), $AZ$6:$AZ$22, "Error", 0)} | E53: {=_xlfn.XLOOKUP(MIN(ABS($AY$6:$AY$22 - MEDIAN(-2, 2, E24))), ABS($AY$6:$AY$22 - MEDIAN(-2, 2, E24)), $AZ$6:$AZ$22, "Error", 0)} | F53: {=_xlfn.XLOOKUP(MIN(ABS($AY$6:$AY$22 - MEDIAN(-2, 2, F24))), ABS($AY$6:$AY$22 - MEDIAN(-2, 2, F24)), $AZ$6:$AZ$22, "Error", 0)} | G53: {=_xlfn.XLOOKUP(MIN(ABS($AY$6:$AY$22 - MEDIAN(-2, 2, G24))), ABS($AY$6:$AY$22 - MEDIAN(-2, 2, G24)), $AZ$6:$AZ$22, "Error", 0)} | H53: {=_xlfn.XLOOKUP(MIN(ABS($AY$6:$AY$22 - MEDIAN(-2, 2, H24))), ABS($AY$6:$AY$22 - MEDIAN(-2, 2, H24)), $AZ$6:$AZ$22, "Error", 0)} | I53: {=_xlfn.XLOOKUP(MIN(ABS($AY$6:$AY$22 - MEDIAN(-2, 2, I24))), ABS($AY$6:$AY$22 - MEDIAN(-2, 2, I24)), $AZ$6:$AZ$22, "Error", 0)} | ... AW53: {=_xlfn.XLOOKUP(MIN(ABS($AY$6:$AY$22 - MEDIAN(-2, 2, AW24))), ABS($AY$6:$AY$22 - MEDIAN(-2, 2, AW24)), $AZ$6:$AZ$22, "Error", 0)}
A54: GBP USD | B54: {=_xlfn.XLOOKUP(MIN(ABS($AY$6:$AY$22 - MEDIAN(-2, 2, B25))), ABS($AY$6:$AY$22 - MEDIAN(-2, 2, B25)), $AZ$6:$AZ$22, "Error", 0)} | C54: {=_xlfn.XLOOKUP(MIN(ABS($AY$6:$AY$22 - MEDIAN(-2, 2, C25))), ABS($AY$6:$AY$22 - MEDIAN(-2, 2, C25)), $AZ$6:$AZ$22, "Error", 0)} | D54: {=_xlfn.XLOOKUP(MIN(ABS($AY$6:$AY$22 - MEDIAN(-2, 2, D25))), ABS($AY$6:$AY$22 - MEDIAN(-2, 2, D25)), $AZ$6:$AZ$22, "Error", 0)} | E54: {=_xlfn.XLOOKUP(MIN(ABS($AY$6:$AY$22 - MEDIAN(-2, 2, E25))), ABS($AY$6:$AY$22 - MEDIAN(-2, 2, E25)), $AZ$6:$AZ$22, "Error", 0)} | F54: {=_xlfn.XLOOKUP(MIN(ABS($AY$6:$AY$22 - MEDIAN(-2, 2, F25))), ABS($AY$6:$AY$22 - MEDIAN(-2, 2, F25)), $AZ$6:$AZ$22, "Error", 0)} | G54: {=_xlfn.XLOOKUP(MIN(ABS($AY$6:$AY$22 - MEDIAN(-2, 2, G25))), ABS($AY$6:$AY$22 - MEDIAN(-2, 2, G25)), $AZ$6:$AZ$22, "Error", 0)} | H54: {=_xlfn.XLOOKUP(MIN(ABS($AY$6:$AY$22 - MEDIAN(-2, 2, H25))), ABS($AY$6:$AY$22 - MEDIAN(-2, 2, H25)), $AZ$6:$AZ$22, "Error", 0)} | I54: {=_xlfn.XLOOKUP(MIN(ABS($AY$6:$AY$22 - MEDIAN(-2, 2, I25))), ABS($AY$6:$AY$22 - MEDIAN(-2, 2, I25)), $AZ$6:$AZ$22, "Error", 0)} | ... AW54: {=_xlfn.XLOOKUP(MIN(ABS($AY$6:$AY$22 - MEDIAN(-2, 2, AW25))), ABS($AY$6:$AY$22 - MEDIAN(-2, 2, AW25)), $AZ$6:$AZ$22, "Error", 0)}
A55: GBP JPY | B55: {=_xlfn.XLOOKUP(MIN(ABS($AY$6:$AY$22 - MEDIAN(-2, 2, B26))), ABS($AY$6:$AY$22 - MEDIAN(-2, 2, B26)), $AZ$6:$AZ$22, "Error", 0)} | C55: {=_xlfn.XLOOKUP(MIN(ABS($AY$6:$AY$22 - MEDIAN(-2, 2, C26))), ABS($AY$6:$AY$22 - MEDIAN(-2, 2, C26)), $AZ$6:$AZ$22, "Error", 0)} | D55: {=_xlfn.XLOOKUP(MIN(ABS($AY$6:$AY$22 - MEDIAN(-2, 2, D26))), ABS($AY$6:$AY$22 - MEDIAN(-2, 2, D26)), $AZ$6:$AZ$22, "Error", 0)} | E55: {=_xlfn.XLOOKUP(MIN(ABS($AY$6:$AY$22 - MEDIAN(-2, 2, E26))), ABS($AY$6:$AY$22 - MEDIAN(-2, 2, E26)), $AZ$6:$AZ$22, "Error", 0)} | F55: {=_xlfn.XLOOKUP(MIN(ABS($AY$6:$AY$22 - MEDIAN(-2, 2, F26))), ABS($AY$6:$AY$22 - MEDIAN(-2, 2, F26)), $AZ$6:$AZ$22, "Error", 0)} | G55: {=_xlfn.XLOOKUP(MIN(ABS($AY$6:$AY$22 - MEDIAN(-2, 2, G26))), ABS($AY$6:$AY$22 - MEDIAN(-2, 2, G26)), $AZ$6:$AZ$22, "Error", 0)} | H55: {=_xlfn.XLOOKUP(MIN(ABS($AY$6:$AY$22 - MEDIAN(-2, 2, H26))), ABS($AY$6:$AY$22 - MEDIAN(-2, 2, H26)), $AZ$6:$AZ$22, "Error", 0)} | I55: {=_xlfn.XLOOKUP(MIN(ABS($AY$6:$AY$22 - MEDIAN(-2, 2, I26))), ABS($AY$6:$AY$22 - MEDIAN(-2, 2, I26)), $AZ$6:$AZ$22, "Error", 0)} | ... AW55: {=_xlfn.XLOOKUP(MIN(ABS($AY$6:$AY$22 - MEDIAN(-2, 2, AW26))), ABS($AY$6:$AY$22 - MEDIAN(-2, 2, AW26)), $AZ$6:$AZ$22, "Error", 0)}
... A66: CAD JPY | B66: {=_xlfn.XLOOKUP(MIN(ABS($AY$6:$AY$22 - MEDIAN(-2, 2, B37))), ABS($AY$6:$AY$22 - MEDIAN(-2, 2, B37)), $AZ$6:$AZ$22, "Error", 0)} | C66: {=_xlfn.XLOOKUP(MIN(ABS($AY$6:$AY$22 - MEDIAN(-2, 2, C37))), ABS($AY$6:$AY$22 - MEDIAN(-2, 2, C37)), $AZ$6:$AZ$22, "Error", 0)} | D66: {=_xlfn.XLOOKUP(MIN(ABS($AY$6:$AY$22 - MEDIAN(-2, 2, D37))), ABS($AY$6:$AY$22 - MEDIAN(-2, 2, D37)), $AZ$6:$AZ$22, "Error", 0)} | E66: {=_xlfn.XLOOKUP(MIN(ABS($AY$6:$AY$22 - MEDIAN(-2, 2, E37))), ABS($AY$6:$AY$22 - MEDIAN(-2, 2, E37)), $AZ$6:$AZ$22, "Error", 0)} | F66: {=_xlfn.XLOOKUP(MIN(ABS($AY$6:$AY$22 - MEDIAN(-2, 2, F37))), ABS($AY$6:$AY$22 - MEDIAN(-2, 2, F37)), $AZ$6:$AZ$22, "Error", 0)} | G66: {=_xlfn.XLOOKUP(MIN(ABS($AY$6:$AY$22 - MEDIAN(-2, 2, G37))), ABS($AY$6:$AY$22 - MEDIAN(-2, 2, G37)), $AZ$6:$AZ$22, "Error", 0)} | H66: {=_xlfn.XLOOKUP(MIN(ABS($AY$6:$AY$22 - MEDIAN(-2, 2, H37))), ABS($AY$6:$AY$22 - MEDIAN(-2, 2, H37)), $AZ$6:$AZ$22, "Error", 0)} | I66: {=_xlfn.XLOOKUP(MIN(ABS($AY$6:$AY$22 - MEDIAN(-2, 2, I37))), ABS($AY$6:$AY$22 - MEDIAN(-2, 2, I37)), $AZ$6:$AZ$22, "Error", 0)} | ... AW66: {=_xlfn.XLOOKUP(MIN(ABS($AY$6:$AY$22 - MEDIAN(-2, 2, AW37))), ABS($AY$6:$AY$22 - MEDIAN(-2, 2, AW37)), $AZ$6:$AZ$22, "Error", 0)}
B69: -2 | C69: 2 | F69: 0.25 | G69: -4
B70: -1.75 | C70: 3 | F70: 0.5 | G70: -6
B71: -1.5 | C71: 4 | F71: 0.75 | G71: -8
B72: -1.25 | C72: 6 | F72: 1 | G72: -10
B73: -1 | C73: 10 | D73: 0 | E73: 0 | F73: 1.25 | G73: 6
B74: -0.75 | C74: 8 | F74: 1.5 | G74: 8
B75: -0.5 | C75: 6 | F75: 1.75 | G75: 9
B76: -0.25 | C76: 4 | F76: 2 | G76: 10

Sheet FX RESERVE DATA
A2: BOP | B2: 44562 | C2: 44593 | D2: 44621 | E2: 44652 | F2: 44682 | G2: 44713 | H2: 44743 | I2: 44774 | J2: 44805 | K2: 44835 | L2: 44866 | M2: 44896 | N2: 44927 | O2: 44958 | P2: 44986 | Q2: 45017 | R2: 45047 | S2: 45078 | T2: 45108 | U2: 45139 | V2: 45170 | W2: 45200 | X2: 45231 | Y2: 45261 | Z2: 45292 | AA2: 45323 | AB2: 45352 | AC2: 45383 | AD2: 45413 | AE2: 45444 | AF2: 45474 | AG2: 45505 | AH2: 45536 | AI2: 45566 | AJ2: 45597 | AK2: 45627 | AL2: 45658 | AM2: 45689 | AN2: 45717 | AO2: 45748 | AP2: 45778 | AQ2: 45809 | AR2: 45839 | AS2: 45870 | AT2: 45901 | AU2: 45931 | AV2: 45962 | AW2: 45992 | AX2: 46023 | AY2: 46054 | AZ2: 46082 | BA2: 46113 | BB2: 46143 | BC2: 46174 | BD2: 46204 | BE2: 46235 | BF2: 46266 | BG2: 46296 | BH2: 46327 | BI2: 46357
A3: Australia | B3: 35902 | C3: 36120 | D3: 36276 | E3: 34607 | F3: 35095 | G3: 34447 | H3: 35634 | I3: 35922 | J3: 35037 | K3: 36113 | L3: 39040 | M3: 38480 | N3: 38149 | O3: 35320 | P3: 36375 | Q3: 38679 | R3: 36115 | S3: 36911 | T3: 38215 | U3: 38434 | V3: 35744 | W3: 35888 | X3: 38009 | Y3: 40897 | Z3: 35026 | AA3: 35126 | AB3: 34212 | AC3: 33803 | AD3: 35618 | AE3: 37644 | AF3: 36729 | AG3: 40610 | AH3: 39957 | AI3: 39030 | AJ3: 39287 | AK3: 39576 | AL3: 40770 | AM3: 41970 | AN3: 41098 | AO3: 39891 | AP3: 41757 | AQ3: 39970 | AR3: 39476 | AS3: 40717 | AT3: 42175 | AU3: 41482 | AV3: 42782 | AW3: 44962 | AX3: 40964 | AY3: 42106 | AZ3: 41982 | BA3: 41544 | BB3: 40705 | BC3: 41187 | BD3: 46150 | BE3: 46150 | BF3: 46150 | BK3: -2000 | BL3: 10
A4: Canada | B4: 76095 | C4: 74519 | D4: 75387 | E4: 78056 | F4: 80218 | G4: 79017 | H4: 79458 | I4: 80964 | J4: 76411 | K4: 77353 | L4: 79282 | M4: 79729 | N4: 82059 | O4: 80984 | P4: 81835 | Q4: 86299 | R4: 86006 | S4: 86474 | T4: 86488 | U4: 86550 | V4: 84626 | W4: 85070 | X4: 87525 | Y4: 89914 | Z4: 88305 | AA4: 88288 | AB4: 89875 | AC4: 93627 | AD4: 95171 | AE4: 94963 | AF4: 95929 | AG4: 97153 | AH4: 99088 | AI4: 94663 | AJ4: 94505 | AK4: 93879 | AL4: 90209 | AM4: 91801 | AN4: 97780 | AO4: 95814 | AP4: 96089 | AQ4: 98529 | AR4: 97607 | AS4: 98412 | AT4: 97141 | AU4: 99676 | AV4: 98608 | AW4: 98396 | AX4: 98880 | AY4: 98087 | AZ4: 97132 | BA4: 96496 | BB4: 96721 | BC4: 96543 | BD4: 96979 | BE4: 97000 | BF4: 97000 | BK4: -1800 | BL4: 9
A5: Japan | B5: 1264244 | C5: 1259159 | D5: 1230520 | E5: 1199561 | F5: 1208699 | G5: 1192911 | H5: 1206630 | I5: 1176896 | J5: 1125304 | K5: 1082452 | L5: 1109364 | M5: 1108189 | N5: 1126868 | O5: 1106343 | P5: 1134005 | Q5: 1142230 | R5: 1132162 | S5: 1126104 | T5: 1130301 | U5: 1132621 | V5: 1120048 | W5: 1117193 | X5: 1146719 | Y5: 1170437 | Z5: 1169506 | AA5: 1158491 | AB5: 1163521 | AC5: 1149316 | AD5: 1100113 | AE5: 1100691 | AF5: 1084573 | AG5: 1097528 | AH5: 1112931 | AI5: 1095601 | AJ5: 1099052 | AK5: 1092306 | AL5: 1096788 | AM5: 1108410 | AN5: 1118981 | AO5: 1136746 | AP5: 1137098 | AQ5: 1151692 | AR5: 1143537 | AS5: 1158765 | AT5: 1165059 | AU5: 1166724 | AV5: 1173675 | AW5: 1180501 | AX5: 1186456 | AY5: 1196112 | AZ5: 1177804 | BA5: 1185242 | BB5: 1109822 | BC5: 1106270 | BD5: 1105474 | BE5: 1105474 | BF5: 1105474 | BK5: -1600 | BL5: 8
A6: Switzerland | B6: 1017415.3 | C6: 1021205.1 | D6: 985078.61 | E6: 953465.07 | F6: 964651.06 | G6: 887448.48 | H6: 887071.83 | I6: 877562.25 | J6: 822339.5 | K6: 814555.69 | L6: 832856.42 | M6: 848509.64 | N6: 850924.63 | O6: 822856.41 | P6: 813080.99 | Q6: 819722.55 | R6: 805716.7 | S6: 808190.39 | T6: 803228.9 | U6: 785734.47 | V6: 741365.63 | W6: 724518.23 | X6: 733629.27 | Y6: 779970.87 | Z6: 773682.26 | AA6: 771212.31 | AB6: 793167.83 | AC6: 787294.66 | AD6: 795406.01 | AE6: 791623.08 | AF6: 801978.47 | AG6: 816745.33 | AH6: 847502.5 | AI6: 831453.68 | AJ6: 822005.26 | AK6: 808024.55 | AL6: 809259.31 | AM6: 814973.06 | AN6: 822339.5 | AO6: 854313.96 | AP6: 854058.97 | AQ6: 894234.6 | AR6: 880000.59 | AS6: 892783.55 | AT6: 911657.16 | AU6: 902110.07 | AV6: 903578.55 | AW6: 914657.72 | AX6: 926074.95 | AY6: 923641.88 | AZ6: 901037.53 | BA6: 912992.02 | BB6: 909891 | BC6: 938060 | BD6: 921227 | BE6: 921227 | BF6: 921227 | BK6: -1400 | BL6: 7
A7: New Zealand | B7: 11132 | C7: 11012 | D7: 12794 | E7: 8547 | F7: 11076 | G7: 9127 | H7: 10034 | I7: 8685 | J7: 8231 | K7: 6716 | L7: 11377 | M7: 11061 | N7: 11419 | O7: 13462 | P7: 11364 | Q7: 12534 | R7: 12544 | S7: 9934 | T7: 13615 | U7: 12940 | V7: 13708 | W7: 12577 | X7: 15987 | Y7: 12113 | Z7: 14893 | AA7: 15975 | AB7: 12891 | AC7: 15712 | AD7: 14660 | AE7: 14485 | AF7: 17689 | AG7: 17055 | AH7: 17316 | AI7: 20275 | AJ7: 19174 | AK7: 18836 | AL7: 23379 | AM7: 24951 | AN7: 22603 | AO7: 23387 | AP7: 24600 | AQ7: 24320 | AR7: 25170 | AS7: 24884 | AT7: 24006 | AU7: 24202 | AV7: 28622 | AW7: 24781 | AX7: 27581 | AY7: 25799 | AZ7: 31400 | BA7: 27963 | BB7: 29365 | BC7: 26165 | BD7: 30563 | BE7: 30563 | BF7: 30563 | BK7: -1200 | BL7: 6
A8: United Kingdom | B8: 120411.92 | C8: 120532.75 | D8: 123104.96 | E8: 115053.03 | F8: 112608.82 | G8: 110336.99 | H8: 108203.65 | I8: 107780.62 | J8: 97646.819 | K8: 101927.45 | L8: 108268.35 | M8: 110285.51 | N8: 108424.78 | O8: 102781.8 | P8: 105046.47 | Q8: 107719.01 | R8: 104068.46 | S8: 106042.77 | T8: 110108.85 | U8: 109175.59 | V8: 103971.13 | W8: 103736.91 | X8: 106107.64 | Y8: 108765.24 | Z8: 105698.52 | AA8: 104694.58 | AB8: 105493.85 | AC8: 100104.93 | AD8: 103539.63 | AE8: 102150.43 | AF8: 106238.07 | AG8: 107970.45 | AH8: 106798.85 | AI8: 104268.48 | AJ8: 104730.56 | AK8: 102683.2 | AL8: 102719.52 | AM8: 104175.92 | AN8: 106345.15 | AO8: 111229.13 | AP8: 112666.82 | AQ8: 116903.29 | AR8: 115962.86 | AS8: 118608.23 | AT8: 122086.56 | AU8: 121043.62 | AV8: 123015.11 | AW8: 123790.23 | AX8: 123927.95 | AY8: 126625.3 | AZ8: 126449.82 | BA8: 122681.06 | BB8: 125316 | BC8: 125035 | BD8: 124927 | BE8: 124927 | BF8: 124927 | BK8: -1000 | BL8: 5
A9: United States | B9: 40353.171 | C9: 40387.912 | D9: 39252.167 | E9: 37053.645 | F9: 37610.21 | G9: 36273.389 | H9: 35946.732 | I9: 35098.677 | J9: 33935.231 | K9: 33821.296 | L9: 35619.669 | M9: 37208.746 | N9: 37755.474 | O9: 36604.928 | P9: 37565.901 | Q9: 37627.61 | R9: 36459.008 | S9: 36643.742 | T9: 37113.847 | U9: 36448.63 | V9: 35613.44 | W9: 35213.519 | X9: 36302.629 | Y9: 37316.475 | Z9: 36438.875 | AA9: 36076.821 | AB9: 35990.22 | AC9: 35315.933 | AD9: 35757.623 | AE9: 35242.83 | AF9: 36357.415 | AG9: 37318.045 | AH9: 37804.752 | AI9: 36337.084 | AJ9: 35805.154 | AK9: 34865.011 | AL9: 35207.948 | AM9: 35597.682 | AN9: 36586.626 | AO9: 38564.764 | AP9: 38470.276 | AQ9: 39471.181 | AR9: 38203.046 | AS9: 39161.137 | AT9: 39204.554 | AU9: 38314.056 | AV9: 38330 | AW9: 38641 | AX9: 39222.229 | AY9: 38992.34 | AZ9: 38121 | BA9: 38121 | BB9: 39000 | BC9: 38591 | BD9: 38992 | BE9: 38992 | BF9: 38992 | BK9: -800 | BL9: 4
A10: EURO AREA | B10: 312546 | C10: 313471 | D10: 309506 | E10: 305206 | F10: 307840 | G10: 305918 | H10: 308938 | I10: 306005 | J10: 303179 | K10: 304221 | L10: 309061 | M10: 315345 | N10: 310949 | O10: 293900 | P10: 297950 | Q10: 295116 | R10: 292792 | S10: 293016 | T10: 294678 | U10: 292405 | V10: 285245 | W10: 287457 | X10: 295267 | Y10: 301470 | Z10: 299104 | AA10: 298787 | AB10: 298344 | AC10: 295492 | AD10: 298861 | AE10: 301235 | AF10: 301245 | AG10: 300873 | AH10: 303818 | AI10: 299382 | AJ10: 300478 | AK10: 300657 | AL10: 298104 | AM10: 302136 | AN10: 304980 | AO10: 310594 | AP10: 312792 | AQ10: 316343 | AR10: 314415 | AS10: 316890 | AT10: 322760 | AU10: 322351 | AV10: 325548 | AW10: 334436 | AX10: 343000 | AY10: 343000 | AZ10: 348000 | BA10: 359000 | BB10: 352000 | BC10: 340574 | BD10: 342550 | BE10: 342550 | BF10: 342550 | BK10: -600 | BL10: 3
BK11: -400 | BL11: 2
A12: Monthly Change | BK12: -200 | BL12: 1
A13: BOP | B13: 44562 | C13: 44593 | D13: 44621 | E13: 44652 | F13: 44682 | G13: 44713 | H13: 44743 | I13: 44774 | J13: 44805 | K13: 44835 | L13: 44866 | M13: 44896 | N13: 44927 | O13: 44958 | P13: 44986 | Q13: 45017 | R13: 45047 | S13: 45078 | T13: 45108 | U13: 45139 | V13: 45170 | W13: 45200 | X13: 45231 | Y13: 45261 | Z13: 45292 | AA13: 45323 | AB13: 45352 | AC13: 45383 | AD13: 45413 | AE13: 45444 | AF13: 45474 | AG13: 45505 | AH13: 45536 | AI13: 45566 | AJ13: 45597 | AK13: 45627 | AL13: 45658 | AM13: 45689 | AN13: 45717 | AO13: 45748 | AP13: 45778 | AQ13: 45809 | AR13: 45839 | AS13: 45870 | AT13: 45901 | AU13: 45931 | AV13: 45962 | AW13: 45992 | AX13: 46023 | AY13: 46054 | AZ13: 46082 | BA13: 46113 | BB13: 46143 | BC13: 46174 | BD13: 46204 | BE13: 46235 | BF13: 46266 | BG13: 46296 | BH13: 46327 | BI13: 46357 | BK13: 0 | BL13: 0
A14: Australia | C14: =C3-B3 | D14: =D3-C3 | E14: =E3-D3 | F14: =F3-E3 | G14: =G3-F3 | H14: =H3-G3 | I14: =I3-H3 | J14: =J3-I3 | ... BI14: =BI3-BH3 | BJ14: =MAX(C14:BA14) | BK14: 200 | BL14: -1 | BM14: =MIN(C14:BA14)
A15: Canada | C15: =C4-B4 | D15: =D4-C4 | E15: =E4-D4 | F15: =F4-E4 | G15: =G4-F4 | H15: =H4-G4 | I15: =I4-H4 | J15: =J4-I4 | ... BI15: =BI4-BH4 | BJ15: =MAX(C15:BA15) | BK15: 400 | BL15: -2 | BM15: =MIN(C15:BA15)
A16: Japan | C16: =C5-B5 | D16: =D5-C5 | E16: =E5-D5 | F16: =F5-E5 | G16: =G5-F5 | H16: =H5-G5 | I16: =I5-H5 | J16: =J5-I5 | ... BI16: =BI5-BH5 | BJ16: =MAX(C16:BA16) | BK16: 600 | BL16: -3 | BM16: =MIN(C16:BA16)
A17: Switzerland | C17: =C6-B6 | D17: =D6-C6 | E17: =E6-D6 | F17: =F6-E6 | G17: =G6-F6 | H17: =H6-G6 | I17: =I6-H6 | J17: =J6-I6 | ... AW17: =AW6-AV6 | AX17: 11079.17 | AY17: 11080.17 | AZ17: 11081.17 | BA17: 11082.17 | BB17: 11083.17 | BC17: 11084.17 | BD17: 11085.17 | BE17: 11086.17 | BF17: 11087.17 | BG17: 11088.17 | BH17: 11089.17 | BI17: 11090.17 | BJ17: =MAX(C17:BA17) | BK17: 800 | BL17: -4 | BM17: =MIN(C17:BA17)
A18: New Zealand | C18: =C7-B7 | D18: =D7-C7 | E18: =E7-D7 | F18: =F7-E7 | G18: =G7-F7 | H18: =H7-G7 | I18: =I7-H7 | J18: =J7-I7 | ... BI18: =BI7-BH7 | BJ18: =MAX(C18:BA18) | BK18: 1000 | BL18: -5 | BM18: =MIN(C18:BA18)
A19: United Kingdom | C19: =C8-B8 | D19: =D8-C8 | E19: =E8-D8 | F19: =F8-E8 | G19: =G8-F8 | H19: =H8-G8 | I19: =I8-H8 | J19: =J8-I8 | ... BI19: =BI8-BH8 | BJ19: =MAX(C19:BA19) | BK19: 1200 | BL19: -6 | BM19: =MIN(C19:BA19)
A20: United States | C20: =C9-B9 | D20: =D9-C9 | E20: =E9-D9 | F20: =F9-E9 | G20: =G9-F9 | H20: =H9-G9 | I20: =I9-H9 | J20: =J9-I9 | ... BI20: =BI9-BH9 | BJ20: =MAX(C20:BA20) | BK20: 1400 | BL20: -7 | BM20: =MIN(C20:BA20)
A21: EURO AREA | C21: =C10-B10 | D21: =D10-C10 | E21: =E10-D10 | F21: =F10-E10 | G21: =G10-F10 | H21: =H10-G10 | I21: =I10-H10 | J21: =J10-I10 | ... BI21: =BI10-BH10 | BJ21: =MAX(C21:BA21) | BK21: 1600 | BL21: -8 | BM21: =MIN(C21:BA21)
BK22: 1800 | BL22: -9
A23: 12 Month Average | BK23: 2000 | BL23: -10
A24: BOP | B24: 44562 | C24: 44593 | D24: 44621 | E24: 44652 | F24: 44682 | G24: 44713 | H24: 44743 | I24: 44774 | J24: 44805 | K24: 44835 | L24: 44866 | M24: 44896 | N24: 44927 | O24: 44958 | P24: 44986 | Q24: 45017 | R24: 45047 | S24: 45078 | T24: 45108 | U24: 45139 | V24: 45170 | W24: 45200 | X24: 45231 | Y24: 45261 | Z24: 45292 | AA24: 45323 | AB24: 45352 | AC24: 45383 | AD24: 45413 | AE24: 45444 | AF24: 45474 | AG24: 45505 | AH24: 45536 | AI24: 45566 | AJ24: 45597 | AK24: 45627 | AL24: 45658 | AM24: 45689 | AN24: 45717 | AO24: 45748 | AP24: 45778 | AQ24: 45809 | AR24: 45839 | AS24: 45870 | AT24: 45901 | AU24: 45931 | AV24: 45962 | AW24: 45992 | AX24: 46023 | AY24: 46054 | AZ24: 46082 | BA24: 46113 | BB24: 46143 | BC24: 46174 | BD24: 46204 | BE24: 46235 | BF24: 46266 | BG24: 46296 | BH24: 46327 | BI24: 46357
A25: Australia | N25: =+AVERAGEA(C14:N14) | O25: =+AVERAGEA(D14:O14) | P25: =+AVERAGEA(E14:P14) | Q25: =+AVERAGEA(F14:Q14) | R25: =+AVERAGEA(G14:R14) | S25: =+AVERAGEA(H14:S14) | T25: =+AVERAGEA(I14:T14) | U25: =+AVERAGEA(J14:U14) | ... BI25: =+AVERAGEA(AX14:BI14)
A26: Canada | N26: =+AVERAGEA(C15:N15) | O26: =+AVERAGEA(D15:O15) | P26: =+AVERAGEA(E15:P15) | Q26: =+AVERAGEA(F15:Q15) | R26: =+AVERAGEA(G15:R15) | S26: =+AVERAGEA(H15:S15) | T26: =+AVERAGEA(I15:T15) | U26: =+AVERAGEA(J15:U15) | ... BI26: =+AVERAGEA(AX15:BI15)
A27: Japan | N27: =+AVERAGEA(C16:N16) | O27: =+AVERAGEA(D16:O16) | P27: =+AVERAGEA(E16:P16) | Q27: =+AVERAGEA(F16:Q16) | R27: =+AVERAGEA(G16:R16) | S27: =+AVERAGEA(H16:S16) | T27: =+AVERAGEA(I16:T16) | U27: =+AVERAGEA(J16:U16) | ... BI27: =+AVERAGEA(AX16:BI16)
A28: Switzerland | N28: =+AVERAGEA(C17:N17) | O28: =+AVERAGEA(D17:O17) | P28: =+AVERAGEA(E17:P17) | Q28: =+AVERAGEA(F17:Q17) | R28: =+AVERAGEA(G17:R17) | S28: =+AVERAGEA(H17:S17) | T28: =+AVERAGEA(I17:T17) | U28: =+AVERAGEA(J17:U17) | ... BI28: =+AVERAGEA(AX17:BI17)
A29: New Zealand | N29: =+AVERAGEA(C18:N18) | O29: =+AVERAGEA(D18:O18) | P29: =+AVERAGEA(E18:P18) | Q29: =+AVERAGEA(F18:Q18) | R29: =+AVERAGEA(G18:R18) | S29: =+AVERAGEA(H18:S18) | T29: =+AVERAGEA(I18:T18) | U29: =+AVERAGEA(J18:U18) | ... BI29: =+AVERAGEA(AX18:BI18)
A30: United Kingdom | N30: =+AVERAGEA(C19:N19) | O30: =+AVERAGEA(D19:O19) | P30: =+AVERAGEA(E19:P19) | Q30: =+AVERAGEA(F19:Q19) | R30: =+AVERAGEA(G19:R19) | S30: =+AVERAGEA(H19:S19) | T30: =+AVERAGEA(I19:T19) | U30: =+AVERAGEA(J19:U19) | ... BI30: =+AVERAGEA(AX19:BI19)
A31: United States | N31: =+AVERAGEA(C20:N20) | O31: =+AVERAGEA(D20:O20) | P31: =+AVERAGEA(E20:P20) | Q31: =+AVERAGEA(F20:Q20) | R31: =+AVERAGEA(G20:R20) | S31: =+AVERAGEA(H20:S20) | T31: =+AVERAGEA(I20:T20) | U31: =+AVERAGEA(J20:U20) | ... BI31: =+AVERAGEA(AX20:BI20)
A32: EURO AREA | N32: =+AVERAGEA(C21:N21) | O32: =+AVERAGEA(D21:O21) | P32: =+AVERAGEA(E21:P21) | Q32: =+AVERAGEA(F21:Q21) | R32: =+AVERAGEA(G21:R21) | S32: =+AVERAGEA(H21:S21) | T32: =+AVERAGEA(I21:T21) | U32: =+AVERAGEA(J21:U21) | ... BI32: =+AVERAGEA(AX21:BI21)
A35: SPREAD
A36: Paire | N36: 44927 | O36: 44958 | P36: 44986 | Q36: 45017 | R36: 45047 | S36: 45078 | T36: 45108 | U36: 45139 | V36: 45170 | W36: 45200 | X36: 45231 | Y36: 45261 | Z36: 45292 | AA36: 45323 | AB36: 45352 | AC36: 45383 | AD36: 45413 | AE36: 45444 | AF36: 45474 | AG36: 45505 | AH36: 45536 | AI36: 45566 | AJ36: 45597 | AK36: 45627 | AL36: 45658 | AM36: 45689 | AN36: 45717 | AO36: 45748 | AP36: 45778 | AQ36: 45809 | AR36: 45839 | AS36: 45870 | AT36: 45901 | AU36: 45931 | AV36: 45962 | AW36: 45992 | AX36: 46023 | AY36: 46054 | AZ36: 46082 | BA36: 46113 | BB36: 46143 | BC36: 46174 | BD36: 46204 | BE36: 46235 | BF36: 46266 | BG36: 46296 | BH36: 46327 | BI36: 46357
A37: USD JPY | N37: =N31-N27 | O37: =O31-O27 | P37: =P31-P27 | Q37: =Q31-Q27 | R37: =R31-R27 | S37: =S31-S27 | T37: =T31-T27 | U37: =U31-U27 | ... BI37: =BI31-BI27
A38: USD CHF | N38: =N31-N28 | O38: =O31-O28 | P38: =P31-P28 | Q38: =Q31-Q28 | R38: =R31-R28 | S38: =S31-S28 | T38: =T31-T28 | U38: =U31-U28 | ... BI38: =BI31-BI28
A39: USD CAD | N39: =N31-N26 | O39: =O31-O26 | P39: =P31-P26 | Q39: =Q31-Q26 | R39: =R31-R26 | S39: =S31-S26 | T39: =T31-T26 | U39: =U31-U26 | ... BI39: =BI31-BI26
A40: EUR USD | N40: =N32-N31 | O40: =O32-O31 | P40: =P32-P31 | Q40: =Q32-Q31 | R40: =R32-R31 | S40: =S32-S31 | T40: =T32-T31 | U40: =U32-U31 | ... BI40: =BI32-BI31
A41: EUR JPY | N41: =N32-N27 | O41: =O32-O27 | P41: =P32-P27 | Q41: =Q32-Q27 | R41: =R32-R27 | S41: =S32-S27 | T41: =T32-T27 | U41: =U32-U27 | ... BI41: =BI32-BI27
A42: EUR CHF | N42: =N32-N28 | O42: =O32-O28 | P42: =P32-P28 | Q42: =Q32-Q28 | R42: =R32-R28 | S42: =S32-S28 | T42: =T32-T28 | U42: =U32-U28 | ... BI42: =BI32-BI28
A43: EUR GBP | N43: =N32-N30 | O43: =O32-O30 | P43: =P32-P30 | Q43: =Q32-Q30 | R43: =R32-R30 | S43: =S32-S30 | T43: =T32-T30 | U43: =U32-U30 | ... BI43: =BI32-BI30
A44: EUR CAD | N44: =N32-N26 | O44: =O32-O26 | P44: =P32-P26 | Q44: =Q32-Q26 | R44: =R32-R26 | S44: =S32-S26 | T44: =T32-T26 | U44: =U32-U26 | ... BI44: =BI32-BI26
A45: EUR AUD | N45: 0 | O45: 0 | P45: 0 | Q45: 0 | R45: 0 | S45: 0 | T45: 0 | U45: 0 | V45: 0 | W45: 0 | X45: 0 | Y45: 0 | Z45: 0 | AA45: 0 | AB45: 0 | AC45: 0 | AD45: 0 | AE45: 0 | AF45: 0 | AG45: 0 | AH45: 0 | AI45: 0 | AJ45: 0 | AK45: 0 | AL45: 0 | AM45: 0 | AN45: 0 | AO45: =AO32-AO25 | AP45: =AP32-AP25 | AQ45: =AQ32-AQ25 | AR45: =AR32-AR25 | AS45: =AS32-AS25 | AT45: =AT32-AT25 | AU45: =AU32-AU25 | AV45: =AV32-AV25 | ... BI45: =BI32-BI25
A46: EUR NZD | N46: =N32-N29 | O46: =O32-O29 | P46: =P32-P29 | Q46: =Q32-Q29 | R46: =R32-R29 | S46: =S32-S29 | T46: =T32-T29 | U46: =U32-U29 | ... BI46: =BI32-BI29
A47: GBP USD | N47: =N30-N31 | O47: =O30-O31 | P47: =P30-P31 | Q47: =Q30-Q31 | R47: =R30-R31 | S47: =S30-S31 | T47: =T30-T31 | U47: =U30-U31 | ... BI47: =BI30-BI31
A48: GBP JPY | N48: =N30-N27 | O48: =O30-O27 | P48: =P30-P27 | Q48: =Q30-Q27 | R48: =R30-R27 | S48: =S30-S27 | T48: =T30-T27 | U48: =U30-U27 | ... BI48: =BI30-BI27
A49: GBP CHF | N49: =N30-N28 | O49: =O30-O28 | P49: =P30-P28 | Q49: =Q30-Q28 | R49: =R30-R28 | S49: =S30-S28 | T49: =T30-T28 | U49: =U30-U28 | ... BI49: =BI30-BI28
A50: GBP CAD | N50: =N30-N26 | O50: =O30-O26 | P50: =P30-P26 | Q50: =Q30-Q26 | R50: =R30-R26 | S50: =S30-S26 | T50: =T30-T26 | U50: =U30-U26 | ... BI50: =BI30-BI26
A51: GBP AUD | N51: =N30-N25 | O51: =O30-O25 | P51: =P30-P25 | Q51: =Q30-Q25 | R51: =R30-R25 | S51: =S30-S25 | T51: =T30-T25 | U51: =U30-U25 | ... BI51: =BI30-BI25
A52: GBP NZD | N52: =N30-N29 | O52: =O30-O29 | P52: =P30-P29 | Q52: =Q30-Q29 | R52: =R30-R29 | S52: =S30-S29 | T52: =T30-T29 | U52: =U30-U29 | ... BI52: =BI30-BI29
A53: CHF JPY | N53: =N28-N27 | O53: =O28-O27 | P53: =P28-P27 | Q53: =Q28-Q27 | R53: =R28-R27 | S53: =S28-S27 | T53: =T28-T27 | U53: =U28-U27 | ... BI53: =BI28-BI27
A54: AUD USD | N54: =N25-N31 | O54: =O25-O31 | P54: =P25-P31 | Q54: =Q25-Q31 | R54: =R25-R31 | S54: =S25-S31 | T54: =T25-T31 | U54: =U25-U31 | ... BI54: =BI25-BI31
A55: AUD CHF | N55: =N25-N28 | O55: =O25-O28 | P55: =P25-P28 | Q55: =Q25-Q28 | R55: =R25-R28 | S55: =S25-S28 | T55: =T25-T28 | U55: =U25-U28 | ... BI55: =BI25-BI28
A56: AUD JPY | N56: =N25-N27 | O56: =O25-O27 | P56: =P25-P27 | Q56: =Q25-Q27 | R56: =R25-R27 | S56: =S25-S27 | T56: =T25-T27 | U56: =U25-U27 | ... BI56: =BI25-BI27
A57: AUD NZD | N57: =N25-N29 | O57: =O25-O29 | P57: =P25-P29 | Q57: =Q25-Q29 | R57: =R25-R29 | S57: =S25-S29 | T57: =T25-T29 | U57: =U25-U29 | ... BI57: =BI25-BI29
A58: AUD CAD | N58: =N25-N26 | O58: =O25-O26 | P58: =P25-P26 | Q58: =Q25-Q26 | R58: =R25-R26 | S58: =S25-S26 | T58: =T25-T26 | U58: =U25-U26 | ... BI58: =BI25-BI26
A59: CAD JPY | N59: =N26-N27 | O59: =O26-O27 | P59: =P26-P27 | Q59: =Q26-Q27 | R59: =R26-R27 | S59: =S26-S27 | T59: =T26-T27 | U59: =U26-U27 | ... BI59: =BI26-BI27
A63: RATING
A65: Paire | N65: 44927 | O65: 44958 | P65: 44986 | Q65: 45017 | R65: 45047 | S65: 45078 | T65: 45108 | U65: 45139 | V65: 45170 | W65: 45200 | X65: 45231 | Y65: 45261 | Z65: 45292 | AA65: 45323 | AB65: 45352 | AC65: 45383 | AD65: 45413 | AE65: 45444 | AF65: 45474 | AG65: 45505 | AH65: 45536 | AI65: 45566 | AJ65: 45597 | AK65: 45627 | AL65: 45658 | AM65: 45689 | AN65: 45717 | AO65: 45748 | AP65: 45778 | AQ65: 45809 | AR65: 45839 | AS65: 45870 | AT65: 45901 | AU65: 45931 | AV65: 45962 | AW65: 45992 | AX65: 46023 | AY65: 46054 | AZ65: 46082 | BA65: 46113 | BB65: 46143 | BC65: 46174 | BD65: 46204 | BE65: 46235 | BF65: 46266 | BG65: 46296 | BH65: 46327 | BI65: 46357
A66: USD JPY | N66: {=_xlfn.XLOOKUP(MIN(ABS($BK$3:$BK$23 - MEDIAN(MIN($BK$3:$BK$23), MAX($BK$3:$BK$23), N37))), ABS($BK$3:$BK$23 - MEDIAN(MIN($BK$3:$BK$23), MAX($BK$3:$BK$23), N37)), $BL$3:$BL$23, "Error", 0)} | O66: {=_xlfn.XLOOKUP(MIN(ABS($BK$3:$BK$23 - MEDIAN(MIN($BK$3:$BK$23), MAX($BK$3:$BK$23), O37))), ABS($BK$3:$BK$23 - MEDIAN(MIN($BK$3:$BK$23), MAX($BK$3:$BK$23), O37)), $BL$3:$BL$23, "Error", 0)} | P66: {=_xlfn.XLOOKUP(MIN(ABS($BK$3:$BK$23 - MEDIAN(MIN($BK$3:$BK$23), MAX($BK$3:$BK$23), P37))), ABS($BK$3:$BK$23 - MEDIAN(MIN($BK$3:$BK$23), MAX($BK$3:$BK$23), P37)), $BL$3:$BL$23, "Error", 0)} | Q66: {=_xlfn.XLOOKUP(MIN(ABS($BK$3:$BK$23 - MEDIAN(MIN($BK$3:$BK$23), MAX($BK$3:$BK$23), Q37))), ABS($BK$3:$BK$23 - MEDIAN(MIN($BK$3:$BK$23), MAX($BK$3:$BK$23), Q37)), $BL$3:$BL$23, "Error", 0)} | R66: {=_xlfn.XLOOKUP(MIN(ABS($BK$3:$BK$23 - MEDIAN(MIN($BK$3:$BK$23), MAX($BK$3:$BK$23), R37))), ABS($BK$3:$BK$23 - MEDIAN(MIN($BK$3:$BK$23), MAX($BK$3:$BK$23), R37)), $BL$3:$BL$23, "Error", 0)} | S66: {=_xlfn.XLOOKUP(MIN(ABS($BK$3:$BK$23 - MEDIAN(MIN($BK$3:$BK$23), MAX($BK$3:$BK$23), S37))), ABS($BK$3:$BK$23 - MEDIAN(MIN($BK$3:$BK$23), MAX($BK$3:$BK$23), S37)), $BL$3:$BL$23, "Error", 0)} | T66: {=_xlfn.XLOOKUP(MIN(ABS($BK$3:$BK$23 - MEDIAN(MIN($BK$3:$BK$23), MAX($BK$3:$BK$23), T37))), ABS($BK$3:$BK$23 - MEDIAN(MIN($BK$3:$BK$23), MAX($BK$3:$BK$23), T37)), $BL$3:$BL$23, "Error", 0)} | U66: {=_xlfn.XLOOKUP(MIN(ABS($BK$3:$BK$23 - MEDIAN(MIN($BK$3:$BK$23), MAX($BK$3:$BK$23), U37))), ABS($BK$3:$BK$23 - MEDIAN(MIN($BK$3:$BK$23), MAX($BK$3:$BK$23), U37)), $BL$3:$BL$23, "Error", 0)} | ... BI66: {=_xlfn.XLOOKUP(MIN(ABS($BK$3:$BK$23 - MEDIAN(MIN($BK$3:$BK$23), MAX($BK$3:$BK$23), BI37))), ABS($BK$3:$BK$23 - MEDIAN(MIN($BK$3:$BK$23), MAX($BK$3:$BK$23), BI37)), $BL$3:$BL$23, "Error", 0)}
A67: USD CHF | N67: {=_xlfn.XLOOKUP(MIN(ABS($BK$3:$BK$23 - MEDIAN(MIN($BK$3:$BK$23), MAX($BK$3:$BK$23), N38))), ABS($BK$3:$BK$23 - MEDIAN(MIN($BK$3:$BK$23), MAX($BK$3:$BK$23), N38)), $BL$3:$BL$23, "Error", 0)} | O67: {=_xlfn.XLOOKUP(MIN(ABS($BK$3:$BK$23 - MEDIAN(MIN($BK$3:$BK$23), MAX($BK$3:$BK$23), O38))), ABS($BK$3:$BK$23 - MEDIAN(MIN($BK$3:$BK$23), MAX($BK$3:$BK$23), O38)), $BL$3:$BL$23, "Error", 0)} | P67: {=_xlfn.XLOOKUP(MIN(ABS($BK$3:$BK$23 - MEDIAN(MIN($BK$3:$BK$23), MAX($BK$3:$BK$23), P38))), ABS($BK$3:$BK$23 - MEDIAN(MIN($BK$3:$BK$23), MAX($BK$3:$BK$23), P38)), $BL$3:$BL$23, "Error", 0)} | Q67: {=_xlfn.XLOOKUP(MIN(ABS($BK$3:$BK$23 - MEDIAN(MIN($BK$3:$BK$23), MAX($BK$3:$BK$23), Q38))), ABS($BK$3:$BK$23 - MEDIAN(MIN($BK$3:$BK$23), MAX($BK$3:$BK$23), Q38)), $BL$3:$BL$23, "Error", 0)} | R67: {=_xlfn.XLOOKUP(MIN(ABS($BK$3:$BK$23 - MEDIAN(MIN($BK$3:$BK$23), MAX($BK$3:$BK$23), R38))), ABS($BK$3:$BK$23 - MEDIAN(MIN($BK$3:$BK$23), MAX($BK$3:$BK$23), R38)), $BL$3:$BL$23, "Error", 0)} | S67: {=_xlfn.XLOOKUP(MIN(ABS($BK$3:$BK$23 - MEDIAN(MIN($BK$3:$BK$23), MAX($BK$3:$BK$23), S38))), ABS($BK$3:$BK$23 - MEDIAN(MIN($BK$3:$BK$23), MAX($BK$3:$BK$23), S38)), $BL$3:$BL$23, "Error", 0)} | T67: {=_xlfn.XLOOKUP(MIN(ABS($BK$3:$BK$23 - MEDIAN(MIN($BK$3:$BK$23), MAX($BK$3:$BK$23), T38))), ABS($BK$3:$BK$23 - MEDIAN(MIN($BK$3:$BK$23), MAX($BK$3:$BK$23), T38)), $BL$3:$BL$23, "Error", 0)} | U67: {=_xlfn.XLOOKUP(MIN(ABS($BK$3:$BK$23 - MEDIAN(MIN($BK$3:$BK$23), MAX($BK$3:$BK$23), U38))), ABS($BK$3:$BK$23 - MEDIAN(MIN($BK$3:$BK$23), MAX($BK$3:$BK$23), U38)), $BL$3:$BL$23, "Error", 0)} | ... BI67: {=_xlfn.XLOOKUP(MIN(ABS($BK$3:$BK$23 - MEDIAN(MIN($BK$3:$BK$23), MAX($BK$3:$BK$23), BI38))), ABS($BK$3:$BK$23 - MEDIAN(MIN($BK$3:$BK$23), MAX($BK$3:$BK$23), BI38)), $BL$3:$BL$23, "Error", 0)}
A68: USD CAD | N68: {=_xlfn.XLOOKUP(MIN(ABS($BK$3:$BK$23 - MEDIAN(MIN($BK$3:$BK$23), MAX($BK$3:$BK$23), N39))), ABS($BK$3:$BK$23 - MEDIAN(MIN($BK$3:$BK$23), MAX($BK$3:$BK$23), N39)), $BL$3:$BL$23, "Error", 0)} | O68: {=_xlfn.XLOOKUP(MIN(ABS($BK$3:$BK$23 - MEDIAN(MIN($BK$3:$BK$23), MAX($BK$3:$BK$23), O39))), ABS($BK$3:$BK$23 - MEDIAN(MIN($BK$3:$BK$23), MAX($BK$3:$BK$23), O39)), $BL$3:$BL$23, "Error", 0)} | P68: {=_xlfn.XLOOKUP(MIN(ABS($BK$3:$BK$23 - MEDIAN(MIN($BK$3:$BK$23), MAX($BK$3:$BK$23), P39))), ABS($BK$3:$BK$23 - MEDIAN(MIN($BK$3:$BK$23), MAX($BK$3:$BK$23), P39)), $BL$3:$BL$23, "Error", 0)} | Q68: {=_xlfn.XLOOKUP(MIN(ABS($BK$3:$BK$23 - MEDIAN(MIN($BK$3:$BK$23), MAX($BK$3:$BK$23), Q39))), ABS($BK$3:$BK$23 - MEDIAN(MIN($BK$3:$BK$23), MAX($BK$3:$BK$23), Q39)), $BL$3:$BL$23, "Error", 0)} | R68: {=_xlfn.XLOOKUP(MIN(ABS($BK$3:$BK$23 - MEDIAN(MIN($BK$3:$BK$23), MAX($BK$3:$BK$23), R39))), ABS($BK$3:$BK$23 - MEDIAN(MIN($BK$3:$BK$23), MAX($BK$3:$BK$23), R39)), $BL$3:$BL$23, "Error", 0)} | S68: {=_xlfn.XLOOKUP(MIN(ABS($BK$3:$BK$23 - MEDIAN(MIN($BK$3:$BK$23), MAX($BK$3:$BK$23), S39))), ABS($BK$3:$BK$23 - MEDIAN(MIN($BK$3:$BK$23), MAX($BK$3:$BK$23), S39)), $BL$3:$BL$23, "Error", 0)} | T68: {=_xlfn.XLOOKUP(MIN(ABS($BK$3:$BK$23 - MEDIAN(MIN($BK$3:$BK$23), MAX($BK$3:$BK$23), T39))), ABS($BK$3:$BK$23 - MEDIAN(MIN($BK$3:$BK$23), MAX($BK$3:$BK$23), T39)), $BL$3:$BL$23, "Error", 0)} | U68: {=_xlfn.XLOOKUP(MIN(ABS($BK$3:$BK$23 - MEDIAN(MIN($BK$3:$BK$23), MAX($BK$3:$BK$23), U39))), ABS($BK$3:$BK$23 - MEDIAN(MIN($BK$3:$BK$23), MAX($BK$3:$BK$23), U39)), $BL$3:$BL$23, "Error", 0)} | ... BI68: {=_xlfn.XLOOKUP(MIN(ABS($BK$3:$BK$23 - MEDIAN(MIN($BK$3:$BK$23), MAX($BK$3:$BK$23), BI39))), ABS($BK$3:$BK$23 - MEDIAN(MIN($BK$3:$BK$23), MAX($BK$3:$BK$23), BI39)), $BL$3:$BL$23, "Error", 0)}
A69: EUR USD | N69: {=_xlfn.XLOOKUP(MIN(ABS($BK$3:$BK$23 - MEDIAN(MIN($BK$3:$BK$23), MAX($BK$3:$BK$23), N40))), ABS($BK$3:$BK$23 - MEDIAN(MIN($BK$3:$BK$23), MAX($BK$3:$BK$23), N40)), $BL$3:$BL$23, "Error", 0)} | O69: {=_xlfn.XLOOKUP(MIN(ABS($BK$3:$BK$23 - MEDIAN(MIN($BK$3:$BK$23), MAX($BK$3:$BK$23), O40))), ABS($BK$3:$BK$23 - MEDIAN(MIN($BK$3:$BK$23), MAX($BK$3:$BK$23), O40)), $BL$3:$BL$23, "Error", 0)} | P69: {=_xlfn.XLOOKUP(MIN(ABS($BK$3:$BK$23 - MEDIAN(MIN($BK$3:$BK$23), MAX($BK$3:$BK$23), P40))), ABS($BK$3:$BK$23 - MEDIAN(MIN($BK$3:$BK$23), MAX($BK$3:$BK$23), P40)), $BL$3:$BL$23, "Error", 0)} | Q69: {=_xlfn.XLOOKUP(MIN(ABS($BK$3:$BK$23 - MEDIAN(MIN($BK$3:$BK$23), MAX($BK$3:$BK$23), Q40))), ABS($BK$3:$BK$23 - MEDIAN(MIN($BK$3:$BK$23), MAX($BK$3:$BK$23), Q40)), $BL$3:$BL$23, "Error", 0)} | R69: {=_xlfn.XLOOKUP(MIN(ABS($BK$3:$BK$23 - MEDIAN(MIN($BK$3:$BK$23), MAX($BK$3:$BK$23), R40))), ABS($BK$3:$BK$23 - MEDIAN(MIN($BK$3:$BK$23), MAX($BK$3:$BK$23), R40)), $BL$3:$BL$23, "Error", 0)} | S69: {=_xlfn.XLOOKUP(MIN(ABS($BK$3:$BK$23 - MEDIAN(MIN($BK$3:$BK$23), MAX($BK$3:$BK$23), S40))), ABS($BK$3:$BK$23 - MEDIAN(MIN($BK$3:$BK$23), MAX($BK$3:$BK$23), S40)), $BL$3:$BL$23, "Error", 0)} | T69: {=_xlfn.XLOOKUP(MIN(ABS($BK$3:$BK$23 - MEDIAN(MIN($BK$3:$BK$23), MAX($BK$3:$BK$23), T40))), ABS($BK$3:$BK$23 - MEDIAN(MIN($BK$3:$BK$23), MAX($BK$3:$BK$23), T40)), $BL$3:$BL$23, "Error", 0)} | U69: {=_xlfn.XLOOKUP(MIN(ABS($BK$3:$BK$23 - MEDIAN(MIN($BK$3:$BK$23), MAX($BK$3:$BK$23), U40))), ABS($BK$3:$BK$23 - MEDIAN(MIN($BK$3:$BK$23), MAX($BK$3:$BK$23), U40)), $BL$3:$BL$23, "Error", 0)} | ... BI69: {=_xlfn.XLOOKUP(MIN(ABS($BK$3:$BK$23 - MEDIAN(MIN($BK$3:$BK$23), MAX($BK$3:$BK$23), BI40))), ABS($BK$3:$BK$23 - MEDIAN(MIN($BK$3:$BK$23), MAX($BK$3:$BK$23), BI40)), $BL$3:$BL$23, "Error", 0)}
A70: EUR JPY | N70: {=_xlfn.XLOOKUP(MIN(ABS($BK$3:$BK$23 - MEDIAN(MIN($BK$3:$BK$23), MAX($BK$3:$BK$23), N41))), ABS($BK$3:$BK$23 - MEDIAN(MIN($BK$3:$BK$23), MAX($BK$3:$BK$23), N41)), $BL$3:$BL$23, "Error", 0)} | O70: {=_xlfn.XLOOKUP(MIN(ABS($BK$3:$BK$23 - MEDIAN(MIN($BK$3:$BK$23), MAX($BK$3:$BK$23), O41))), ABS($BK$3:$BK$23 - MEDIAN(MIN($BK$3:$BK$23), MAX($BK$3:$BK$23), O41)), $BL$3:$BL$23, "Error", 0)} | P70: {=_xlfn.XLOOKUP(MIN(ABS($BK$3:$BK$23 - MEDIAN(MIN($BK$3:$BK$23), MAX($BK$3:$BK$23), P41))), ABS($BK$3:$BK$23 - MEDIAN(MIN($BK$3:$BK$23), MAX($BK$3:$BK$23), P41)), $BL$3:$BL$23, "Error", 0)} | Q70: {=_xlfn.XLOOKUP(MIN(ABS($BK$3:$BK$23 - MEDIAN(MIN($BK$3:$BK$23), MAX($BK$3:$BK$23), Q41))), ABS($BK$3:$BK$23 - MEDIAN(MIN($BK$3:$BK$23), MAX($BK$3:$BK$23), Q41)), $BL$3:$BL$23, "Error", 0)} | R70: {=_xlfn.XLOOKUP(MIN(ABS($BK$3:$BK$23 - MEDIAN(MIN($BK$3:$BK$23), MAX($BK$3:$BK$23), R41))), ABS($BK$3:$BK$23 - MEDIAN(MIN($BK$3:$BK$23), MAX($BK$3:$BK$23), R41)), $BL$3:$BL$23, "Error", 0)} | S70: {=_xlfn.XLOOKUP(MIN(ABS($BK$3:$BK$23 - MEDIAN(MIN($BK$3:$BK$23), MAX($BK$3:$BK$23), S41))), ABS($BK$3:$BK$23 - MEDIAN(MIN($BK$3:$BK$23), MAX($BK$3:$BK$23), S41)), $BL$3:$BL$23, "Error", 0)} | T70: {=_xlfn.XLOOKUP(MIN(ABS($BK$3:$BK$23 - MEDIAN(MIN($BK$3:$BK$23), MAX($BK$3:$BK$23), T41))), ABS($BK$3:$BK$23 - MEDIAN(MIN($BK$3:$BK$23), MAX($BK$3:$BK$23), T41)), $BL$3:$BL$23, "Error", 0)} | U70: {=_xlfn.XLOOKUP(MIN(ABS($BK$3:$BK$23 - MEDIAN(MIN($BK$3:$BK$23), MAX($BK$3:$BK$23), U41))), ABS($BK$3:$BK$23 - MEDIAN(MIN($BK$3:$BK$23), MAX($BK$3:$BK$23), U41)), $BL$3:$BL$23, "Error", 0)} | ... BI70: {=_xlfn.XLOOKUP(MIN(ABS($BK$3:$BK$23 - MEDIAN(MIN($BK$3:$BK$23), MAX($BK$3:$BK$23), BI41))), ABS($BK$3:$BK$23 - MEDIAN(MIN($BK$3:$BK$23), MAX($BK$3:$BK$23), BI41)), $BL$3:$BL$23, "Error", 0)}
A71: EUR CHF | N71: {=_xlfn.XLOOKUP(MIN(ABS($BK$3:$BK$23 - MEDIAN(MIN($BK$3:$BK$23), MAX($BK$3:$BK$23), N42))), ABS($BK$3:$BK$23 - MEDIAN(MIN($BK$3:$BK$23), MAX($BK$3:$BK$23), N42)), $BL$3:$BL$23, "Error", 0)} | O71: {=_xlfn.XLOOKUP(MIN(ABS($BK$3:$BK$23 - MEDIAN(MIN($BK$3:$BK$23), MAX($BK$3:$BK$23), O42))), ABS($BK$3:$BK$23 - MEDIAN(MIN($BK$3:$BK$23), MAX($BK$3:$BK$23), O42)), $BL$3:$BL$23, "Error", 0)} | P71: {=_xlfn.XLOOKUP(MIN(ABS($BK$3:$BK$23 - MEDIAN(MIN($BK$3:$BK$23), MAX($BK$3:$BK$23), P42))), ABS($BK$3:$BK$23 - MEDIAN(MIN($BK$3:$BK$23), MAX($BK$3:$BK$23), P42)), $BL$3:$BL$23, "Error", 0)} | Q71: {=_xlfn.XLOOKUP(MIN(ABS($BK$3:$BK$23 - MEDIAN(MIN($BK$3:$BK$23), MAX($BK$3:$BK$23), Q42))), ABS($BK$3:$BK$23 - MEDIAN(MIN($BK$3:$BK$23), MAX($BK$3:$BK$23), Q42)), $BL$3:$BL$23, "Error", 0)} | R71: {=_xlfn.XLOOKUP(MIN(ABS($BK$3:$BK$23 - MEDIAN(MIN($BK$3:$BK$23), MAX($BK$3:$BK$23), R42))), ABS($BK$3:$BK$23 - MEDIAN(MIN($BK$3:$BK$23), MAX($BK$3:$BK$23), R42)), $BL$3:$BL$23, "Error", 0)} | S71: {=_xlfn.XLOOKUP(MIN(ABS($BK$3:$BK$23 - MEDIAN(MIN($BK$3:$BK$23), MAX($BK$3:$BK$23), S42))), ABS($BK$3:$BK$23 - MEDIAN(MIN($BK$3:$BK$23), MAX($BK$3:$BK$23), S42)), $BL$3:$BL$23, "Error", 0)} | T71: {=_xlfn.XLOOKUP(MIN(ABS($BK$3:$BK$23 - MEDIAN(MIN($BK$3:$BK$23), MAX($BK$3:$BK$23), T42))), ABS($BK$3:$BK$23 - MEDIAN(MIN($BK$3:$BK$23), MAX($BK$3:$BK$23), T42)), $BL$3:$BL$23, "Error", 0)} | U71: {=_xlfn.XLOOKUP(MIN(ABS($BK$3:$BK$23 - MEDIAN(MIN($BK$3:$BK$23), MAX($BK$3:$BK$23), U42))), ABS($BK$3:$BK$23 - MEDIAN(MIN($BK$3:$BK$23), MAX($BK$3:$BK$23), U42)), $BL$3:$BL$23, "Error", 0)} | ... BI71: {=_xlfn.XLOOKUP(MIN(ABS($BK$3:$BK$23 - MEDIAN(MIN($BK$3:$BK$23), MAX($BK$3:$BK$23), BI42))), ABS($BK$3:$BK$23 - MEDIAN(MIN($BK$3:$BK$23), MAX($BK$3:$BK$23), BI42)), $BL$3:$BL$23, "Error", 0)}
A72: EUR GBP | N72: {=_xlfn.XLOOKUP(MIN(ABS($BK$3:$BK$23 - MEDIAN(MIN($BK$3:$BK$23), MAX($BK$3:$BK$23), N43))), ABS($BK$3:$BK$23 - MEDIAN(MIN($BK$3:$BK$23), MAX($BK$3:$BK$23), N43)), $BL$3:$BL$23, "Error", 0)} | O72: {=_xlfn.XLOOKUP(MIN(ABS($BK$3:$BK$23 - MEDIAN(MIN($BK$3:$BK$23), MAX($BK$3:$BK$23), O43))), ABS($BK$3:$BK$23 - MEDIAN(MIN($BK$3:$BK$23), MAX($BK$3:$BK$23), O43)), $BL$3:$BL$23, "Error", 0)} | P72: {=_xlfn.XLOOKUP(MIN(ABS($BK$3:$BK$23 - MEDIAN(MIN($BK$3:$BK$23), MAX($BK$3:$BK$23), P43))), ABS($BK$3:$BK$23 - MEDIAN(MIN($BK$3:$BK$23), MAX($BK$3:$BK$23), P43)), $BL$3:$BL$23, "Error", 0)} | Q72: {=_xlfn.XLOOKUP(MIN(ABS($BK$3:$BK$23 - MEDIAN(MIN($BK$3:$BK$23), MAX($BK$3:$BK$23), Q43))), ABS($BK$3:$BK$23 - MEDIAN(MIN($BK$3:$BK$23), MAX($BK$3:$BK$23), Q43)), $BL$3:$BL$23, "Error", 0)} | R72: {=_xlfn.XLOOKUP(MIN(ABS($BK$3:$BK$23 - MEDIAN(MIN($BK$3:$BK$23), MAX($BK$3:$BK$23), R43))), ABS($BK$3:$BK$23 - MEDIAN(MIN($BK$3:$BK$23), MAX($BK$3:$BK$23), R43)), $BL$3:$BL$23, "Error", 0)} | S72: {=_xlfn.XLOOKUP(MIN(ABS($BK$3:$BK$23 - MEDIAN(MIN($BK$3:$BK$23), MAX($BK$3:$BK$23), S43))), ABS($BK$3:$BK$23 - MEDIAN(MIN($BK$3:$BK$23), MAX($BK$3:$BK$23), S43)), $BL$3:$BL$23, "Error", 0)} | T72: {=_xlfn.XLOOKUP(MIN(ABS($BK$3:$BK$23 - MEDIAN(MIN($BK$3:$BK$23), MAX($BK$3:$BK$23), T43))), ABS($BK$3:$BK$23 - MEDIAN(MIN($BK$3:$BK$23), MAX($BK$3:$BK$23), T43)), $BL$3:$BL$23, "Error", 0)} | U72: {=_xlfn.XLOOKUP(MIN(ABS($BK$3:$BK$23 - MEDIAN(MIN($BK$3:$BK$23), MAX($BK$3:$BK$23), U43))), ABS($BK$3:$BK$23 - MEDIAN(MIN($BK$3:$BK$23), MAX($BK$3:$BK$23), U43)), $BL$3:$BL$23, "Error", 0)} | ... BI72: {=_xlfn.XLOOKUP(MIN(ABS($BK$3:$BK$23 - MEDIAN(MIN($BK$3:$BK$23), MAX($BK$3:$BK$23), BI43))), ABS($BK$3:$BK$23 - MEDIAN(MIN($BK$3:$BK$23), MAX($BK$3:$BK$23), BI43)), $BL$3:$BL$23, "Error", 0)}
A73: EUR CAD | N73: {=_xlfn.XLOOKUP(MIN(ABS($BK$3:$BK$23 - MEDIAN(MIN($BK$3:$BK$23), MAX($BK$3:$BK$23), N44))), ABS($BK$3:$BK$23 - MEDIAN(MIN($BK$3:$BK$23), MAX($BK$3:$BK$23), N44)), $BL$3:$BL$23, "Error", 0)} | O73: {=_xlfn.XLOOKUP(MIN(ABS($BK$3:$BK$23 - MEDIAN(MIN($BK$3:$BK$23), MAX($BK$3:$BK$23), O44))), ABS($BK$3:$BK$23 - MEDIAN(MIN($BK$3:$BK$23), MAX($BK$3:$BK$23), O44)), $BL$3:$BL$23, "Error", 0)} | P73: {=_xlfn.XLOOKUP(MIN(ABS($BK$3:$BK$23 - MEDIAN(MIN($BK$3:$BK$23), MAX($BK$3:$BK$23), P44))), ABS($BK$3:$BK$23 - MEDIAN(MIN($BK$3:$BK$23), MAX($BK$3:$BK$23), P44)), $BL$3:$BL$23, "Error", 0)} | Q73: {=_xlfn.XLOOKUP(MIN(ABS($BK$3:$BK$23 - MEDIAN(MIN($BK$3:$BK$23), MAX($BK$3:$BK$23), Q44))), ABS($BK$3:$BK$23 - MEDIAN(MIN($BK$3:$BK$23), MAX($BK$3:$BK$23), Q44)), $BL$3:$BL$23, "Error", 0)} | R73: {=_xlfn.XLOOKUP(MIN(ABS($BK$3:$BK$23 - MEDIAN(MIN($BK$3:$BK$23), MAX($BK$3:$BK$23), R44))), ABS($BK$3:$BK$23 - MEDIAN(MIN($BK$3:$BK$23), MAX($BK$3:$BK$23), R44)), $BL$3:$BL$23, "Error", 0)} | S73: {=_xlfn.XLOOKUP(MIN(ABS($BK$3:$BK$23 - MEDIAN(MIN($BK$3:$BK$23), MAX($BK$3:$BK$23), S44))), ABS($BK$3:$BK$23 - MEDIAN(MIN($BK$3:$BK$23), MAX($BK$3:$BK$23), S44)), $BL$3:$BL$23, "Error", 0)} | T73: {=_xlfn.XLOOKUP(MIN(ABS($BK$3:$BK$23 - MEDIAN(MIN($BK$3:$BK$23), MAX($BK$3:$BK$23), T44))), ABS($BK$3:$BK$23 - MEDIAN(MIN($BK$3:$BK$23), MAX($BK$3:$BK$23), T44)), $BL$3:$BL$23, "Error", 0)} | U73: {=_xlfn.XLOOKUP(MIN(ABS($BK$3:$BK$23 - MEDIAN(MIN($BK$3:$BK$23), MAX($BK$3:$BK$23), U44))), ABS($BK$3:$BK$23 - MEDIAN(MIN($BK$3:$BK$23), MAX($BK$3:$BK$23), U44)), $BL$3:$BL$23, "Error", 0)} | ... BI73: {=_xlfn.XLOOKUP(MIN(ABS($BK$3:$BK$23 - MEDIAN(MIN($BK$3:$BK$23), MAX($BK$3:$BK$23), BI44))), ABS($BK$3:$BK$23 - MEDIAN(MIN($BK$3:$BK$23), MAX($BK$3:$BK$23), BI44)), $BL$3:$BL$23, "Error", 0)}
A74: EUR AUD | N74: {=_xlfn.XLOOKUP(MIN(ABS($BK$3:$BK$23 - MEDIAN(MIN($BK$3:$BK$23), MAX($BK$3:$BK$23), N45))), ABS($BK$3:$BK$23 - MEDIAN(MIN($BK$3:$BK$23), MAX($BK$3:$BK$23), N45)), $BL$3:$BL$23, "Error", 0)} | O74: {=_xlfn.XLOOKUP(MIN(ABS($BK$3:$BK$23 - MEDIAN(MIN($BK$3:$BK$23), MAX($BK$3:$BK$23), O45))), ABS($BK$3:$BK$23 - MEDIAN(MIN($BK$3:$BK$23), MAX($BK$3:$BK$23), O45)), $BL$3:$BL$23, "Error", 0)} | P74: {=_xlfn.XLOOKUP(MIN(ABS($BK$3:$BK$23 - MEDIAN(MIN($BK$3:$BK$23), MAX($BK$3:$BK$23), P45))), ABS($BK$3:$BK$23 - MEDIAN(MIN($BK$3:$BK$23), MAX($BK$3:$BK$23), P45)), $BL$3:$BL$23, "Error", 0)} | Q74: {=_xlfn.XLOOKUP(MIN(ABS($BK$3:$BK$23 - MEDIAN(MIN($BK$3:$BK$23), MAX($BK$3:$BK$23), Q45))), ABS($BK$3:$BK$23 - MEDIAN(MIN($BK$3:$BK$23), MAX($BK$3:$BK$23), Q45)), $BL$3:$BL$23, "Error", 0)} | R74: {=_xlfn.XLOOKUP(MIN(ABS($BK$3:$BK$23 - MEDIAN(MIN($BK$3:$BK$23), MAX($BK$3:$BK$23), R45))), ABS($BK$3:$BK$23 - MEDIAN(MIN($BK$3:$BK$23), MAX($BK$3:$BK$23), R45)), $BL$3:$BL$23, "Error", 0)} | S74: {=_xlfn.XLOOKUP(MIN(ABS($BK$3:$BK$23 - MEDIAN(MIN($BK$3:$BK$23), MAX($BK$3:$BK$23), S45))), ABS($BK$3:$BK$23 - MEDIAN(MIN($BK$3:$BK$23), MAX($BK$3:$BK$23), S45)), $BL$3:$BL$23, "Error", 0)} | T74: {=_xlfn.XLOOKUP(MIN(ABS($BK$3:$BK$23 - MEDIAN(MIN($BK$3:$BK$23), MAX($BK$3:$BK$23), T45))), ABS($BK$3:$BK$23 - MEDIAN(MIN($BK$3:$BK$23), MAX($BK$3:$BK$23), T45)), $BL$3:$BL$23, "Error", 0)} | U74: {=_xlfn.XLOOKUP(MIN(ABS($BK$3:$BK$23 - MEDIAN(MIN($BK$3:$BK$23), MAX($BK$3:$BK$23), U45))), ABS($BK$3:$BK$23 - MEDIAN(MIN($BK$3:$BK$23), MAX($BK$3:$BK$23), U45)), $BL$3:$BL$23, "Error", 0)} | ... BI74: {=_xlfn.XLOOKUP(MIN(ABS($BK$3:$BK$23 - MEDIAN(MIN($BK$3:$BK$23), MAX($BK$3:$BK$23), BI45))), ABS($BK$3:$BK$23 - MEDIAN(MIN($BK$3:$BK$23), MAX($BK$3:$BK$23), BI45)), $BL$3:$BL$23, "Error", 0)}
A75: EUR NZD | N75: {=_xlfn.XLOOKUP(MIN(ABS($BK$3:$BK$23 - MEDIAN(MIN($BK$3:$BK$23), MAX($BK$3:$BK$23), N46))), ABS($BK$3:$BK$23 - MEDIAN(MIN($BK$3:$BK$23), MAX($BK$3:$BK$23), N46)), $BL$3:$BL$23, "Error", 0)} | O75: {=_xlfn.XLOOKUP(MIN(ABS($BK$3:$BK$23 - MEDIAN(MIN($BK$3:$BK$23), MAX($BK$3:$BK$23), O46))), ABS($BK$3:$BK$23 - MEDIAN(MIN($BK$3:$BK$23), MAX($BK$3:$BK$23), O46)), $BL$3:$BL$23, "Error", 0)} | P75: {=_xlfn.XLOOKUP(MIN(ABS($BK$3:$BK$23 - MEDIAN(MIN($BK$3:$BK$23), MAX($BK$3:$BK$23), P46))), ABS($BK$3:$BK$23 - MEDIAN(MIN($BK$3:$BK$23), MAX($BK$3:$BK$23), P46)), $BL$3:$BL$23, "Error", 0)} | Q75: {=_xlfn.XLOOKUP(MIN(ABS($BK$3:$BK$23 - MEDIAN(MIN($BK$3:$BK$23), MAX($BK$3:$BK$23), Q46))), ABS($BK$3:$BK$23 - MEDIAN(MIN($BK$3:$BK$23), MAX($BK$3:$BK$23), Q46)), $BL$3:$BL$23, "Error", 0)} | R75: {=_xlfn.XLOOKUP(MIN(ABS($BK$3:$BK$23 - MEDIAN(MIN($BK$3:$BK$23), MAX($BK$3:$BK$23), R46))), ABS($BK$3:$BK$23 - MEDIAN(MIN($BK$3:$BK$23), MAX($BK$3:$BK$23), R46)), $BL$3:$BL$23, "Error", 0)} | S75: {=_xlfn.XLOOKUP(MIN(ABS($BK$3:$BK$23 - MEDIAN(MIN($BK$3:$BK$23), MAX($BK$3:$BK$23), S46))), ABS($BK$3:$BK$23 - MEDIAN(MIN($BK$3:$BK$23), MAX($BK$3:$BK$23), S46)), $BL$3:$BL$23, "Error", 0)} | T75: {=_xlfn.XLOOKUP(MIN(ABS($BK$3:$BK$23 - MEDIAN(MIN($BK$3:$BK$23), MAX($BK$3:$BK$23), T46))), ABS($BK$3:$BK$23 - MEDIAN(MIN($BK$3:$BK$23), MAX($BK$3:$BK$23), T46)), $BL$3:$BL$23, "Error", 0)} | U75: {=_xlfn.XLOOKUP(MIN(ABS($BK$3:$BK$23 - MEDIAN(MIN($BK$3:$BK$23), MAX($BK$3:$BK$23), U46))), ABS($BK$3:$BK$23 - MEDIAN(MIN($BK$3:$BK$23), MAX($BK$3:$BK$23), U46)), $BL$3:$BL$23, "Error", 0)} | ... BI75: {=_xlfn.XLOOKUP(MIN(ABS($BK$3:$BK$23 - MEDIAN(MIN($BK$3:$BK$23), MAX($BK$3:$BK$23), BI46))), ABS($BK$3:$BK$23 - MEDIAN(MIN($BK$3:$BK$23), MAX($BK$3:$BK$23), BI46)), $BL$3:$BL$23, "Error", 0)}
A76: GBP USD | N76: {=_xlfn.XLOOKUP(MIN(ABS($BK$3:$BK$23 - MEDIAN(MIN($BK$3:$BK$23), MAX($BK$3:$BK$23), N47))), ABS($BK$3:$BK$23 - MEDIAN(MIN($BK$3:$BK$23), MAX($BK$3:$BK$23), N47)), $BL$3:$BL$23, "Error", 0)} | O76: {=_xlfn.XLOOKUP(MIN(ABS($BK$3:$BK$23 - MEDIAN(MIN($BK$3:$BK$23), MAX($BK$3:$BK$23), O47))), ABS($BK$3:$BK$23 - MEDIAN(MIN($BK$3:$BK$23), MAX($BK$3:$BK$23), O47)), $BL$3:$BL$23, "Error", 0)} | P76: {=_xlfn.XLOOKUP(MIN(ABS($BK$3:$BK$23 - MEDIAN(MIN($BK$3:$BK$23), MAX($BK$3:$BK$23), P47))), ABS($BK$3:$BK$23 - MEDIAN(MIN($BK$3:$BK$23), MAX($BK$3:$BK$23), P47)), $BL$3:$BL$23, "Error", 0)} | Q76: {=_xlfn.XLOOKUP(MIN(ABS($BK$3:$BK$23 - MEDIAN(MIN($BK$3:$BK$23), MAX($BK$3:$BK$23), Q47))), ABS($BK$3:$BK$23 - MEDIAN(MIN($BK$3:$BK$23), MAX($BK$3:$BK$23), Q47)), $BL$3:$BL$23, "Error", 0)} | R76: {=_xlfn.XLOOKUP(MIN(ABS($BK$3:$BK$23 - MEDIAN(MIN($BK$3:$BK$23), MAX($BK$3:$BK$23), R47))), ABS($BK$3:$BK$23 - MEDIAN(MIN($BK$3:$BK$23), MAX($BK$3:$BK$23), R47)), $BL$3:$BL$23, "Error", 0)} | S76: {=_xlfn.XLOOKUP(MIN(ABS($BK$3:$BK$23 - MEDIAN(MIN($BK$3:$BK$23), MAX($BK$3:$BK$23), S47))), ABS($BK$3:$BK$23 - MEDIAN(MIN($BK$3:$BK$23), MAX($BK$3:$BK$23), S47)), $BL$3:$BL$23, "Error", 0)} | T76: {=_xlfn.XLOOKUP(MIN(ABS($BK$3:$BK$23 - MEDIAN(MIN($BK$3:$BK$23), MAX($BK$3:$BK$23), T47))), ABS($BK$3:$BK$23 - MEDIAN(MIN($BK$3:$BK$23), MAX($BK$3:$BK$23), T47)), $BL$3:$BL$23, "Error", 0)} | U76: {=_xlfn.XLOOKUP(MIN(ABS($BK$3:$BK$23 - MEDIAN(MIN($BK$3:$BK$23), MAX($BK$3:$BK$23), U47))), ABS($BK$3:$BK$23 - MEDIAN(MIN($BK$3:$BK$23), MAX($BK$3:$BK$23), U47)), $BL$3:$BL$23, "Error", 0)} | ... BI76: {=_xlfn.XLOOKUP(MIN(ABS($BK$3:$BK$23 - MEDIAN(MIN($BK$3:$BK$23), MAX($BK$3:$BK$23), BI47))), ABS($BK$3:$BK$23 - MEDIAN(MIN($BK$3:$BK$23), MAX($BK$3:$BK$23), BI47)), $BL$3:$BL$23, "Error", 0)}
A77: GBP JPY | N77: {=_xlfn.XLOOKUP(MIN(ABS($BK$3:$BK$23 - MEDIAN(MIN($BK$3:$BK$23), MAX($BK$3:$BK$23), N48))), ABS($BK$3:$BK$23 - MEDIAN(MIN($BK$3:$BK$23), MAX($BK$3:$BK$23), N48)), $BL$3:$BL$23, "Error", 0)} | O77: {=_xlfn.XLOOKUP(MIN(ABS($BK$3:$BK$23 - MEDIAN(MIN($BK$3:$BK$23), MAX($BK$3:$BK$23), O48))), ABS($BK$3:$BK$23 - MEDIAN(MIN($BK$3:$BK$23), MAX($BK$3:$BK$23), O48)), $BL$3:$BL$23, "Error", 0)} | P77: {=_xlfn.XLOOKUP(MIN(ABS($BK$3:$BK$23 - MEDIAN(MIN($BK$3:$BK$23), MAX($BK$3:$BK$23), P48))), ABS($BK$3:$BK$23 - MEDIAN(MIN($BK$3:$BK$23), MAX($BK$3:$BK$23), P48)), $BL$3:$BL$23, "Error", 0)} | Q77: {=_xlfn.XLOOKUP(MIN(ABS($BK$3:$BK$23 - MEDIAN(MIN($BK$3:$BK$23), MAX($BK$3:$BK$23), Q48))), ABS($BK$3:$BK$23 - MEDIAN(MIN($BK$3:$BK$23), MAX($BK$3:$BK$23), Q48)), $BL$3:$BL$23, "Error", 0)} | R77: {=_xlfn.XLOOKUP(MIN(ABS($BK$3:$BK$23 - MEDIAN(MIN($BK$3:$BK$23), MAX($BK$3:$BK$23), R48))), ABS($BK$3:$BK$23 - MEDIAN(MIN($BK$3:$BK$23), MAX($BK$3:$BK$23), R48)), $BL$3:$BL$23, "Error", 0)} | S77: {=_xlfn.XLOOKUP(MIN(ABS($BK$3:$BK$23 - MEDIAN(MIN($BK$3:$BK$23), MAX($BK$3:$BK$23), S48))), ABS($BK$3:$BK$23 - MEDIAN(MIN($BK$3:$BK$23), MAX($BK$3:$BK$23), S48)), $BL$3:$BL$23, "Error", 0)} | T77: {=_xlfn.XLOOKUP(MIN(ABS($BK$3:$BK$23 - MEDIAN(MIN($BK$3:$BK$23), MAX($BK$3:$BK$23), T48))), ABS($BK$3:$BK$23 - MEDIAN(MIN($BK$3:$BK$23), MAX($BK$3:$BK$23), T48)), $BL$3:$BL$23, "Error", 0)} | U77: {=_xlfn.XLOOKUP(MIN(ABS($BK$3:$BK$23 - MEDIAN(MIN($BK$3:$BK$23), MAX($BK$3:$BK$23), U48))), ABS($BK$3:$BK$23 - MEDIAN(MIN($BK$3:$BK$23), MAX($BK$3:$BK$23), U48)), $BL$3:$BL$23, "Error", 0)} | ... BI77: {=_xlfn.XLOOKUP(MIN(ABS($BK$3:$BK$23 - MEDIAN(MIN($BK$3:$BK$23), MAX($BK$3:$BK$23), BI48))), ABS($BK$3:$BK$23 - MEDIAN(MIN($BK$3:$BK$23), MAX($BK$3:$BK$23), BI48)), $BL$3:$BL$23, "Error", 0)}
... A88: CAD JPY | N88: {=_xlfn.XLOOKUP(MIN(ABS($BK$3:$BK$23 - MEDIAN(MIN($BK$3:$BK$23), MAX($BK$3:$BK$23), N59))), ABS($BK$3:$BK$23 - MEDIAN(MIN($BK$3:$BK$23), MAX($BK$3:$BK$23), N59)), $BL$3:$BL$23, "Error", 0)} | O88: {=_xlfn.XLOOKUP(MIN(ABS($BK$3:$BK$23 - MEDIAN(MIN($BK$3:$BK$23), MAX($BK$3:$BK$23), O59))), ABS($BK$3:$BK$23 - MEDIAN(MIN($BK$3:$BK$23), MAX($BK$3:$BK$23), O59)), $BL$3:$BL$23, "Error", 0)} | P88: {=_xlfn.XLOOKUP(MIN(ABS($BK$3:$BK$23 - MEDIAN(MIN($BK$3:$BK$23), MAX($BK$3:$BK$23), P59))), ABS($BK$3:$BK$23 - MEDIAN(MIN($BK$3:$BK$23), MAX($BK$3:$BK$23), P59)), $BL$3:$BL$23, "Error", 0)} | Q88: {=_xlfn.XLOOKUP(MIN(ABS($BK$3:$BK$23 - MEDIAN(MIN($BK$3:$BK$23), MAX($BK$3:$BK$23), Q59))), ABS($BK$3:$BK$23 - MEDIAN(MIN($BK$3:$BK$23), MAX($BK$3:$BK$23), Q59)), $BL$3:$BL$23, "Error", 0)} | R88: {=_xlfn.XLOOKUP(MIN(ABS($BK$3:$BK$23 - MEDIAN(MIN($BK$3:$BK$23), MAX($BK$3:$BK$23), R59))), ABS($BK$3:$BK$23 - MEDIAN(MIN($BK$3:$BK$23), MAX($BK$3:$BK$23), R59)), $BL$3:$BL$23, "Error", 0)} | S88: {=_xlfn.XLOOKUP(MIN(ABS($BK$3:$BK$23 - MEDIAN(MIN($BK$3:$BK$23), MAX($BK$3:$BK$23), S59))), ABS($BK$3:$BK$23 - MEDIAN(MIN($BK$3:$BK$23), MAX($BK$3:$BK$23), S59)), $BL$3:$BL$23, "Error", 0)} | T88: {=_xlfn.XLOOKUP(MIN(ABS($BK$3:$BK$23 - MEDIAN(MIN($BK$3:$BK$23), MAX($BK$3:$BK$23), T59))), ABS($BK$3:$BK$23 - MEDIAN(MIN($BK$3:$BK$23), MAX($BK$3:$BK$23), T59)), $BL$3:$BL$23, "Error", 0)} | U88: {=_xlfn.XLOOKUP(MIN(ABS($BK$3:$BK$23 - MEDIAN(MIN($BK$3:$BK$23), MAX($BK$3:$BK$23), U59))), ABS($BK$3:$BK$23 - MEDIAN(MIN($BK$3:$BK$23), MAX($BK$3:$BK$23), U59)), $BL$3:$BL$23, "Error", 0)} | ... BI88: {=_xlfn.XLOOKUP(MIN(ABS($BK$3:$BK$23 - MEDIAN(MIN($BK$3:$BK$23), MAX($BK$3:$BK$23), BI59))), ABS($BK$3:$BK$23 - MEDIAN(MIN($BK$3:$BK$23), MAX($BK$3:$BK$23), BI59)), $BL$3:$BL$23, "Error", 0)}

Sheet Interest Rates data
B1: Interest Rates selected indicators
B2: Country | C2: 44927 | D2: 44958 | E2: 44986 | F2: 45017 | G2: 45047 | H2: 45078 | I2: 45108 | J2: 45139 | K2: 45170 | L2: 45200 | M2: 45231 | N2: 45261 | O2: 45292 | P2: 45323 | Q2: 45352 | R2: 45383 | S2: 45413 | T2: 45444 | U2: 45474 | V2: 45505 | W2: 45536 | X2: 45566 | Y2: 45597 | Z2: 45627 | AA2: 45658 | AB2: 45689 | AC2: 45717 | AD2: 45748 | AE2: 45778 | AF2: 45809 | AG2: 45839 | AH2: 45870 | AI2: 45901 | AJ2: 45931 | AK2: 45962 | AL2: 45992 | AM2: 46023 | AN2: 46054 | AO2: 46082 | AP2: 46113 | AQ2: 46143 | AR2: 46174 | AS2: 46204 | AT2: 46235 | AU2: 46266 | AV2: 46296 | AW2: 46327 | AX2: 46357
B3: Australia | C3: 3.1 | D3: 3.35 | E3: 3.6 | F3: 3.6 | G3: 3.85 | H3: 4.1 | I3: 4.1 | J3: 4.1 | K3: 4.1 | L3: 4.1 | M3: 4.35 | N3: 4.35 | O3: 4.35 | P3: 4.35 | Q3: 4.35 | R3: 4.35 | S3: 4.35 | T3: 4.35 | U3: 4.35 | V3: 4.35 | W3: 4.35 | X3: 4.35 | Y3: 4.35 | Z3: 4.35 | AA3: 4.35 | AB3: 4.1 | AC3: 4.1 | AD3: 4.1 | AE3: 3.85 | AF3: 3.85 | AG3: 3.85 | AH3: 3.6 | AI3: 3.6 | AJ3: 3.6 | AK3: 3.6 | AL3: 3.6 | AM3: 3.6 | AN3: 3.85 | AO3: 3.85 | AP3: 4.1 | AQ3: 4.35 | AR3: 4.35 | AS3: 4.35 | AT3: 4.35 | AU3: 4.35 | AV3: 4.35 | AW3: 4.6 | AX3: Hawkish | AZ3: 7 | BA3: 3
B4: Canada | C4: 4.5 | D4: 4.5 | E4: 4.5 | F4: 4.5 | G4: 4.5 | H4: 4.75 | I4: 5 | J4: 5 | K4: 5 | L4: 5 | M4: 5 | N4: 5 | O4: 5 | P4: 5 | Q4: 5 | R4: 5 | S4: 5 | T4: 4.75 | U4: 4.5 | V4: 4.5 | W4: 4.25 | X4: 3.75 | Y4: 3.75 | Z4: 3.25 | AA4: 3 | AB4: 3 | AC4: 2.75 | AD4: 2.75 | AE4: 2.75 | AF4: 2.75 | AG4: 2.75 | AH4: 2.75 | AI4: 2.5 | AJ4: 2.25 | AK4: 2.25 | AL4: 2.25 | AM4: 2.25 | AN4: 2.25 | AO4: 2.25 | AP4: 2.25 | AQ4: 2.25 | AR4: 2.25 | AS4: 2.25 | AT4: 2.25 | AU4: 2.25 | AV4: 2.25 | AW4: 2.25 | AX4: Neutre | AZ4: 6.5 | BA4: 4
B5: Japan | C5: -0.1 | D5: -0.1 | E5: -0.1 | F5: -0.1 | G5: -0.1 | H5: -0.1 | I5: -0.1 | J5: -0.1 | K5: -0.1 | L5: -0.1 | M5: -0.1 | N5: -0.1 | O5: -0.1 | P5: -0.1 | Q5: 0.1 | R5: 0.1 | S5: 0.1 | T5: 0.1 | U5: 0.25 | V5: 0.25 | W5: 0.25 | X5: 0.25 | Y5: 0.25 | Z5: 0.25 | AA5: 0.5 | AB5: 0.5 | AC5: 0.5 | AD5: 0.5 | AE5: 0.5 | AF5: 0.5 | AG5: 0.5 | AH5: 0.5 | AI5: 0.5 | AJ5: 0.5 | AK5: 0.5 | AL5: 0.75 | AM5: 0.75 | AN5: 0.75 | AO5: 0.75 | AP5: 0.75 | AQ5: 0.75 | AR5: 1 | AS5: 1 | AT5: 1 | AU5: 1 | AV5: 1 | AW5: 1.25 | AX5: Hawkish | AZ5: 6 | BA5: 5
B6: Switzerland | C6: 1 | D6: 1 | E6: 1.5 | F6: 1.5 | G6: 1.5 | H6: 1.75 | I6: 1.75 | J6: 1.75 | K6: 1.75 | L6: 1.75 | M6: 1.75 | N6: 1.75 | O6: 1.75 | P6: 1.75 | Q6: 1.5 | R6: 1.5 | S6: 1.5 | T6: 1.25 | U6: 1.25 | V6: 1.25 | W6: 1 | X6: 1 | Y6: 1 | Z6: 0.5 | AA6: 0.5 | AB6: 0.5 | AC6: 0.25 | AD6: 0.25 | AE6: 0.25 | AF6: 0 | AG6: 0 | AH6: 0 | AI6: 0 | AJ6: 0 | AK6: 0 | AL6: 0 | AM6: 0 | AN6: 0 | AO6: 0 | AP6: 0 | AQ6: 0 | AR6: 0 | AS6: 0 | AT6: 0 | AU6: 0 | AV6: 0 | AW6: 0 | AX6: Neutre | AZ6: 5.5 | BA6: 6
B7: New Zelaand | C7: 4.25 | D7: 4.75 | E7: 4.75 | F7: 5.25 | G7: 5.5 | H7: 5.5 | I7: 5.5 | J7: 5.5 | K7: 5.5 | L7: 5.5 | M7: 5.5 | N7: 5.5 | O7: 5.5 | P7: 5.5 | Q7: 5.5 | R7: 5.5 | S7: 5.5 | T7: 5.5 | U7: 5.5 | V7: 5.25 | W7: 4.75 | X7: 4.75 | Y7: 4.25 | Z7: 4.25 | AA7: 4.25 | AB7: 3.75 | AC7: 3.75 | AD7: 3.5 | AE7: 3.25 | AF7: 3.25 | AG7: 3.25 | AH7: 3 | AI7: 3 | AJ7: 2.5 | AK7: 2.25 | AL7: 2.25 | AM7: 2.25 | AN7: 2.25 | AO7: 2.25 | AP7: 2.25 | AQ7: 2.25 | AR7: 2.25 | AS7: 2.5 | AT7: 2.5 | AU7: 2.75 | AV7: 2.75 | AW7: 3 | AX7: Hawkish | AZ7: 5 | BA7: 10
B8: United Kingdom | C8: 3.5 | D8: 4 | E8: 4.25 | F8: 4.25 | G8: 4.5 | H8: 5 | I8: 5 | J8: 5.25 | K8: 5.25 | L8: 5.25 | M8: 5.25 | N8: 5.25 | O8: 5.25 | P8: 5.25 | Q8: 5.25 | R8: 5.25 | S8: 5.25 | T8: 5.25 | U8: 5.25 | V8: 5 | W8: 5 | X8: 5 | Y8: 4.75 | Z8: 4.75 | AA8: 4.75 | AB8: 4.5 | AC8: 4.5 | AD8: 4.5 | AE8: 4.25 | AF8: 4.25 | AG8: 4.25 | AH8: 4 | AI8: 4 | AJ8: 4 | AK8: 4 | AL8: 3.75 | AM8: 3.75 | AN8: 3.75 | AO8: 3.75 | AP8: 3.75 | AQ8: 3.75 | AR8: 3.75 | AS8: 3.75 | AT8: 3.75 | AU8: 3.75 | AV8: 3.75 | AW8: 3.75 | AX8: Hawkish | AZ8: 4.5 | BA8: 9
B9: United States | C9: 4.5 | D9: 4.75 | E9: 5 | F9: 5 | G9: 5.25 | H9: 5.25 | I9: 5.5 | J9: 5.5 | K9: 5.5 | L9: 5.5 | M9: 5.5 | N9: 5.5 | O9: 5.5 | P9: 5.5 | Q9: 5.5 | R9: 5.5 | S9: 5.5 | T9: 5.5 | U9: 5.5 | V9: 5.5 | W9: 5 | X9: 5 | Y9: 4.75 | Z9: 4.5 | AA9: 4.5 | AB9: 4.5 | AC9: 4.5 | AD9: 4.5 | AE9: 4.5 | AF9: 4.5 | AG9: 4.5 | AH9: 4.5 | AI9: 4.25 | AJ9: 4 | AK9: 4 | AL9: 3.75 | AM9: 3.75 | AN9: 3.75 | AO9: 3.75 | AP9: 3.75 | AQ9: 3.75 | AR9: 3.75 | AS9: 3.75 | AT9: 3.75 | AU9: 3.75 | AV9: 4 | AW9: 4 | AX9: Hawkish | AZ9: 4 | BA9: 8
B10: EURO AREA | C10: 2.5 | D10: 3 | E10: 3.5 | F10: 3.5 | G10: 3.75 | H10: 4 | I10: 4.25 | J10: 4.25 | K10: 4.5 | L10: 4.5 | M10: 4.5 | N10: 4.5 | O10: 4.5 | P10: 4.5 | Q10: 4.5 | R10: 4.5 | S10: 4.5 | T10: 4.25 | U10: 4.25 | V10: 4.25 | W10: 3.65 | X10: 3.4 | Y10: 3.4 | Z10: 3.15 | AA10: 2.9 | AB10: 2.9 | AC10: 2.65 | AD10: 2.4 | AE10: 2.4 | AF10: 2.15 | AG10: 2.15 | AH10: 2.15 | AI10: 2.15 | AJ10: 2.15 | AK10: 2.15 | AL10: 2.15 | AM10: 2.15 | AN10: 2.15 | AO10: 2.15 | AP10: 2.15 | AQ10: 2.15 | AR10: 2.4 | AS10: 2.4 | AT10: 2.4 | AU10: 2.65 | AV10: 2.65 | AW10: 2.65 | AX10: Hawkish | AZ10: 3.5 | BA10: 7
AZ11: 3 | BA11: 6
AZ12: 2.5 | BA12: 5
AZ13: 2 | BA13: 4
B14: SPREAD IR DIFF | C14: 44927 | D14: 44958 | E14: 44986 | F14: 45017 | G14: 45047 | H14: 45078 | I14: 45108 | J14: 45139 | K14: 45170 | L14: 45200 | M14: 45231 | N14: 45261 | O14: 45292 | P14: 45323 | Q14: 45352 | AZ14: 1.5 | BA14: 3
B15: USD JPY | C15: =C9-C5 | D15: =D9-D5 | E15: =E9-E5 | F15: =F9-F5 | G15: =G9-G5 | H15: =H9-H5 | I15: =I9-I5 | J15: =J9-J5 | ... AX15: =AX9-AX5 | AZ15: 1 | BA15: 2
B16: USD CHF | C16: =C9-C6 | D16: =D9-D6 | E16: =E9-E6 | F16: =F9-F6 | G16: =G9-G6 | H16: =H9-H6 | I16: =I9-I6 | J16: =J9-J6 | ... AX16: =AX9-AX6 | AZ16: 0.5 | BA16: 1
B17: USD CAD | C17: =C9-C4 | D17: =D9-D4 | E17: =E9-E4 | F17: =F9-F4 | G17: =G9-G4 | H17: =H9-H4 | I17: =I9-I4 | J17: =J9-J4 | ... AX17: =AX9-AX4 | AZ17: 0 | BA17: 0
B18: EUR USD | C18: =C10-C9 | D18: =D10-D9 | E18: =E10-E9 | F18: =F10-F9 | G18: =G10-G9 | H18: =H10-H9 | I18: =I10-I9 | J18: =J10-J9 | ... AX18: =AX10-AX9 | AZ18: -0.5 | BA18: -1
B19: EUR JPY | C19: =C10-C5 | D19: =D10-D5 | E19: =E10-E5 | F19: =F10-F5 | G19: =G10-G5 | H19: =H10-H5 | I19: =I10-I5 | J19: =J10-J5 | ... AX19: =AX10-AX5 | AZ19: -1 | BA19: -2
B20: EUR CHF | C20: =C10-C6 | D20: =D10-D6 | E20: =E10-E6 | F20: =F10-F6 | G20: =G10-G6 | H20: =H10-H6 | I20: =I10-I6 | J20: =J10-J6 | ... AX20: =AX10-AX6 | AZ20: -1.5 | BA20: -3
B21: EUR GBP | C21: =C10-C8 | D21: =D10-D8 | E21: =E10-E8 | F21: =F10-F8 | G21: =G10-G8 | H21: =H10-H8 | I21: =I10-I8 | J21: =J10-J8 | ... AX21: =AX10-AX8 | AZ21: -2 | BA21: -4
B22: EUR CAD | C22: =C10-C4 | D22: =D10-D4 | E22: =E10-E4 | F22: =F10-F4 | G22: =G10-G4 | H22: =H10-H4 | I22: =I10-I4 | J22: =J10-J4 | ... AX22: =AX10-AX4 | AZ22: -2.5 | BA22: -5
B23: EUR AUD | C23: =C10-C3 | D23: =D10-D3 | E23: =E10-E3 | F23: =F10-F3 | G23: =G10-G3 | H23: =H10-H3 | I23: =I10-I3 | J23: =J10-J3 | ... AX23: =AX10-AX3 | AZ23: -3 | BA23: -6
B24: EUR NZD | C24: =C10-C7 | D24: =D10-D7 | E24: =E10-E7 | F24: =F10-F7 | G24: =G10-G7 | H24: =H10-H7 | I24: =I10-I7 | J24: =J10-J7 | ... AX24: =AX10-AX7 | AZ24: -3.5 | BA24: -7
B25: GBP USD | C25: =C8-C9 | D25: =D8-D9 | E25: =E8-E9 | F25: =F8-F9 | G25: =G8-G9 | H25: =H8-H9 | I25: =I8-I9 | J25: =J8-J9 | ... AX25: =AX8-AX9 | AZ25: -4 | BA25: -8
B26: GBP JPY | C26: =C8-C5 | D26: =D8-D5 | E26: =E8-E5 | F26: =F8-F5 | G26: =G8-G5 | H26: =H8-H5 | I26: =I8-I5 | J26: =J8-J5 | ... AX26: =AX8-AX5 | AZ26: -4.5 | BA26: -9
B27: GBP CHF | C27: =C8-C6 | D27: =D8-D6 | E27: =E8-E6 | F27: =F8-F6 | G27: =G8-G6 | H27: =H8-H6 | I27: =I8-I6 | J27: =J8-J6 | ... AX27: =AX8-AX6 | AZ27: -5 | BA27: -10
B28: GBP CAD | C28: =C8-C4 | D28: =D8-D4 | E28: =E8-E4 | F28: =F8-F4 | G28: =G8-G4 | H28: =H8-H4 | I28: =I8-I4 | J28: =J8-J4 | ... AX28: =AX8-AX4 | AZ28: -5.5 | BA28: -6
B29: GBP AUD | C29: =C8-C3 | D29: =D8-D3 | E29: =E8-E3 | F29: =F8-F3 | G29: =G8-G3 | H29: =H8-H3 | I29: =I8-I3 | J29: =J8-J3 | ... AX29: =AX8-AX3 | AZ29: -6 | BA29: -5
B30: GBP NZD | C30: =C8-C7 | D30: =D8-D7 | E30: =E8-E7 | F30: =F8-F7 | G30: =G8-G7 | H30: =H8-H7 | I30: =I8-I7 | J30: =J8-J7 | ... AX30: =AX8-AX7 | AZ30: -6.5 | BA30: -4
B31: CHF JPY | C31: =C6-C5 | D31: =D6-D5 | E31: =E6-E5 | F31: =F6-F5 | G31: =G6-G5 | H31: =H6-H5 | I31: =I6-I5 | J31: =J6-J5 | ... AX31: =AX6-AX5 | AZ31: -7 | BA31: -3
B32: AUD USD | C32: =C3-C9 | D32: =D3-D9 | E32: =E3-E9 | F32: =F3-F9 | G32: =G3-G9 | H32: =H3-H9 | I32: =I3-I9 | J32: =J3-J9 | ... AX32: =AX3-AX9
B33: AUD CHF | C33: =C3-C6 | D33: =D3-D6 | E33: =E3-E6 | F33: =F3-F6 | G33: =G3-G6 | H33: =H3-H6 | I33: =I3-I6 | J33: =J3-J6 | ... AX33: =AX3-AX6
B34: AUD JPY | C34: =C3-C5 | D34: =D3-D5 | E34: =E3-E5 | F34: =F3-F5 | G34: =G3-G5 | H34: =H3-H5 | I34: =I3-I5 | J34: =J3-J5 | ... AX34: =AX3-AX5
B35: AUD NZD | C35: =C3-C7 | D35: =D3-D7 | E35: =E3-E7 | F35: =F3-F7 | G35: =G3-G7 | H35: =H3-H7 | I35: =I3-I7 | J35: =J3-J7 | ... AX35: =AX3-AX7
B36: AUD CAD | C36: =C3-C4 | D36: =D3-D4 | E36: =E3-E4 | F36: =F3-F4 | G36: =G3-G4 | H36: =H3-H4 | I36: =I3-I4 | J36: =J3-J4 | ... AX36: =AX3-AX4
B37: CAD JPY | C37: =C4-C5 | D37: =D4-D5 | E37: =E4-E5 | F37: =F4-F5 | G37: =G4-G5 | H37: =H4-H5 | I37: =I4-I5 | J37: =J4-J5 | ... AX37: =AX4-AX5
B44: SPREAD IR DIFF | C44: 44927 | D44: 44958 | E44: 44986 | F44: 45017 | G44: 45047 | H44: 45078 | I44: 45108 | J44: 45139 | K44: 45170 | L44: 45200 | M44: 45231 | N44: 45261 | O44: 45292 | P44: 45323 | Q44: 45352 | R44: 45383 | S44: 45413 | T44: 45444 | U44: 45474 | V44: 45505 | W44: 45536 | X44: 45566 | Y44: 45597 | Z44: 45627 | AA44: 45658 | AB44: 45689 | AC44: 45717 | AD44: 45748 | AE44: 45778 | AF44: 45809 | AG44: 45839 | AH44: 45870 | AI44: 45901 | AJ44: 45931 | AK44: 45962 | AL44: 45992 | AM44: 46023 | AN44: 46054 | AO44: 46082 | AP44: 46113 | AQ44: 46143 | AR44: 46174 | AS44: 46204 | AT44: 46235 | AU44: 46266 | AV44: 46296 | AW44: 46327 | AX44: 46357
B45: USD JPY | C45: {=_xlfn.XLOOKUP(MIN(ABS($AZ$3:$AZ$31 - MEDIAN(MIN($AZ$3:$AZ$31), MAX($AZ$3:$AZ$31), C15))), ABS($AZ$3:$AZ$31 - MEDIAN(MIN($AZ$3:$AZ$31), MAX($AZ$3:$AZ$31), C15)), $BA$3:$BA$31, "Error", 0)} | D45: {=_xlfn.XLOOKUP(MIN(ABS($AZ$3:$AZ$31 - MEDIAN(MIN($AZ$3:$AZ$31), MAX($AZ$3:$AZ$31), D15))), ABS($AZ$3:$AZ$31 - MEDIAN(MIN($AZ$3:$AZ$31), MAX($AZ$3:$AZ$31), D15)), $BA$3:$BA$31, "Error", 0)} | E45: {=_xlfn.XLOOKUP(MIN(ABS($AZ$3:$AZ$31 - MEDIAN(MIN($AZ$3:$AZ$31), MAX($AZ$3:$AZ$31), E15))), ABS($AZ$3:$AZ$31 - MEDIAN(MIN($AZ$3:$AZ$31), MAX($AZ$3:$AZ$31), E15)), $BA$3:$BA$31, "Error", 0)} | F45: {=_xlfn.XLOOKUP(MIN(ABS($AZ$3:$AZ$31 - MEDIAN(MIN($AZ$3:$AZ$31), MAX($AZ$3:$AZ$31), F15))), ABS($AZ$3:$AZ$31 - MEDIAN(MIN($AZ$3:$AZ$31), MAX($AZ$3:$AZ$31), F15)), $BA$3:$BA$31, "Error", 0)} | G45: {=_xlfn.XLOOKUP(MIN(ABS($AZ$3:$AZ$31 - MEDIAN(MIN($AZ$3:$AZ$31), MAX($AZ$3:$AZ$31), G15))), ABS($AZ$3:$AZ$31 - MEDIAN(MIN($AZ$3:$AZ$31), MAX($AZ$3:$AZ$31), G15)), $BA$3:$BA$31, "Error", 0)} | H45: {=_xlfn.XLOOKUP(MIN(ABS($AZ$3:$AZ$31 - MEDIAN(MIN($AZ$3:$AZ$31), MAX($AZ$3:$AZ$31), H15))), ABS($AZ$3:$AZ$31 - MEDIAN(MIN($AZ$3:$AZ$31), MAX($AZ$3:$AZ$31), H15)), $BA$3:$BA$31, "Error", 0)} | I45: {=_xlfn.XLOOKUP(MIN(ABS($AZ$3:$AZ$31 - MEDIAN(MIN($AZ$3:$AZ$31), MAX($AZ$3:$AZ$31), I15))), ABS($AZ$3:$AZ$31 - MEDIAN(MIN($AZ$3:$AZ$31), MAX($AZ$3:$AZ$31), I15)), $BA$3:$BA$31, "Error", 0)} | J45: {=_xlfn.XLOOKUP(MIN(ABS($AZ$3:$AZ$31 - MEDIAN(MIN($AZ$3:$AZ$31), MAX($AZ$3:$AZ$31), J15))), ABS($AZ$3:$AZ$31 - MEDIAN(MIN($AZ$3:$AZ$31), MAX($AZ$3:$AZ$31), J15)), $BA$3:$BA$31, "Error", 0)} | ... AX45: {=_xlfn.XLOOKUP(MIN(ABS($AZ$3:$AZ$31 - MEDIAN(MIN($AZ$3:$AZ$31), MAX($AZ$3:$AZ$31), AX15))), ABS($AZ$3:$AZ$31 - MEDIAN(MIN($AZ$3:$AZ$31), MAX($AZ$3:$AZ$31), AX15)), $BA$3:$BA$31, "Error", 0)}
B46: USD CHF | C46: {=_xlfn.XLOOKUP(MIN(ABS($AZ$3:$AZ$31 - MEDIAN(MIN($AZ$3:$AZ$31), MAX($AZ$3:$AZ$31), C16))), ABS($AZ$3:$AZ$31 - MEDIAN(MIN($AZ$3:$AZ$31), MAX($AZ$3:$AZ$31), C16)), $BA$3:$BA$31, "Error", 0)} | D46: {=_xlfn.XLOOKUP(MIN(ABS($AZ$3:$AZ$31 - MEDIAN(MIN($AZ$3:$AZ$31), MAX($AZ$3:$AZ$31), D16))), ABS($AZ$3:$AZ$31 - MEDIAN(MIN($AZ$3:$AZ$31), MAX($AZ$3:$AZ$31), D16)), $BA$3:$BA$31, "Error", 0)} | E46: {=_xlfn.XLOOKUP(MIN(ABS($AZ$3:$AZ$31 - MEDIAN(MIN($AZ$3:$AZ$31), MAX($AZ$3:$AZ$31), E16))), ABS($AZ$3:$AZ$31 - MEDIAN(MIN($AZ$3:$AZ$31), MAX($AZ$3:$AZ$31), E16)), $BA$3:$BA$31, "Error", 0)} | F46: {=_xlfn.XLOOKUP(MIN(ABS($AZ$3:$AZ$31 - MEDIAN(MIN($AZ$3:$AZ$31), MAX($AZ$3:$AZ$31), F16))), ABS($AZ$3:$AZ$31 - MEDIAN(MIN($AZ$3:$AZ$31), MAX($AZ$3:$AZ$31), F16)), $BA$3:$BA$31, "Error", 0)} | G46: {=_xlfn.XLOOKUP(MIN(ABS($AZ$3:$AZ$31 - MEDIAN(MIN($AZ$3:$AZ$31), MAX($AZ$3:$AZ$31), G16))), ABS($AZ$3:$AZ$31 - MEDIAN(MIN($AZ$3:$AZ$31), MAX($AZ$3:$AZ$31), G16)), $BA$3:$BA$31, "Error", 0)} | H46: {=_xlfn.XLOOKUP(MIN(ABS($AZ$3:$AZ$31 - MEDIAN(MIN($AZ$3:$AZ$31), MAX($AZ$3:$AZ$31), H16))), ABS($AZ$3:$AZ$31 - MEDIAN(MIN($AZ$3:$AZ$31), MAX($AZ$3:$AZ$31), H16)), $BA$3:$BA$31, "Error", 0)} | I46: {=_xlfn.XLOOKUP(MIN(ABS($AZ$3:$AZ$31 - MEDIAN(MIN($AZ$3:$AZ$31), MAX($AZ$3:$AZ$31), I16))), ABS($AZ$3:$AZ$31 - MEDIAN(MIN($AZ$3:$AZ$31), MAX($AZ$3:$AZ$31), I16)), $BA$3:$BA$31, "Error", 0)} | J46: {=_xlfn.XLOOKUP(MIN(ABS($AZ$3:$AZ$31 - MEDIAN(MIN($AZ$3:$AZ$31), MAX($AZ$3:$AZ$31), J16))), ABS($AZ$3:$AZ$31 - MEDIAN(MIN($AZ$3:$AZ$31), MAX($AZ$3:$AZ$31), J16)), $BA$3:$BA$31, "Error", 0)} | ... AX46: {=_xlfn.XLOOKUP(MIN(ABS($AZ$3:$AZ$31 - MEDIAN(MIN($AZ$3:$AZ$31), MAX($AZ$3:$AZ$31), AX16))), ABS($AZ$3:$AZ$31 - MEDIAN(MIN($AZ$3:$AZ$31), MAX($AZ$3:$AZ$31), AX16)), $BA$3:$BA$31, "Error", 0)}
B47: USD CAD | C47: {=_xlfn.XLOOKUP(MIN(ABS($AZ$3:$AZ$31 - MEDIAN(MIN($AZ$3:$AZ$31), MAX($AZ$3:$AZ$31), C17))), ABS($AZ$3:$AZ$31 - MEDIAN(MIN($AZ$3:$AZ$31), MAX($AZ$3:$AZ$31), C17)), $BA$3:$BA$31, "Error", 0)} | D47: {=_xlfn.XLOOKUP(MIN(ABS($AZ$3:$AZ$31 - MEDIAN(MIN($AZ$3:$AZ$31), MAX($AZ$3:$AZ$31), D17))), ABS($AZ$3:$AZ$31 - MEDIAN(MIN($AZ$3:$AZ$31), MAX($AZ$3:$AZ$31), D17)), $BA$3:$BA$31, "Error", 0)} | E47: {=_xlfn.XLOOKUP(MIN(ABS($AZ$3:$AZ$31 - MEDIAN(MIN($AZ$3:$AZ$31), MAX($AZ$3:$AZ$31), E17))), ABS($AZ$3:$AZ$31 - MEDIAN(MIN($AZ$3:$AZ$31), MAX($AZ$3:$AZ$31), E17)), $BA$3:$BA$31, "Error", 0)} | F47: {=_xlfn.XLOOKUP(MIN(ABS($AZ$3:$AZ$31 - MEDIAN(MIN($AZ$3:$AZ$31), MAX($AZ$3:$AZ$31), F17))), ABS($AZ$3:$AZ$31 - MEDIAN(MIN($AZ$3:$AZ$31), MAX($AZ$3:$AZ$31), F17)), $BA$3:$BA$31, "Error", 0)} | G47: {=_xlfn.XLOOKUP(MIN(ABS($AZ$3:$AZ$31 - MEDIAN(MIN($AZ$3:$AZ$31), MAX($AZ$3:$AZ$31), G17))), ABS($AZ$3:$AZ$31 - MEDIAN(MIN($AZ$3:$AZ$31), MAX($AZ$3:$AZ$31), G17)), $BA$3:$BA$31, "Error", 0)} | H47: {=_xlfn.XLOOKUP(MIN(ABS($AZ$3:$AZ$31 - MEDIAN(MIN($AZ$3:$AZ$31), MAX($AZ$3:$AZ$31), H17))), ABS($AZ$3:$AZ$31 - MEDIAN(MIN($AZ$3:$AZ$31), MAX($AZ$3:$AZ$31), H17)), $BA$3:$BA$31, "Error", 0)} | I47: {=_xlfn.XLOOKUP(MIN(ABS($AZ$3:$AZ$31 - MEDIAN(MIN($AZ$3:$AZ$31), MAX($AZ$3:$AZ$31), I17))), ABS($AZ$3:$AZ$31 - MEDIAN(MIN($AZ$3:$AZ$31), MAX($AZ$3:$AZ$31), I17)), $BA$3:$BA$31, "Error", 0)} | J47: {=_xlfn.XLOOKUP(MIN(ABS($AZ$3:$AZ$31 - MEDIAN(MIN($AZ$3:$AZ$31), MAX($AZ$3:$AZ$31), J17))), ABS($AZ$3:$AZ$31 - MEDIAN(MIN($AZ$3:$AZ$31), MAX($AZ$3:$AZ$31), J17)), $BA$3:$BA$31, "Error", 0)} | ... AX47: {=_xlfn.XLOOKUP(MIN(ABS($AZ$3:$AZ$31 - MEDIAN(MIN($AZ$3:$AZ$31), MAX($AZ$3:$AZ$31), AX17))), ABS($AZ$3:$AZ$31 - MEDIAN(MIN($AZ$3:$AZ$31), MAX($AZ$3:$AZ$31), AX17)), $BA$3:$BA$31, "Error", 0)}
B48: EUR USD | C48: {=_xlfn.XLOOKUP(MIN(ABS($AZ$3:$AZ$31 - MEDIAN(MIN($AZ$3:$AZ$31), MAX($AZ$3:$AZ$31), C18))), ABS($AZ$3:$AZ$31 - MEDIAN(MIN($AZ$3:$AZ$31), MAX($AZ$3:$AZ$31), C18)), $BA$3:$BA$31, "Error", 0)} | D48: {=_xlfn.XLOOKUP(MIN(ABS($AZ$3:$AZ$31 - MEDIAN(MIN($AZ$3:$AZ$31), MAX($AZ$3:$AZ$31), D18))), ABS($AZ$3:$AZ$31 - MEDIAN(MIN($AZ$3:$AZ$31), MAX($AZ$3:$AZ$31), D18)), $BA$3:$BA$31, "Error", 0)} | E48: {=_xlfn.XLOOKUP(MIN(ABS($AZ$3:$AZ$31 - MEDIAN(MIN($AZ$3:$AZ$31), MAX($AZ$3:$AZ$31), E18))), ABS($AZ$3:$AZ$31 - MEDIAN(MIN($AZ$3:$AZ$31), MAX($AZ$3:$AZ$31), E18)), $BA$3:$BA$31, "Error", 0)} | F48: {=_xlfn.XLOOKUP(MIN(ABS($AZ$3:$AZ$31 - MEDIAN(MIN($AZ$3:$AZ$31), MAX($AZ$3:$AZ$31), F18))), ABS($AZ$3:$AZ$31 - MEDIAN(MIN($AZ$3:$AZ$31), MAX($AZ$3:$AZ$31), F18)), $BA$3:$BA$31, "Error", 0)} | G48: {=_xlfn.XLOOKUP(MIN(ABS($AZ$3:$AZ$31 - MEDIAN(MIN($AZ$3:$AZ$31), MAX($AZ$3:$AZ$31), G18))), ABS($AZ$3:$AZ$31 - MEDIAN(MIN($AZ$3:$AZ$31), MAX($AZ$3:$AZ$31), G18)), $BA$3:$BA$31, "Error", 0)} | H48: {=_xlfn.XLOOKUP(MIN(ABS($AZ$3:$AZ$31 - MEDIAN(MIN($AZ$3:$AZ$31), MAX($AZ$3:$AZ$31), H18))), ABS($AZ$3:$AZ$31 - MEDIAN(MIN($AZ$3:$AZ$31), MAX($AZ$3:$AZ$31), H18)), $BA$3:$BA$31, "Error", 0)} | I48: {=_xlfn.XLOOKUP(MIN(ABS($AZ$3:$AZ$31 - MEDIAN(MIN($AZ$3:$AZ$31), MAX($AZ$3:$AZ$31), I18))), ABS($AZ$3:$AZ$31 - MEDIAN(MIN($AZ$3:$AZ$31), MAX($AZ$3:$AZ$31), I18)), $BA$3:$BA$31, "Error", 0)} | J48: {=_xlfn.XLOOKUP(MIN(ABS($AZ$3:$AZ$31 - MEDIAN(MIN($AZ$3:$AZ$31), MAX($AZ$3:$AZ$31), J18))), ABS($AZ$3:$AZ$31 - MEDIAN(MIN($AZ$3:$AZ$31), MAX($AZ$3:$AZ$31), J18)), $BA$3:$BA$31, "Error", 0)} | ... AX48: {=_xlfn.XLOOKUP(MIN(ABS($AZ$3:$AZ$31 - MEDIAN(MIN($AZ$3:$AZ$31), MAX($AZ$3:$AZ$31), AX18))), ABS($AZ$3:$AZ$31 - MEDIAN(MIN($AZ$3:$AZ$31), MAX($AZ$3:$AZ$31), AX18)), $BA$3:$BA$31, "Error", 0)}
B49: EUR JPY | C49: {=_xlfn.XLOOKUP(MIN(ABS($AZ$3:$AZ$31 - MEDIAN(MIN($AZ$3:$AZ$31), MAX($AZ$3:$AZ$31), C19))), ABS($AZ$3:$AZ$31 - MEDIAN(MIN($AZ$3:$AZ$31), MAX($AZ$3:$AZ$31), C19)), $BA$3:$BA$31, "Error", 0)} | D49: {=_xlfn.XLOOKUP(MIN(ABS($AZ$3:$AZ$31 - MEDIAN(MIN($AZ$3:$AZ$31), MAX($AZ$3:$AZ$31), D19))), ABS($AZ$3:$AZ$31 - MEDIAN(MIN($AZ$3:$AZ$31), MAX($AZ$3:$AZ$31), D19)), $BA$3:$BA$31, "Error", 0)} | E49: {=_xlfn.XLOOKUP(MIN(ABS($AZ$3:$AZ$31 - MEDIAN(MIN($AZ$3:$AZ$31), MAX($AZ$3:$AZ$31), E19))), ABS($AZ$3:$AZ$31 - MEDIAN(MIN($AZ$3:$AZ$31), MAX($AZ$3:$AZ$31), E19)), $BA$3:$BA$31, "Error", 0)} | F49: {=_xlfn.XLOOKUP(MIN(ABS($AZ$3:$AZ$31 - MEDIAN(MIN($AZ$3:$AZ$31), MAX($AZ$3:$AZ$31), F19))), ABS($AZ$3:$AZ$31 - MEDIAN(MIN($AZ$3:$AZ$31), MAX($AZ$3:$AZ$31), F19)), $BA$3:$BA$31, "Error", 0)} | G49: {=_xlfn.XLOOKUP(MIN(ABS($AZ$3:$AZ$31 - MEDIAN(MIN($AZ$3:$AZ$31), MAX($AZ$3:$AZ$31), G19))), ABS($AZ$3:$AZ$31 - MEDIAN(MIN($AZ$3:$AZ$31), MAX($AZ$3:$AZ$31), G19)), $BA$3:$BA$31, "Error", 0)} | H49: {=_xlfn.XLOOKUP(MIN(ABS($AZ$3:$AZ$31 - MEDIAN(MIN($AZ$3:$AZ$31), MAX($AZ$3:$AZ$31), H19))), ABS($AZ$3:$AZ$31 - MEDIAN(MIN($AZ$3:$AZ$31), MAX($AZ$3:$AZ$31), H19)), $BA$3:$BA$31, "Error", 0)} | I49: {=_xlfn.XLOOKUP(MIN(ABS($AZ$3:$AZ$31 - MEDIAN(MIN($AZ$3:$AZ$31), MAX($AZ$3:$AZ$31), I19))), ABS($AZ$3:$AZ$31 - MEDIAN(MIN($AZ$3:$AZ$31), MAX($AZ$3:$AZ$31), I19)), $BA$3:$BA$31, "Error", 0)} | J49: {=_xlfn.XLOOKUP(MIN(ABS($AZ$3:$AZ$31 - MEDIAN(MIN($AZ$3:$AZ$31), MAX($AZ$3:$AZ$31), J19))), ABS($AZ$3:$AZ$31 - MEDIAN(MIN($AZ$3:$AZ$31), MAX($AZ$3:$AZ$31), J19)), $BA$3:$BA$31, "Error", 0)} | ... AX49: {=_xlfn.XLOOKUP(MIN(ABS($AZ$3:$AZ$31 - MEDIAN(MIN($AZ$3:$AZ$31), MAX($AZ$3:$AZ$31), AX19))), ABS($AZ$3:$AZ$31 - MEDIAN(MIN($AZ$3:$AZ$31), MAX($AZ$3:$AZ$31), AX19)), $BA$3:$BA$31, "Error", 0)}
B50: EUR CHF | C50: {=_xlfn.XLOOKUP(MIN(ABS($AZ$3:$AZ$31 - MEDIAN(MIN($AZ$3:$AZ$31), MAX($AZ$3:$AZ$31), C20))), ABS($AZ$3:$AZ$31 - MEDIAN(MIN($AZ$3:$AZ$31), MAX($AZ$3:$AZ$31), C20)), $BA$3:$BA$31, "Error", 0)} | D50: {=_xlfn.XLOOKUP(MIN(ABS($AZ$3:$AZ$31 - MEDIAN(MIN($AZ$3:$AZ$31), MAX($AZ$3:$AZ$31), D20))), ABS($AZ$3:$AZ$31 - MEDIAN(MIN($AZ$3:$AZ$31), MAX($AZ$3:$AZ$31), D20)), $BA$3:$BA$31, "Error", 0)} | E50: {=_xlfn.XLOOKUP(MIN(ABS($AZ$3:$AZ$31 - MEDIAN(MIN($AZ$3:$AZ$31), MAX($AZ$3:$AZ$31), E20))), ABS($AZ$3:$AZ$31 - MEDIAN(MIN($AZ$3:$AZ$31), MAX($AZ$3:$AZ$31), E20)), $BA$3:$BA$31, "Error", 0)} | F50: {=_xlfn.XLOOKUP(MIN(ABS($AZ$3:$AZ$31 - MEDIAN(MIN($AZ$3:$AZ$31), MAX($AZ$3:$AZ$31), F20))), ABS($AZ$3:$AZ$31 - MEDIAN(MIN($AZ$3:$AZ$31), MAX($AZ$3:$AZ$31), F20)), $BA$3:$BA$31, "Error", 0)} | G50: {=_xlfn.XLOOKUP(MIN(ABS($AZ$3:$AZ$31 - MEDIAN(MIN($AZ$3:$AZ$31), MAX($AZ$3:$AZ$31), G20))), ABS($AZ$3:$AZ$31 - MEDIAN(MIN($AZ$3:$AZ$31), MAX($AZ$3:$AZ$31), G20)), $BA$3:$BA$31, "Error", 0)} | H50: {=_xlfn.XLOOKUP(MIN(ABS($AZ$3:$AZ$31 - MEDIAN(MIN($AZ$3:$AZ$31), MAX($AZ$3:$AZ$31), H20))), ABS($AZ$3:$AZ$31 - MEDIAN(MIN($AZ$3:$AZ$31), MAX($AZ$3:$AZ$31), H20)), $BA$3:$BA$31, "Error", 0)} | I50: {=_xlfn.XLOOKUP(MIN(ABS($AZ$3:$AZ$31 - MEDIAN(MIN($AZ$3:$AZ$31), MAX($AZ$3:$AZ$31), I20))), ABS($AZ$3:$AZ$31 - MEDIAN(MIN($AZ$3:$AZ$31), MAX($AZ$3:$AZ$31), I20)), $BA$3:$BA$31, "Error", 0)} | J50: {=_xlfn.XLOOKUP(MIN(ABS($AZ$3:$AZ$31 - MEDIAN(MIN($AZ$3:$AZ$31), MAX($AZ$3:$AZ$31), J20))), ABS($AZ$3:$AZ$31 - MEDIAN(MIN($AZ$3:$AZ$31), MAX($AZ$3:$AZ$31), J20)), $BA$3:$BA$31, "Error", 0)} | ... AX50: {=_xlfn.XLOOKUP(MIN(ABS($AZ$3:$AZ$31 - MEDIAN(MIN($AZ$3:$AZ$31), MAX($AZ$3:$AZ$31), AX20))), ABS($AZ$3:$AZ$31 - MEDIAN(MIN($AZ$3:$AZ$31), MAX($AZ$3:$AZ$31), AX20)), $BA$3:$BA$31, "Error", 0)}
B51: EUR GBP | C51: {=_xlfn.XLOOKUP(MIN(ABS($AZ$3:$AZ$31 - MEDIAN(MIN($AZ$3:$AZ$31), MAX($AZ$3:$AZ$31), C21))), ABS($AZ$3:$AZ$31 - MEDIAN(MIN($AZ$3:$AZ$31), MAX($AZ$3:$AZ$31), C21)), $BA$3:$BA$31, "Error", 0)} | D51: {=_xlfn.XLOOKUP(MIN(ABS($AZ$3:$AZ$31 - MEDIAN(MIN($AZ$3:$AZ$31), MAX($AZ$3:$AZ$31), D21))), ABS($AZ$3:$AZ$31 - MEDIAN(MIN($AZ$3:$AZ$31), MAX($AZ$3:$AZ$31), D21)), $BA$3:$BA$31, "Error", 0)} | E51: {=_xlfn.XLOOKUP(MIN(ABS($AZ$3:$AZ$31 - MEDIAN(MIN($AZ$3:$AZ$31), MAX($AZ$3:$AZ$31), E21))), ABS($AZ$3:$AZ$31 - MEDIAN(MIN($AZ$3:$AZ$31), MAX($AZ$3:$AZ$31), E21)), $BA$3:$BA$31, "Error", 0)} | F51: {=_xlfn.XLOOKUP(MIN(ABS($AZ$3:$AZ$31 - MEDIAN(MIN($AZ$3:$AZ$31), MAX($AZ$3:$AZ$31), F21))), ABS($AZ$3:$AZ$31 - MEDIAN(MIN($AZ$3:$AZ$31), MAX($AZ$3:$AZ$31), F21)), $BA$3:$BA$31, "Error", 0)} | G51: {=_xlfn.XLOOKUP(MIN(ABS($AZ$3:$AZ$31 - MEDIAN(MIN($AZ$3:$AZ$31), MAX($AZ$3:$AZ$31), G21))), ABS($AZ$3:$AZ$31 - MEDIAN(MIN($AZ$3:$AZ$31), MAX($AZ$3:$AZ$31), G21)), $BA$3:$BA$31, "Error", 0)} | H51: {=_xlfn.XLOOKUP(MIN(ABS($AZ$3:$AZ$31 - MEDIAN(MIN($AZ$3:$AZ$31), MAX($AZ$3:$AZ$31), H21))), ABS($AZ$3:$AZ$31 - MEDIAN(MIN($AZ$3:$AZ$31), MAX($AZ$3:$AZ$31), H21)), $BA$3:$BA$31, "Error", 0)} | I51: {=_xlfn.XLOOKUP(MIN(ABS($AZ$3:$AZ$31 - MEDIAN(MIN($AZ$3:$AZ$31), MAX($AZ$3:$AZ$31), I21))), ABS($AZ$3:$AZ$31 - MEDIAN(MIN($AZ$3:$AZ$31), MAX($AZ$3:$AZ$31), I21)), $BA$3:$BA$31, "Error", 0)} | J51: {=_xlfn.XLOOKUP(MIN(ABS($AZ$3:$AZ$31 - MEDIAN(MIN($AZ$3:$AZ$31), MAX($AZ$3:$AZ$31), J21))), ABS($AZ$3:$AZ$31 - MEDIAN(MIN($AZ$3:$AZ$31), MAX($AZ$3:$AZ$31), J21)), $BA$3:$BA$31, "Error", 0)} | ... AX51: {=_xlfn.XLOOKUP(MIN(ABS($AZ$3:$AZ$31 - MEDIAN(MIN($AZ$3:$AZ$31), MAX($AZ$3:$AZ$31), AX21))), ABS($AZ$3:$AZ$31 - MEDIAN(MIN($AZ$3:$AZ$31), MAX($AZ$3:$AZ$31), AX21)), $BA$3:$BA$31, "Error", 0)}
B52: EUR CAD | C52: {=_xlfn.XLOOKUP(MIN(ABS($AZ$3:$AZ$31 - MEDIAN(MIN($AZ$3:$AZ$31), MAX($AZ$3:$AZ$31), C22))), ABS($AZ$3:$AZ$31 - MEDIAN(MIN($AZ$3:$AZ$31), MAX($AZ$3:$AZ$31), C22)), $BA$3:$BA$31, "Error", 0)} | D52: {=_xlfn.XLOOKUP(MIN(ABS($AZ$3:$AZ$31 - MEDIAN(MIN($AZ$3:$AZ$31), MAX($AZ$3:$AZ$31), D22))), ABS($AZ$3:$AZ$31 - MEDIAN(MIN($AZ$3:$AZ$31), MAX($AZ$3:$AZ$31), D22)), $BA$3:$BA$31, "Error", 0)} | E52: {=_xlfn.XLOOKUP(MIN(ABS($AZ$3:$AZ$31 - MEDIAN(MIN($AZ$3:$AZ$31), MAX($AZ$3:$AZ$31), E22))), ABS($AZ$3:$AZ$31 - MEDIAN(MIN($AZ$3:$AZ$31), MAX($AZ$3:$AZ$31), E22)), $BA$3:$BA$31, "Error", 0)} | F52: {=_xlfn.XLOOKUP(MIN(ABS($AZ$3:$AZ$31 - MEDIAN(MIN($AZ$3:$AZ$31), MAX($AZ$3:$AZ$31), F22))), ABS($AZ$3:$AZ$31 - MEDIAN(MIN($AZ$3:$AZ$31), MAX($AZ$3:$AZ$31), F22)), $BA$3:$BA$31, "Error", 0)} | G52: {=_xlfn.XLOOKUP(MIN(ABS($AZ$3:$AZ$31 - MEDIAN(MIN($AZ$3:$AZ$31), MAX($AZ$3:$AZ$31), G22))), ABS($AZ$3:$AZ$31 - MEDIAN(MIN($AZ$3:$AZ$31), MAX($AZ$3:$AZ$31), G22)), $BA$3:$BA$31, "Error", 0)} | H52: {=_xlfn.XLOOKUP(MIN(ABS($AZ$3:$AZ$31 - MEDIAN(MIN($AZ$3:$AZ$31), MAX($AZ$3:$AZ$31), H22))), ABS($AZ$3:$AZ$31 - MEDIAN(MIN($AZ$3:$AZ$31), MAX($AZ$3:$AZ$31), H22)), $BA$3:$BA$31, "Error", 0)} | I52: {=_xlfn.XLOOKUP(MIN(ABS($AZ$3:$AZ$31 - MEDIAN(MIN($AZ$3:$AZ$31), MAX($AZ$3:$AZ$31), I22))), ABS($AZ$3:$AZ$31 - MEDIAN(MIN($AZ$3:$AZ$31), MAX($AZ$3:$AZ$31), I22)), $BA$3:$BA$31, "Error", 0)} | J52: {=_xlfn.XLOOKUP(MIN(ABS($AZ$3:$AZ$31 - MEDIAN(MIN($AZ$3:$AZ$31), MAX($AZ$3:$AZ$31), J22))), ABS($AZ$3:$AZ$31 - MEDIAN(MIN($AZ$3:$AZ$31), MAX($AZ$3:$AZ$31), J22)), $BA$3:$BA$31, "Error", 0)} | ... AX52: {=_xlfn.XLOOKUP(MIN(ABS($AZ$3:$AZ$31 - MEDIAN(MIN($AZ$3:$AZ$31), MAX($AZ$3:$AZ$31), AX22))), ABS($AZ$3:$AZ$31 - MEDIAN(MIN($AZ$3:$AZ$31), MAX($AZ$3:$AZ$31), AX22)), $BA$3:$BA$31, "Error", 0)}
B53: EUR AUD | C53: {=_xlfn.XLOOKUP(MIN(ABS($AZ$3:$AZ$31 - MEDIAN(MIN($AZ$3:$AZ$31), MAX($AZ$3:$AZ$31), C23))), ABS($AZ$3:$AZ$31 - MEDIAN(MIN($AZ$3:$AZ$31), MAX($AZ$3:$AZ$31), C23)), $BA$3:$BA$31, "Error", 0)} | D53: {=_xlfn.XLOOKUP(MIN(ABS($AZ$3:$AZ$31 - MEDIAN(MIN($AZ$3:$AZ$31), MAX($AZ$3:$AZ$31), D23))), ABS($AZ$3:$AZ$31 - MEDIAN(MIN($AZ$3:$AZ$31), MAX($AZ$3:$AZ$31), D23)), $BA$3:$BA$31, "Error", 0)} | E53: {=_xlfn.XLOOKUP(MIN(ABS($AZ$3:$AZ$31 - MEDIAN(MIN($AZ$3:$AZ$31), MAX($AZ$3:$AZ$31), E23))), ABS($AZ$3:$AZ$31 - MEDIAN(MIN($AZ$3:$AZ$31), MAX($AZ$3:$AZ$31), E23)), $BA$3:$BA$31, "Error", 0)} | F53: {=_xlfn.XLOOKUP(MIN(ABS($AZ$3:$AZ$31 - MEDIAN(MIN($AZ$3:$AZ$31), MAX($AZ$3:$AZ$31), F23))), ABS($AZ$3:$AZ$31 - MEDIAN(MIN($AZ$3:$AZ$31), MAX($AZ$3:$AZ$31), F23)), $BA$3:$BA$31, "Error", 0)} | G53: {=_xlfn.XLOOKUP(MIN(ABS($AZ$3:$AZ$31 - MEDIAN(MIN($AZ$3:$AZ$31), MAX($AZ$3:$AZ$31), G23))), ABS($AZ$3:$AZ$31 - MEDIAN(MIN($AZ$3:$AZ$31), MAX($AZ$3:$AZ$31), G23)), $BA$3:$BA$31, "Error", 0)} | H53: {=_xlfn.XLOOKUP(MIN(ABS($AZ$3:$AZ$31 - MEDIAN(MIN($AZ$3:$AZ$31), MAX($AZ$3:$AZ$31), H23))), ABS($AZ$3:$AZ$31 - MEDIAN(MIN($AZ$3:$AZ$31), MAX($AZ$3:$AZ$31), H23)), $BA$3:$BA$31, "Error", 0)} | I53: {=_xlfn.XLOOKUP(MIN(ABS($AZ$3:$AZ$31 - MEDIAN(MIN($AZ$3:$AZ$31), MAX($AZ$3:$AZ$31), I23))), ABS($AZ$3:$AZ$31 - MEDIAN(MIN($AZ$3:$AZ$31), MAX($AZ$3:$AZ$31), I23)), $BA$3:$BA$31, "Error", 0)} | J53: {=_xlfn.XLOOKUP(MIN(ABS($AZ$3:$AZ$31 - MEDIAN(MIN($AZ$3:$AZ$31), MAX($AZ$3:$AZ$31), J23))), ABS($AZ$3:$AZ$31 - MEDIAN(MIN($AZ$3:$AZ$31), MAX($AZ$3:$AZ$31), J23)), $BA$3:$BA$31, "Error", 0)} | ... AX53: {=_xlfn.XLOOKUP(MIN(ABS($AZ$3:$AZ$31 - MEDIAN(MIN($AZ$3:$AZ$31), MAX($AZ$3:$AZ$31), AX23))), ABS($AZ$3:$AZ$31 - MEDIAN(MIN($AZ$3:$AZ$31), MAX($AZ$3:$AZ$31), AX23)), $BA$3:$BA$31, "Error", 0)}
B54: EUR NZD | C54: {=_xlfn.XLOOKUP(MIN(ABS($AZ$3:$AZ$31 - MEDIAN(MIN($AZ$3:$AZ$31), MAX($AZ$3:$AZ$31), C24))), ABS($AZ$3:$AZ$31 - MEDIAN(MIN($AZ$3:$AZ$31), MAX($AZ$3:$AZ$31), C24)), $BA$3:$BA$31, "Error", 0)} | D54: {=_xlfn.XLOOKUP(MIN(ABS($AZ$3:$AZ$31 - MEDIAN(MIN($AZ$3:$AZ$31), MAX($AZ$3:$AZ$31), D24))), ABS($AZ$3:$AZ$31 - MEDIAN(MIN($AZ$3:$AZ$31), MAX($AZ$3:$AZ$31), D24)), $BA$3:$BA$31, "Error", 0)} | E54: {=_xlfn.XLOOKUP(MIN(ABS($AZ$3:$AZ$31 - MEDIAN(MIN($AZ$3:$AZ$31), MAX($AZ$3:$AZ$31), E24))), ABS($AZ$3:$AZ$31 - MEDIAN(MIN($AZ$3:$AZ$31), MAX($AZ$3:$AZ$31), E24)), $BA$3:$BA$31, "Error", 0)} | F54: {=_xlfn.XLOOKUP(MIN(ABS($AZ$3:$AZ$31 - MEDIAN(MIN($AZ$3:$AZ$31), MAX($AZ$3:$AZ$31), F24))), ABS($AZ$3:$AZ$31 - MEDIAN(MIN($AZ$3:$AZ$31), MAX($AZ$3:$AZ$31), F24)), $BA$3:$BA$31, "Error", 0)} | G54: {=_xlfn.XLOOKUP(MIN(ABS($AZ$3:$AZ$31 - MEDIAN(MIN($AZ$3:$AZ$31), MAX($AZ$3:$AZ$31), G24))), ABS($AZ$3:$AZ$31 - MEDIAN(MIN($AZ$3:$AZ$31), MAX($AZ$3:$AZ$31), G24)), $BA$3:$BA$31, "Error", 0)} | H54: {=_xlfn.XLOOKUP(MIN(ABS($AZ$3:$AZ$31 - MEDIAN(MIN($AZ$3:$AZ$31), MAX($AZ$3:$AZ$31), H24))), ABS($AZ$3:$AZ$31 - MEDIAN(MIN($AZ$3:$AZ$31), MAX($AZ$3:$AZ$31), H24)), $BA$3:$BA$31, "Error", 0)} | I54: {=_xlfn.XLOOKUP(MIN(ABS($AZ$3:$AZ$31 - MEDIAN(MIN($AZ$3:$AZ$31), MAX($AZ$3:$AZ$31), I24))), ABS($AZ$3:$AZ$31 - MEDIAN(MIN($AZ$3:$AZ$31), MAX($AZ$3:$AZ$31), I24)), $BA$3:$BA$31, "Error", 0)} | J54: {=_xlfn.XLOOKUP(MIN(ABS($AZ$3:$AZ$31 - MEDIAN(MIN($AZ$3:$AZ$31), MAX($AZ$3:$AZ$31), J24))), ABS($AZ$3:$AZ$31 - MEDIAN(MIN($AZ$3:$AZ$31), MAX($AZ$3:$AZ$31), J24)), $BA$3:$BA$31, "Error", 0)} | ... AX54: {=_xlfn.XLOOKUP(MIN(ABS($AZ$3:$AZ$31 - MEDIAN(MIN($AZ$3:$AZ$31), MAX($AZ$3:$AZ$31), AX24))), ABS($AZ$3:$AZ$31 - MEDIAN(MIN($AZ$3:$AZ$31), MAX($AZ$3:$AZ$31), AX24)), $BA$3:$BA$31, "Error", 0)}
B55: GBP USD | C55: {=_xlfn.XLOOKUP(MIN(ABS($AZ$3:$AZ$31 - MEDIAN(MIN($AZ$3:$AZ$31), MAX($AZ$3:$AZ$31), C25))), ABS($AZ$3:$AZ$31 - MEDIAN(MIN($AZ$3:$AZ$31), MAX($AZ$3:$AZ$31), C25)), $BA$3:$BA$31, "Error", 0)} | D55: {=_xlfn.XLOOKUP(MIN(ABS($AZ$3:$AZ$31 - MEDIAN(MIN($AZ$3:$AZ$31), MAX($AZ$3:$AZ$31), D25))), ABS($AZ$3:$AZ$31 - MEDIAN(MIN($AZ$3:$AZ$31), MAX($AZ$3:$AZ$31), D25)), $BA$3:$BA$31, "Error", 0)} | E55: {=_xlfn.XLOOKUP(MIN(ABS($AZ$3:$AZ$31 - MEDIAN(MIN($AZ$3:$AZ$31), MAX($AZ$3:$AZ$31), E25))), ABS($AZ$3:$AZ$31 - MEDIAN(MIN($AZ$3:$AZ$31), MAX($AZ$3:$AZ$31), E25)), $BA$3:$BA$31, "Error", 0)} | F55: {=_xlfn.XLOOKUP(MIN(ABS($AZ$3:$AZ$31 - MEDIAN(MIN($AZ$3:$AZ$31), MAX($AZ$3:$AZ$31), F25))), ABS($AZ$3:$AZ$31 - MEDIAN(MIN($AZ$3:$AZ$31), MAX($AZ$3:$AZ$31), F25)), $BA$3:$BA$31, "Error", 0)} | G55: {=_xlfn.XLOOKUP(MIN(ABS($AZ$3:$AZ$31 - MEDIAN(MIN($AZ$3:$AZ$31), MAX($AZ$3:$AZ$31), G25))), ABS($AZ$3:$AZ$31 - MEDIAN(MIN($AZ$3:$AZ$31), MAX($AZ$3:$AZ$31), G25)), $BA$3:$BA$31, "Error", 0)} | H55: {=_xlfn.XLOOKUP(MIN(ABS($AZ$3:$AZ$31 - MEDIAN(MIN($AZ$3:$AZ$31), MAX($AZ$3:$AZ$31), H25))), ABS($AZ$3:$AZ$31 - MEDIAN(MIN($AZ$3:$AZ$31), MAX($AZ$3:$AZ$31), H25)), $BA$3:$BA$31, "Error", 0)} | I55: {=_xlfn.XLOOKUP(MIN(ABS($AZ$3:$AZ$31 - MEDIAN(MIN($AZ$3:$AZ$31), MAX($AZ$3:$AZ$31), I25))), ABS($AZ$3:$AZ$31 - MEDIAN(MIN($AZ$3:$AZ$31), MAX($AZ$3:$AZ$31), I25)), $BA$3:$BA$31, "Error", 0)} | J55: {=_xlfn.XLOOKUP(MIN(ABS($AZ$3:$AZ$31 - MEDIAN(MIN($AZ$3:$AZ$31), MAX($AZ$3:$AZ$31), J25))), ABS($AZ$3:$AZ$31 - MEDIAN(MIN($AZ$3:$AZ$31), MAX($AZ$3:$AZ$31), J25)), $BA$3:$BA$31, "Error", 0)} | ... AX55: {=_xlfn.XLOOKUP(MIN(ABS($AZ$3:$AZ$31 - MEDIAN(MIN($AZ$3:$AZ$31), MAX($AZ$3:$AZ$31), AX25))), ABS($AZ$3:$AZ$31 - MEDIAN(MIN($AZ$3:$AZ$31), MAX($AZ$3:$AZ$31), AX25)), $BA$3:$BA$31, "Error", 0)}
B56: GBP JPY | C56: {=_xlfn.XLOOKUP(MIN(ABS($AZ$3:$AZ$31 - MEDIAN(MIN($AZ$3:$AZ$31), MAX($AZ$3:$AZ$31), C26))), ABS($AZ$3:$AZ$31 - MEDIAN(MIN($AZ$3:$AZ$31), MAX($AZ$3:$AZ$31), C26)), $BA$3:$BA$31, "Error", 0)} | D56: {=_xlfn.XLOOKUP(MIN(ABS($AZ$3:$AZ$31 - MEDIAN(MIN($AZ$3:$AZ$31), MAX($AZ$3:$AZ$31), D26))), ABS($AZ$3:$AZ$31 - MEDIAN(MIN($AZ$3:$AZ$31), MAX($AZ$3:$AZ$31), D26)), $BA$3:$BA$31, "Error", 0)} | E56: {=_xlfn.XLOOKUP(MIN(ABS($AZ$3:$AZ$31 - MEDIAN(MIN($AZ$3:$AZ$31), MAX($AZ$3:$AZ$31), E26))), ABS($AZ$3:$AZ$31 - MEDIAN(MIN($AZ$3:$AZ$31), MAX($AZ$3:$AZ$31), E26)), $BA$3:$BA$31, "Error", 0)} | F56: {=_xlfn.XLOOKUP(MIN(ABS($AZ$3:$AZ$31 - MEDIAN(MIN($AZ$3:$AZ$31), MAX($AZ$3:$AZ$31), F26))), ABS($AZ$3:$AZ$31 - MEDIAN(MIN($AZ$3:$AZ$31), MAX($AZ$3:$AZ$31), F26)), $BA$3:$BA$31, "Error", 0)} | G56: {=_xlfn.XLOOKUP(MIN(ABS($AZ$3:$AZ$31 - MEDIAN(MIN($AZ$3:$AZ$31), MAX($AZ$3:$AZ$31), G26))), ABS($AZ$3:$AZ$31 - MEDIAN(MIN($AZ$3:$AZ$31), MAX($AZ$3:$AZ$31), G26)), $BA$3:$BA$31, "Error", 0)} | H56: {=_xlfn.XLOOKUP(MIN(ABS($AZ$3:$AZ$31 - MEDIAN(MIN($AZ$3:$AZ$31), MAX($AZ$3:$AZ$31), H26))), ABS($AZ$3:$AZ$31 - MEDIAN(MIN($AZ$3:$AZ$31), MAX($AZ$3:$AZ$31), H26)), $BA$3:$BA$31, "Error", 0)} | I56: {=_xlfn.XLOOKUP(MIN(ABS($AZ$3:$AZ$31 - MEDIAN(MIN($AZ$3:$AZ$31), MAX($AZ$3:$AZ$31), I26))), ABS($AZ$3:$AZ$31 - MEDIAN(MIN($AZ$3:$AZ$31), MAX($AZ$3:$AZ$31), I26)), $BA$3:$BA$31, "Error", 0)} | J56: {=_xlfn.XLOOKUP(MIN(ABS($AZ$3:$AZ$31 - MEDIAN(MIN($AZ$3:$AZ$31), MAX($AZ$3:$AZ$31), J26))), ABS($AZ$3:$AZ$31 - MEDIAN(MIN($AZ$3:$AZ$31), MAX($AZ$3:$AZ$31), J26)), $BA$3:$BA$31, "Error", 0)} | ... AX56: {=_xlfn.XLOOKUP(MIN(ABS($AZ$3:$AZ$31 - MEDIAN(MIN($AZ$3:$AZ$31), MAX($AZ$3:$AZ$31), AX26))), ABS($AZ$3:$AZ$31 - MEDIAN(MIN($AZ$3:$AZ$31), MAX($AZ$3:$AZ$31), AX26)), $BA$3:$BA$31, "Error", 0)}
... B67: CAD JPY | C67: {=_xlfn.XLOOKUP(MIN(ABS($AZ$3:$AZ$31 - MEDIAN(MIN($AZ$3:$AZ$31), MAX($AZ$3:$AZ$31), C37))), ABS($AZ$3:$AZ$31 - MEDIAN(MIN($AZ$3:$AZ$31), MAX($AZ$3:$AZ$31), C37)), $BA$3:$BA$31, "Error", 0)} | D67: {=_xlfn.XLOOKUP(MIN(ABS($AZ$3:$AZ$31 - MEDIAN(MIN($AZ$3:$AZ$31), MAX($AZ$3:$AZ$31), D37))), ABS($AZ$3:$AZ$31 - MEDIAN(MIN($AZ$3:$AZ$31), MAX($AZ$3:$AZ$31), D37)), $BA$3:$BA$31, "Error", 0)} | E67: {=_xlfn.XLOOKUP(MIN(ABS($AZ$3:$AZ$31 - MEDIAN(MIN($AZ$3:$AZ$31), MAX($AZ$3:$AZ$31), E37))), ABS($AZ$3:$AZ$31 - MEDIAN(MIN($AZ$3:$AZ$31), MAX($AZ$3:$AZ$31), E37)), $BA$3:$BA$31, "Error", 0)} | F67: {=_xlfn.XLOOKUP(MIN(ABS($AZ$3:$AZ$31 - MEDIAN(MIN($AZ$3:$AZ$31), MAX($AZ$3:$AZ$31), F37))), ABS($AZ$3:$AZ$31 - MEDIAN(MIN($AZ$3:$AZ$31), MAX($AZ$3:$AZ$31), F37)), $BA$3:$BA$31, "Error", 0)} | G67: {=_xlfn.XLOOKUP(MIN(ABS($AZ$3:$AZ$31 - MEDIAN(MIN($AZ$3:$AZ$31), MAX($AZ$3:$AZ$31), G37))), ABS($AZ$3:$AZ$31 - MEDIAN(MIN($AZ$3:$AZ$31), MAX($AZ$3:$AZ$31), G37)), $BA$3:$BA$31, "Error", 0)} | H67: {=_xlfn.XLOOKUP(MIN(ABS($AZ$3:$AZ$31 - MEDIAN(MIN($AZ$3:$AZ$31), MAX($AZ$3:$AZ$31), H37))), ABS($AZ$3:$AZ$31 - MEDIAN(MIN($AZ$3:$AZ$31), MAX($AZ$3:$AZ$31), H37)), $BA$3:$BA$31, "Error", 0)} | I67: {=_xlfn.XLOOKUP(MIN(ABS($AZ$3:$AZ$31 - MEDIAN(MIN($AZ$3:$AZ$31), MAX($AZ$3:$AZ$31), I37))), ABS($AZ$3:$AZ$31 - MEDIAN(MIN($AZ$3:$AZ$31), MAX($AZ$3:$AZ$31), I37)), $BA$3:$BA$31, "Error", 0)} | J67: {=_xlfn.XLOOKUP(MIN(ABS($AZ$3:$AZ$31 - MEDIAN(MIN($AZ$3:$AZ$31), MAX($AZ$3:$AZ$31), J37))), ABS($AZ$3:$AZ$31 - MEDIAN(MIN($AZ$3:$AZ$31), MAX($AZ$3:$AZ$31), J37)), $BA$3:$BA$31, "Error", 0)} | ... AX67: {=_xlfn.XLOOKUP(MIN(ABS($AZ$3:$AZ$31 - MEDIAN(MIN($AZ$3:$AZ$31), MAX($AZ$3:$AZ$31), AX37))), ABS($AZ$3:$AZ$31 - MEDIAN(MIN($AZ$3:$AZ$31), MAX($AZ$3:$AZ$31), AX37)), $BA$3:$BA$31, "Error", 0)}

Sheet EQUITY
C5: 44927 | D5: 44958 | E5: 44986 | F5: 45017 | G5: 45047 | H5: 45078 | I5: 45108 | J5: 45139 | K5: 45170 | L5: 45200 | M5: 45231 | N5: 45261 | O5: 45292 | P5: 45323 | Q5: 45352 | R5: 45383 | S5: 45413 | T5: 45444 | U5: 45474 | V5: 45505 | W5: 45536 | X5: 45566 | Y5: 45597 | Z5: 45627 | AA5: 45658 | AB5: 45689 | AC5: 45717 | AD5: 45748 | AE5: 45778 | AF5: 45809 | AG5: 45839 | AH5: 45870 | AI5: 45901 | AJ5: 45931 | AK5: 45962 | AL5: 45992 | AM5: 46023 | AN5: 46054 | AO5: 46082 | AP5: 46113 | AQ5: 46143 | AR5: 46174 | AS5: 46204 | AT5: 46235 | AU5: 46266 | AV5: 46296 | AW5: 46327 | AX5: 46357 | AY5: 46357 | BD5: EUR JPY | BG5: eurusd | BP5: 46143 | BQ5: 46174 | BR5: 46204 | BS5: 46235 | BT5: 46266 | BU5: 46296 | BV5: 46327 | BW5: 46357
A6: USD JPY | B6: All time High (CL) | C6: 601456.1 | D6: 601456.1 | E6: 601456.1 | F6: 601456.1 | G6: 601456.1 | H6: 646626.75 | I6: 667605.87 | J6: 675516.24 | K6: 675516.24 | L6: 675516.24 | M6: 696876.3 | N6: 696876.3 | O6: 733652.51 | P6: 770936.99 | Q6: 799962.38 | R6: 799962.38 | S6: 843920.84 | T6: 890637.24 | U6: 890637.24 | V6: 890637.24 | W6: 890637.24 | X6: 904506.86 | Y6: 947399.47 | Z6: 964252.77 | AA6: 964252.77 | AB6: 964252.77 | AC6: 964252.77 | AD6: 964252.77 | AE6: 964252.77 | AF6: 964252.77 | AG6: 968076.36 | AH6: 982189.48 | AI6: 1004492.5 | AJ6: 1068784.2 | AK6: 1086628.8 | AL6: 1095716.1 | AM6: 1095716.1 | AN6: 1100270.2 | AO6: 1100270.2 | AP6: 1160241.1 | AQ6: 1213187.8 | AR6: 1239547 | AS6: 1239547 | AT6: 1251445.9 | AU6: 1251445.9 | AV6: 1251445.9 | AW6: 1251445.9 | AX6: 1251445.9 | BC6: 45658 | BD6: =#REF! | BE6: 2 | BF6: {=_xlfn.XLOOKUP(MIN(ABS($BJ$7:$BJ$29 - MEDIAN(MIN($BJ$7:$BJ$29), MAX($BJ$7:$BJ$29), BD6))), ABS($BJ$7:$BJ$29 - MEDIAN(MIN($BJ$7:$BJ$29), MAX($BJ$7:$BJ$29), BD6)), $BK$7:$BK$29, "Error", 0)} | BI6: {=_xlfn.XLOOKUP(MIN(ABS($BJ$7:$BJ$29 - MEDIAN(MIN($BJ$7:$BJ$29), MAX($BJ$7:$BJ$29), BG6))), ABS($BJ$7:$BJ$29 - MEDIAN(MIN($BJ$7:$BJ$29), MAX($BJ$7:$BJ$29), BG6)), $BK$7:$BK$29, "Error", 0)} | BO6: All time High SPX
B7: current price | C7: 531910.72 | D7: 541198.93 | E7: 547364.23 | F7: 568383.54 | G7: 584306.84 | H7: 644325.99 | I7: 645932.81 | J7: 658564.64 | K7: 640505.98 | L7: 625341.65 | M7: 671644.72 | N7: 672641.46 | O7: 714098.6 | P7: 767783.69 | Q7: 795193.32 | R7: 787148.81 | S7: 828321.01 | T7: 878482.05 | U7: 843089.5 | V7: 825513.61 | W7: 822784.21 | X7: 874097.76 | Y7: 903324.77 | Z7: 923386.45 | AA7: 930827.52 | AB7: 893246.41 | AC7: 839628.2 | AD7: 792471.65 | AE7: 851519.78 | AF7: 896720.78 | AG7: 946001.82 | AH7: 949787.42 | AI7: 993871.72 | AJ7: 1052706.8 | AK7: 1069485.3 | AL7: 1070725.2 | AM7: 1073745.5 | AN7: 1072135.3 | AO7: 1043525.2 | AP7: 1154768.1 | AQ7: 1207533.9 | AR7: 1214318.9 | AS7: 1199725.8 | AT7: 1230720.1 | AU7: 1217147.9 | AV7: 1217147.9 | AW7: 1217147.9 | AX7: 1217147.9 | BC7: 45689 | BD7: =#REF! | BE7: 3 | BF7: {=_xlfn.XLOOKUP(MIN(ABS($BJ$7:$BJ$29 - MEDIAN(MIN($BJ$7:$BJ$29), MAX($BJ$7:$BJ$29), BD7))), ABS($BJ$7:$BJ$29 - MEDIAN(MIN($BJ$7:$BJ$29), MAX($BJ$7:$BJ$29), BD7)), $BK$7:$BK$29, "Error", 0)} | BI7: {=_xlfn.XLOOKUP(MIN(ABS($BJ$7:$BJ$29 - MEDIAN(MIN($BJ$7:$BJ$29), MAX($BJ$7:$BJ$29), BG7))), ABS($BJ$7:$BJ$29 - MEDIAN(MIN($BJ$7:$BJ$29), MAX($BJ$7:$BJ$29), BG7)), $BK$7:$BK$29, "Error", 0)} | BJ7: 0.25 | BK7: 2 | BL7: 25 | BO7: current price SPX
B8: % CHANGE | C8: =+(C7-C6)/C6 | D8: =+(D7-D6)/D6 | E8: =+(E7-E6)/E6 | F8: =+(F7-F6)/F6 | G8: =+(G7-G6)/G6 | H8: =+(H7-H6)/H6 | I8: =+(I7-I6)/I6 | J8: =+(J7-J6)/J6 | ... AX8: =+(AX7-AX6)/AX6 | BC8: 45717 | BD8: =#REF! | BE8: 5 | BF8: {=_xlfn.XLOOKUP(MIN(ABS($BJ$7:$BJ$29 - MEDIAN(MIN($BJ$7:$BJ$29), MAX($BJ$7:$BJ$29), BD8))), ABS($BJ$7:$BJ$29 - MEDIAN(MIN($BJ$7:$BJ$29), MAX($BJ$7:$BJ$29), BD8)), $BK$7:$BK$29, "Error", 0)} | BI8: {=_xlfn.XLOOKUP(MIN(ABS($BJ$7:$BJ$29 - MEDIAN(MIN($BJ$7:$BJ$29), MAX($BJ$7:$BJ$29), BG8))), ABS($BJ$7:$BJ$29 - MEDIAN(MIN($BJ$7:$BJ$29), MAX($BJ$7:$BJ$29), BG8)), $BK$7:$BK$29, "Error", 0)} | BJ8: 0.2 | BK8: 3 | BL8: 20 | BO8: All time High STOXX50
B9: All time High SPX | C9: 4808.9302 | D9: 4808.9302 | E9: 4808.9302 | F9: 4808.9302 | G9: 4808.9302 | H9: 4808.9302 | I9: 4808.9302 | J9: 4808.9302 | K9: 4808.9302 | L9: 4808.9302 | M9: 4808.9302 | N9: 4808.9302 | O9: 4931.0898 | P9: 5111.0601 | Q9: 5264.8501 | R9: 5264.8501 | S9: 5341.8799 | T9: 5523.6401 | U9: 5669.6699 | V9: 5669.6699 | W9: 5767.3701 | X9: 5767.3701 | Y9: 6044.1699 | Z9: 6044.1699 | AA9: 6128.1802 | AB9: 6128.1802 | AC9: 6128.1802 | AD9: 6128.1802 | AE9: 6128.1802 | AF9: 6215.0801 | AG9: 6427.02 | AH9: 6508.23 | AI9: 6699.52 | AJ9: 6920.3398 | AK9: 6920.3398 | AL9: 6945.77 | AM9: 7002.2798 | AN9: 7002.2798 | AO9: 7002.2798 | AP9: 7219.8301 | AQ9: 7599.3799 | AR9: 7599.3799 | AS9: 7599.3799 | AT9: 7816.7002 | AU9: 7816.7002 | AV9: 7816.7002 | AW9: 7816.7002 | AX9: 7816.7002 | BC9: 45748 | BD9: =#REF! | BE9: 3 | BF9: {=_xlfn.XLOOKUP(MIN(ABS($BJ$7:$BJ$29 - MEDIAN(MIN($BJ$7:$BJ$29), MAX($BJ$7:$BJ$29), BD9))), ABS($BJ$7:$BJ$29 - MEDIAN(MIN($BJ$7:$BJ$29), MAX($BJ$7:$BJ$29), BD9)), $BK$7:$BK$29, "Error", 0)} | BI9: {=_xlfn.XLOOKUP(MIN(ABS($BJ$7:$BJ$29 - MEDIAN(MIN($BJ$7:$BJ$29), MAX($BJ$7:$BJ$29), BG9))), ABS($BJ$7:$BJ$29 - MEDIAN(MIN($BJ$7:$BJ$29), MAX($BJ$7:$BJ$29), BG9)), $BK$7:$BK$29, "Error", 0)} | BJ9: 0.18 | BK9: 5 | BL9: 18 | BO9: current price STOXX50
B10: current price SPX | C10: 4076.6001 | D10: 3970.1499 | E10: 4109.3101 | F10: 4169.48 | G10: 4179.8301 | H10: 4450.3799 | I10: 4588.96 | J10: 4507.6602 | K10: 4288.0498 | L10: 4193.7998 | M10: 4567.7998 | N10: 4769.8301 | O10: 4845.6499 | P10: 5096.27 | Q10: 5254.3501 | R10: 5035.6899 | S10: 5277.5098 | T10: 5460.48 | U10: 5522.2998 | V10: 5648.3999 | W10: 5762.48 | X10: 5705.4502 | Y10: 6032.3799 | Z10: 5881.6299 | AA10: 6040.5298 | AB10: 5954.5 | AC10: 5611.8501 | AD10: 5569.0601 | AE10: 5911.6899 | AF10: 6204.9502 | AG10: 6339.3901 | AH10: 6460.2598 | AI10: 6688.46 | AJ10: 6840.2002 | AK10: 6849.0898 | AL10: 6845.5 | AM10: 6939.0298 | AN10: 6878.8799 | AO10: 6528.52 | AP10: 7209.0098 | AQ10: 7580.0601 | AR10: 7499.3599 | AS10: 7489.7202 | AT10: 7686.1401 | AU10: 7743.4102 | AV10: 7743.4102 | AW10: 7743.4102 | AX10: 7743.4102 | BC10: 45778 | BD10: =#REF! | BE10: 3 | BF10: {=_xlfn.XLOOKUP(MIN(ABS($BJ$7:$BJ$29 - MEDIAN(MIN($BJ$7:$BJ$29), MAX($BJ$7:$BJ$29), BD10))), ABS($BJ$7:$BJ$29 - MEDIAN(MIN($BJ$7:$BJ$29), MAX($BJ$7:$BJ$29), BD10)), $BK$7:$BK$29, "Error", 0)} | BI10: {=_xlfn.XLOOKUP(MIN(ABS($BJ$7:$BJ$29 - MEDIAN(MIN($BJ$7:$BJ$29), MAX($BJ$7:$BJ$29), BG10))), ABS($BJ$7:$BJ$29 - MEDIAN(MIN($BJ$7:$BJ$29), MAX($BJ$7:$BJ$29), BG10)), $BK$7:$BK$29, "Error", 0)} | BJ10: 0.16 | BK10: 7 | BL10: 16 | BO10: All time High TSE UK
B11: original index % change | C11: =+(C10-C9)/C9 | D11: =+(D10-D9)/D9 | E11: =+(E10-E9)/E9 | F11: =+(F10-F9)/F9 | G11: =+(G10-G9)/G9 | H11: =+(H10-H9)/H9 | I11: =+(I10-I9)/I9 | J11: =+(J10-J9)/J9 | ... AX11: =+(AX10-AX9)/AX9 | BC11: 45809 | BD11: =#REF! | BE11: 3 | BF11: {=_xlfn.XLOOKUP(MIN(ABS($BJ$7:$BJ$29 - MEDIAN(MIN($BJ$7:$BJ$29), MAX($BJ$7:$BJ$29), BD11))), ABS($BJ$7:$BJ$29 - MEDIAN(MIN($BJ$7:$BJ$29), MAX($BJ$7:$BJ$29), BD11)), $BK$7:$BK$29, "Error", 0)} | BI11: {=_xlfn.XLOOKUP(MIN(ABS($BJ$7:$BJ$29 - MEDIAN(MIN($BJ$7:$BJ$29), MAX($BJ$7:$BJ$29), BG11))), ABS($BJ$7:$BJ$29 - MEDIAN(MIN($BJ$7:$BJ$29), MAX($BJ$7:$BJ$29), BG11)), $BK$7:$BK$29, "Error", 0)} | BJ11: 0.14 | BK11: 9 | BL11: 14 | BO11: current price TSE UK
B12: real % change | C12: =+C8-C11 | D12: =+D8-D11 | E12: =+E8-E11 | F12: =+F8-F11 | G12: =+G8-G11 | H12: =+H8-H11 | I12: =+I8-I11 | J12: =+J8-J11 | ... AX12: =+AX8-AX11 | BC12: 45839 | BD12: =#REF! | BE12: 3 | BF12: {=_xlfn.XLOOKUP(MIN(ABS($BJ$7:$BJ$29 - MEDIAN(MIN($BJ$7:$BJ$29), MAX($BJ$7:$BJ$29), BD12))), ABS($BJ$7:$BJ$29 - MEDIAN(MIN($BJ$7:$BJ$29), MAX($BJ$7:$BJ$29), BD12)), $BK$7:$BK$29, "Error", 0)} | BI12: {=_xlfn.XLOOKUP(MIN(ABS($BJ$7:$BJ$29 - MEDIAN(MIN($BJ$7:$BJ$29), MAX($BJ$7:$BJ$29), BG12))), ABS($BJ$7:$BJ$29 - MEDIAN(MIN($BJ$7:$BJ$29), MAX($BJ$7:$BJ$29), BG12)), $BK$7:$BK$29, "Error", 0)} | BJ12: 0.12 | BK12: 10 | BL12: 12 | BO12: All time High SMI
B13: Rating | C13: =_xlfn.XLOOKUP(MIN(ABS($BJ$7:$BJ$29 - MEDIAN(MIN($BJ$7:$BJ$29), MAX($BJ$7:$BJ$29), C12))), ABS($BJ$7:$BJ$29 - MEDIAN(MIN($BJ$7:$BJ$29), MAX($BJ$7:$BJ$29), C12)), $BK$7:$BK$29, "Error", 0) | D13: =_xlfn.XLOOKUP(MIN(ABS($BJ$7:$BJ$29 - MEDIAN(MIN($BJ$7:$BJ$29), MAX($BJ$7:$BJ$29), D12))), ABS($BJ$7:$BJ$29 - MEDIAN(MIN($BJ$7:$BJ$29), MAX($BJ$7:$BJ$29), D12)), $BK$7:$BK$29, "Error", 0) | E13: =_xlfn.XLOOKUP(MIN(ABS($BJ$7:$BJ$29 - MEDIAN(MIN($BJ$7:$BJ$29), MAX($BJ$7:$BJ$29), E12))), ABS($BJ$7:$BJ$29 - MEDIAN(MIN($BJ$7:$BJ$29), MAX($BJ$7:$BJ$29), E12)), $BK$7:$BK$29, "Error", 0) | F13: =_xlfn.XLOOKUP(MIN(ABS($BJ$7:$BJ$29 - MEDIAN(MIN($BJ$7:$BJ$29), MAX($BJ$7:$BJ$29), F12))), ABS($BJ$7:$BJ$29 - MEDIAN(MIN($BJ$7:$BJ$29), MAX($BJ$7:$BJ$29), F12)), $BK$7:$BK$29, "Error", 0) | G13: =_xlfn.XLOOKUP(MIN(ABS($BJ$7:$BJ$29 - MEDIAN(MIN($BJ$7:$BJ$29), MAX($BJ$7:$BJ$29), G12))), ABS($BJ$7:$BJ$29 - MEDIAN(MIN($BJ$7:$BJ$29), MAX($BJ$7:$BJ$29), G12)), $BK$7:$BK$29, "Error", 0) | H13: =_xlfn.XLOOKUP(MIN(ABS($BJ$7:$BJ$29 - MEDIAN(MIN($BJ$7:$BJ$29), MAX($BJ$7:$BJ$29), H12))), ABS($BJ$7:$BJ$29 - MEDIAN(MIN($BJ$7:$BJ$29), MAX($BJ$7:$BJ$29), H12)), $BK$7:$BK$29, "Error", 0) | I13: =_xlfn.XLOOKUP(MIN(ABS($BJ$7:$BJ$29 - MEDIAN(MIN($BJ$7:$BJ$29), MAX($BJ$7:$BJ$29), I12))), ABS($BJ$7:$BJ$29 - MEDIAN(MIN($BJ$7:$BJ$29), MAX($BJ$7:$BJ$29), I12)), $BK$7:$BK$29, "Error", 0) | J13: =_xlfn.XLOOKUP(MIN(ABS($BJ$7:$BJ$29 - MEDIAN(MIN($BJ$7:$BJ$29), MAX($BJ$7:$BJ$29), J12))), ABS($BJ$7:$BJ$29 - MEDIAN(MIN($BJ$7:$BJ$29), MAX($BJ$7:$BJ$29), J12)), $BK$7:$BK$29, "Error", 0) | ... AX13: =_xlfn.XLOOKUP(MIN(ABS($BJ$7:$BJ$29 - MEDIAN(MIN($BJ$7:$BJ$29), MAX($BJ$7:$BJ$29), AX12))), ABS($BJ$7:$BJ$29 - MEDIAN(MIN($BJ$7:$BJ$29), MAX($BJ$7:$BJ$29), AX12)), $BK$7:$BK$29, "Error", 0) | BC13: 45870 | BD13: =#REF! | BE13: 5 | BF13: {=_xlfn.XLOOKUP(MIN(ABS($BJ$7:$BJ$29 - MEDIAN(MIN($BJ$7:$BJ$29), MAX($BJ$7:$BJ$29), BD13))), ABS($BJ$7:$BJ$29 - MEDIAN(MIN($BJ$7:$BJ$29), MAX($BJ$7:$BJ$29), BD13)), $BK$7:$BK$29, "Error", 0)} | BI13: {=_xlfn.XLOOKUP(MIN(ABS($BJ$7:$BJ$29 - MEDIAN(MIN($BJ$7:$BJ$29), MAX($BJ$7:$BJ$29), BG13))), ABS($BJ$7:$BJ$29 - MEDIAN(MIN($BJ$7:$BJ$29), MAX($BJ$7:$BJ$29), BG13)), $BK$7:$BK$29, "Error", 0)} | BJ13: 0.1 | BK13: 9 | BL13: 10 | BO13: current price SMI
A14: USD CHF | B14: All time High (CL) | C14: 4459.2248 | D14: 4459.2248 | E14: 4459.2248 | F14: 4459.2248 | G14: 4459.2248 | H14: 4459.2248 | I14: 4459.2248 | J14: 4459.2248 | K14: 4459.2248 | L14: 4459.2248 | M14: 4459.2248 | N14: 4459.2248 | O14: 4459.2248 | P14: 4541.0747 | Q14: 4775.8508 | R14: 4775.8508 | S14: 4926.5486 | T14: 4999.7449 | U14: 4999.7449 | V14: 4999.7449 | W14: 4999.7449 | X14: 5113.9662 | Y14: 5412.5178 | Z14: 5412.5178 | AA14: 5637.558 | AB14: 5637.558 | AC14: 5637.558 | AD14: 5637.558 | AE14: 5637.558 | AF14: 5637.558 | AG14: 5637.558 | AH14: 5637.558 | AI14: 5637.558 | AJ14: 5637.558 | AK14: 5637.558 | AL14: 5637.558 | AM14: 5637.558 | AN14: 5637.558 | AO14: 5637.558 | AP14: 5788.5711 | AQ14: 6008.2976 | AR14: 6202.5741 | AS14: 6202.5741 | AT14: 6366.6243 | AU14: 6457.7392 | AV14: 6457.7392 | AW14: 6457.7392 | AX14: 6457.7392 | BC14: 45901 | BD14: =#REF! | BE14: 2 | BF14: {=_xlfn.XLOOKUP(MIN(ABS($BJ$7:$BJ$29 - MEDIAN(MIN($BJ$7:$BJ$29), MAX($BJ$7:$BJ$29), BD14))), ABS($BJ$7:$BJ$29 - MEDIAN(MIN($BJ$7:$BJ$29), MAX($BJ$7:$BJ$29), BD14)), $BK$7:$BK$29, "Error", 0)} | BI14: {=_xlfn.XLOOKUP(MIN(ABS($BJ$7:$BJ$29 - MEDIAN(MIN($BJ$7:$BJ$29), MAX($BJ$7:$BJ$29), BG14))), ABS($BJ$7:$BJ$29 - MEDIAN(MIN($BJ$7:$BJ$29), MAX($BJ$7:$BJ$29), BG14)), $BK$7:$BK$29, "Error", 0)} | BJ14: 0.08 | BK14: 7 | BL14: 8 | BO14: All time High ASX200
B15: current price | C15: 3771.9964 | D15: 3714.4722 | E15: 3753.3617 | F15: 3728.3116 | G15: 3786.09 | H15: 4001.5146 | I15: 3991.5691 | J15: 3958.2214 | K15: 3924.4232 | L15: 3783.0589 | M15: 3989.1508 | N15: 4009.8007 | O15: 4176.2717 | P15: 4478.1433 | Q15: 4738.7355 | R15: 4586.1035 | S15: 4767.2274 | T15: 4930.7916 | U15: 4870.8342 | V15: 4798.7733 | W15: 4843.3644 | X15: 4942.6314 | Y15: 5313.2117 | Z15: 5312.5235 | AA15: 5493.0705 | AB15: 5358.5736 | AC15: 4943.1983 | AD15: 4585.6754 | AE15: 4860.361 | AF15: 4953.1016 | AG15: 5155.2555 | AH15: 5256.3323 | AI15: 5332.0404 | AJ15: 5483.0362 | AK15: 5496.7437 | AL15: 5419.5824 | AM15: 5359.9702 | AN15: 5318.9564 | AO15: 5222.0328 | AP15: 5699.1548 | AQ15: 5919.2386 | AR15: 6056.4832 | AS15: 6034.9917 | AT15: 6216.8574 | AU15: 6413.8666 | AV15: 6413.8666 | AW15: 6413.8666 | AX15: 6413.8666 | BC15: 45931 | BD15: =#REF! | BE15: 3 | BF15: {=_xlfn.XLOOKUP(MIN(ABS($BJ$7:$BJ$29 - MEDIAN(MIN($BJ$7:$BJ$29), MAX($BJ$7:$BJ$29), BD15))), ABS($BJ$7:$BJ$29 - MEDIAN(MIN($BJ$7:$BJ$29), MAX($BJ$7:$BJ$29), BD15)), $BK$7:$BK$29, "Error", 0)} | BI15: {=_xlfn.XLOOKUP(MIN(ABS($BJ$7:$BJ$29 - MEDIAN(MIN($BJ$7:$BJ$29), MAX($BJ$7:$BJ$29), BG15))), ABS($BJ$7:$BJ$29 - MEDIAN(MIN($BJ$7:$BJ$29), MAX($BJ$7:$BJ$29), BG15)), $BK$7:$BK$29, "Error", 0)} | BJ15: 0.06 | BK15: 5 | BL15: 6 | BO15: current price ASX200
B16: % CHANGE | C16: =+(C15-C14)/C14 | D16: =+(D15-D14)/D14 | E16: =+(E15-E14)/E14 | F16: =+(F15-F14)/F14 | G16: =+(G15-G14)/G14 | H16: =+(H15-H14)/H14 | I16: =+(I15-I14)/I14 | J16: =+(J15-J14)/J14 | ... AX16: =+(AX15-AX14)/AX14 | BC16: 45962 | BD16: =#REF! | BE16: 3 | BF16: {=_xlfn.XLOOKUP(MIN(ABS($BJ$7:$BJ$29 - MEDIAN(MIN($BJ$7:$BJ$29), MAX($BJ$7:$BJ$29), BD16))), ABS($BJ$7:$BJ$29 - MEDIAN(MIN($BJ$7:$BJ$29), MAX($BJ$7:$BJ$29), BD16)), $BK$7:$BK$29, "Error", 0)} | BG16: =#REF! | BI16: {=_xlfn.XLOOKUP(MIN(ABS($BJ$7:$BJ$29 - MEDIAN(MIN($BJ$7:$BJ$29), MAX($BJ$7:$BJ$29), BG16))), ABS($BJ$7:$BJ$29 - MEDIAN(MIN($BJ$7:$BJ$29), MAX($BJ$7:$BJ$29), BG16)), $BK$7:$BK$29, "Error", 0)} | BJ16: 0.04 | BK16: 3 | BL16: 4 | BO16: All time High TSX
B17: All time High SPX | C17: 4808.9302 | D17: 4808.9302 | E17: 4808.9302 | F17: 4808.9302 | G17: 4808.9302 | H17: 4808.9302 | I17: 4808.9302 | J17: 4808.9302 | K17: 4808.9302 | L17: 4808.9302 | M17: 4808.9302 | N17: 4808.9302 | O17: 4931.0898 | P17: 5111.0601 | Q17: 5264.8501 | R17: 5264.8501 | S17: 5341.8799 | T17: 5523.6401 | U17: 5669.6699 | V17: 5669.6699 | W17: 5767.3701 | X17: 5767.3701 | Y17: 6044.1699 | Z17: 6044.1699 | AA17: 6128.1802 | AB17: 6128.1802 | AC17: 6128.1802 | AD17: 6128.1802 | AE17: 6128.1802 | AF17: 6215.0801 | AG17: 6427.02 | AH17: 6508.23 | AI17: 6699.52 | AJ17: 6920.3398 | AK17: 6920.3398 | AL17: 6945.77 | AM17: 7002.2798 | AN17: 7002.2798 | AO17: 7002.2798 | AP17: 7219.8301 | AQ17: 7599.3799 | AR17: 7599.3799 | AS17: 7599.3799 | AT17: 7816.7002 | AU17: 7816.7002 | AV17: 7816.7002 | AW17: 7816.7002 | AX17: 7816.7002 | BC17: 45992 | BD17: =#REF! | BE17: 3 | BF17: {=_xlfn.XLOOKUP(MIN(ABS($BJ$7:$BJ$29 - MEDIAN(MIN($BJ$7:$BJ$29), MAX($BJ$7:$BJ$29), BD17))), ABS($BJ$7:$BJ$29 - MEDIAN(MIN($BJ$7:$BJ$29), MAX($BJ$7:$BJ$29), BD17)), $BK$7:$BK$29, "Error", 0)} | BG17: =#REF! | BI17: {=_xlfn.XLOOKUP(MIN(ABS($BJ$7:$BJ$29 - MEDIAN(MIN($BJ$7:$BJ$29), MAX($BJ$7:$BJ$29), BG17))), ABS($BJ$7:$BJ$29 - MEDIAN(MIN($BJ$7:$BJ$29), MAX($BJ$7:$BJ$29), BG17)), $BK$7:$BK$29, "Error", 0)} | BJ17: 0.02 | BK17: 2 | BL17: 2 | BO17: current price TSX
B18: current price SPX | C18: 4076.6001 | D18: 3970.1499 | E18: 4109.3101 | F18: 4169.48 | G18: 4179.8301 | H18: 4450.3799 | I18: 4588.96 | J18: 4507.6602 | K18: 4288.0498 | L18: 4193.7998 | M18: 4567.7998 | N18: 4769.8301 | O18: 4845.6499 | P18: 5096.27 | Q18: 5254.3501 | R18: 5035.6899 | S18: 5277.5098 | T18: 5460.48 | U18: 5522.2998 | V18: 5648.3999 | W18: 5762.48 | X18: 5705.4502 | Y18: 6032.3799 | Z18: 5881.6299 | AA18: 6040.5298 | AB18: 5954.5 | AC18: 5611.8501 | AD18: 5569.0601 | AE18: 5911.6899 | AF18: 6204.9502 | AG18: 6339.3901 | AH18: 6460.2598 | AI18: 6688.46 | AJ18: 6840.2002 | AK18: 6849.0898 | AL18: 6845.5 | AM18: 6939.0298 | AN18: 6878.8799 | AO18: 6528.52 | AP18: 7209.0098 | AQ18: 7580.0601 | AR18: 7499.3599 | AS18: 7489.7202 | AT18: 7686.1401 | AU18: 7743.4102 | AV18: 7743.4102 | AW18: 7743.4102 | AX18: 7743.4102 | BC18: 46023 | BD18: =#REF! | BE18: 5 | BF18: {=_xlfn.XLOOKUP(MIN(ABS($BJ$7:$BJ$29 - MEDIAN(MIN($BJ$7:$BJ$29), MAX($BJ$7:$BJ$29), BD18))), ABS($BJ$7:$BJ$29 - MEDIAN(MIN($BJ$7:$BJ$29), MAX($BJ$7:$BJ$29), BD18)), $BK$7:$BK$29, "Error", 0)} | BG18: =#REF! | BI18: {=_xlfn.XLOOKUP(MIN(ABS($BJ$7:$BJ$29 - MEDIAN(MIN($BJ$7:$BJ$29), MAX($BJ$7:$BJ$29), BG18))), ABS($BJ$7:$BJ$29 - MEDIAN(MIN($BJ$7:$BJ$29), MAX($BJ$7:$BJ$29), BG18)), $BK$7:$BK$29, "Error", 0)} | BJ18: 0 | BK18: 0 | BL18: 0
B19: original index % change | C19: =+(C18-C17)/C17 | D19: =+(D18-D17)/D17 | E19: =+(E18-E17)/E17 | F19: =+(F18-F17)/F17 | G19: =+(G18-G17)/G17 | H19: =+(H18-H17)/H17 | I19: =+(I18-I17)/I17 | J19: =+(J18-J17)/J17 | ... AX19: =+(AX18-AX17)/AX17 | BC19: 46054 | BD19: =#REF! | BE19: 3 | BF19: {=_xlfn.XLOOKUP(MIN(ABS($BJ$7:$BJ$29 - MEDIAN(MIN($BJ$7:$BJ$29), MAX($BJ$7:$BJ$29), BD19))), ABS($BJ$7:$BJ$29 - MEDIAN(MIN($BJ$7:$BJ$29), MAX($BJ$7:$BJ$29), BD19)), $BK$7:$BK$29, "Error", 0)} | BG19: =#REF! | BI19: {=_xlfn.XLOOKUP(MIN(ABS($BJ$7:$BJ$29 - MEDIAN(MIN($BJ$7:$BJ$29), MAX($BJ$7:$BJ$29), BG19))), ABS($BJ$7:$BJ$29 - MEDIAN(MIN($BJ$7:$BJ$29), MAX($BJ$7:$BJ$29), BG19)), $BK$7:$BK$29, "Error", 0)} | BJ19: -0.02 | BK19: -2 | BL19: -2
B20: real % change | C20: =+C16-C19 | D20: =+D16-D19 | E20: =+E16-E19 | F20: =+F16-F19 | G20: =+G16-G19 | H20: =+H16-H19 | I20: =+I16-I19 | J20: =+J16-J19 | ... AX20: =+AX16-AX19 | BC20: 46082 | BD20: =#REF! | BE20: 0 | BF20: {=_xlfn.XLOOKUP(MIN(ABS($BJ$7:$BJ$29 - MEDIAN(MIN($BJ$7:$BJ$29), MAX($BJ$7:$BJ$29), BD20))), ABS($BJ$7:$BJ$29 - MEDIAN(MIN($BJ$7:$BJ$29), MAX($BJ$7:$BJ$29), BD20)), $BK$7:$BK$29, "Error", 0)} | BG20: =#REF! | BI20: {=_xlfn.XLOOKUP(MIN(ABS($BJ$7:$BJ$29 - MEDIAN(MIN($BJ$7:$BJ$29), MAX($BJ$7:$BJ$29), BG20))), ABS($BJ$7:$BJ$29 - MEDIAN(MIN($BJ$7:$BJ$29), MAX($BJ$7:$BJ$29), BG20)), $BK$7:$BK$29, "Error", 0)} | BJ20: -0.04 | BK20: -3 | BL20: -4
B21: Rating | C21: =_xlfn.XLOOKUP(MIN(ABS($BJ$7:$BJ$29 - MEDIAN(MIN($BJ$7:$BJ$29), MAX($BJ$7:$BJ$29), C20))), ABS($BJ$7:$BJ$29 - MEDIAN(MIN($BJ$7:$BJ$29), MAX($BJ$7:$BJ$29), C20)), $BK$7:$BK$29, "Error", 0) | D21: =_xlfn.XLOOKUP(MIN(ABS($BJ$7:$BJ$29 - MEDIAN(MIN($BJ$7:$BJ$29), MAX($BJ$7:$BJ$29), D20))), ABS($BJ$7:$BJ$29 - MEDIAN(MIN($BJ$7:$BJ$29), MAX($BJ$7:$BJ$29), D20)), $BK$7:$BK$29, "Error", 0) | E21: =_xlfn.XLOOKUP(MIN(ABS($BJ$7:$BJ$29 - MEDIAN(MIN($BJ$7:$BJ$29), MAX($BJ$7:$BJ$29), E20))), ABS($BJ$7:$BJ$29 - MEDIAN(MIN($BJ$7:$BJ$29), MAX($BJ$7:$BJ$29), E20)), $BK$7:$BK$29, "Error", 0) | F21: =_xlfn.XLOOKUP(MIN(ABS($BJ$7:$BJ$29 - MEDIAN(MIN($BJ$7:$BJ$29), MAX($BJ$7:$BJ$29), F20))), ABS($BJ$7:$BJ$29 - MEDIAN(MIN($BJ$7:$BJ$29), MAX($BJ$7:$BJ$29), F20)), $BK$7:$BK$29, "Error", 0) | G21: =_xlfn.XLOOKUP(MIN(ABS($BJ$7:$BJ$29 - MEDIAN(MIN($BJ$7:$BJ$29), MAX($BJ$7:$BJ$29), G20))), ABS($BJ$7:$BJ$29 - MEDIAN(MIN($BJ$7:$BJ$29), MAX($BJ$7:$BJ$29), G20)), $BK$7:$BK$29, "Error", 0) | H21: =_xlfn.XLOOKUP(MIN(ABS($BJ$7:$BJ$29 - MEDIAN(MIN($BJ$7:$BJ$29), MAX($BJ$7:$BJ$29), H20))), ABS($BJ$7:$BJ$29 - MEDIAN(MIN($BJ$7:$BJ$29), MAX($BJ$7:$BJ$29), H20)), $BK$7:$BK$29, "Error", 0) | I21: =_xlfn.XLOOKUP(MIN(ABS($BJ$7:$BJ$29 - MEDIAN(MIN($BJ$7:$BJ$29), MAX($BJ$7:$BJ$29), I20))), ABS($BJ$7:$BJ$29 - MEDIAN(MIN($BJ$7:$BJ$29), MAX($BJ$7:$BJ$29), I20)), $BK$7:$BK$29, "Error", 0) | J21: =_xlfn.XLOOKUP(MIN(ABS($BJ$7:$BJ$29 - MEDIAN(MIN($BJ$7:$BJ$29), MAX($BJ$7:$BJ$29), J20))), ABS($BJ$7:$BJ$29 - MEDIAN(MIN($BJ$7:$BJ$29), MAX($BJ$7:$BJ$29), J20)), $BK$7:$BK$29, "Error", 0) | ... AX21: =_xlfn.XLOOKUP(MIN(ABS($BJ$7:$BJ$29 - MEDIAN(MIN($BJ$7:$BJ$29), MAX($BJ$7:$BJ$29), AX20))), ABS($BJ$7:$BJ$29 - MEDIAN(MIN($BJ$7:$BJ$29), MAX($BJ$7:$BJ$29), AX20)), $BK$7:$BK$29, "Error", 0) | BF21: {=_xlfn.XLOOKUP(MIN(ABS($BJ$7:$BJ$29 - MEDIAN(MIN($BJ$7:$BJ$29), MAX($BJ$7:$BJ$29), BD21))), ABS($BJ$7:$BJ$29 - MEDIAN(MIN($BJ$7:$BJ$29), MAX($BJ$7:$BJ$29), BD21)), $BK$7:$BK$29, "Error", 0)} | BJ21: -0.06 | BK21: -5 | BL21: -6
A22: USD CAD | B22: All time High (CL) | C22: 6233.9122 | D22: 6233.9122 | E22: 6233.9122 | F22: 6233.9122 | G22: 6233.9122 | H22: 6233.9122 | I22: 6233.9122 | J22: 6253.0549 | K22: 6253.0549 | L22: 6253.0549 | M22: 6372.9204 | N22: 6527.372 | O22: 6676.893 | P22: 6953.3418 | Q22: 7167.1458 | R22: 7167.1458 | S22: 7362.2855 | T22: 7616.9895 | U22: 7860.5438 | V22: 7860.5438 | W22: 7870.7298 | X22: 8197.16 | Y22: 8568.4569 | Z22: 8568.4569 | AA22: 8911.3543 | AB22: 8911.3543 | AC22: 8911.3543 | AD22: 8911.3543 | AE22: 8911.3543 | AF22: 8911.3543 | AG22: 8911.3543 | AH22: 9062.2543 | AI22: 9350.9887 | AJ22: 9743.077 | AK22: 9743.077 | AL22: 9743.077 | AM22: 9749.7642 | AN22: 9749.7642 | AO22: 9749.7642 | AP22: 10070.508 | AQ22: 10539.808 | AR22: 10858.106 | AS22: 10858.106 | AT22: 11005.523 | AU22: 11014.912 | AV22: 11014.912 | AW22: 11014.912 | AX22: 11014.912 | BC22: -0.073055774 | BD22: -0.073055774 | BF22: {=_xlfn.XLOOKUP(MIN(ABS($BJ$7:$BJ$29 - MEDIAN(MIN($BJ$7:$BJ$29), MAX($BJ$7:$BJ$29), BD22))), ABS($BJ$7:$BJ$29 - MEDIAN(MIN($BJ$7:$BJ$29), MAX($BJ$7:$BJ$29), BD22)), $BK$7:$BK$29, "Error", 0)} | BJ22: -0.08 | BK22: -7 | BL22: -8
B23: current price | C23: 5456.04 | D23: 5389.0812 | E23: 5556.568 | F23: 5691.3402 | G23: 5684.4434 | H23: 5896.7536 | I23: 6080.8306 | J23: 6101.2535 | K23: 5826.6023 | L23: 5799.4378 | M23: 6207.7313 | N23: 6325.2716 | O23: 6493.9948 | P23: 6919.4609 | Q23: 7113.8644 | R23: 6882.1264 | S23: 7221.3749 | T23: 7476.4891 | U23: 7648.1646 | V23: 7620.8212 | W23: 7784.4191 | X23: 7935.1401 | Y23: 8453.777 | Z23: 8440.0215 | AA23: 8754.5401 | AB23: 8600.3821 | AC23: 8030.0524 | AD23: 7700.2283 | AE23: 8122.0711 | AF23: 8489.2404 | AG23: 8764.3334 | AH23: 8877.6889 | AI23: 9307.7949 | AJ23: 9563.3525 | AK23: 9576.3977 | AL23: 9374.7069 | AM23: 9452.3465 | AN23: 9407.4189 | AO23: 9093.1186 | AP23: 9855.6538 | AQ23: 10458.967 | AR23: 10655.84 | AS23: 10493.996 | AT23: 10683.043 | AU23: 10949.957 | AV23: 10949.957 | AW23: 10949.957 | AX23: 10949.957 | BC23: -0.034900685 | BD23: -0.034900685 | BF23: {=_xlfn.XLOOKUP(MIN(ABS($BJ$7:$BJ$29 - MEDIAN(MIN($BJ$7:$BJ$29), MAX($BJ$7:$BJ$29), BD23))), ABS($BJ$7:$BJ$29 - MEDIAN(MIN($BJ$7:$BJ$29), MAX($BJ$7:$BJ$29), BD23)), $BK$7:$BK$29, "Error", 0)} | BJ23: -0.1 | BK23: -9 | BL23: -10
B24: % CHANGE | C24: =+(C23-C22)/C22 | D24: =+(D23-D22)/D22 | E24: =+(E23-E22)/E22 | F24: =+(F23-F22)/F22 | G24: =+(G23-G22)/G22 | H24: =+(H23-H22)/H22 | I24: =+(I23-I22)/I22 | J24: =+(J23-J22)/J22 | ... AX24: =+(AX23-AX22)/AX22 | BC24: -0.035583638 | BD24: -0.035583638 | BF24: {=_xlfn.XLOOKUP(MIN(ABS($BJ$7:$BJ$29 - MEDIAN(MIN($BJ$7:$BJ$29), MAX($BJ$7:$BJ$29), BD24))), ABS($BJ$7:$BJ$29 - MEDIAN(MIN($BJ$7:$BJ$29), MAX($BJ$7:$BJ$29), BD24)), $BK$7:$BK$29, "Error", 0)} | BJ24: -0.12 | BK24: -10 | BL24: -12
B25: All time High SPX | C25: 4808.9302 | D25: 4808.9302 | E25: 4808.9302 | F25: 4808.9302 | G25: 4808.9302 | H25: 4808.9302 | I25: 4808.9302 | J25: 4808.9302 | K25: 4808.9302 | L25: 4808.9302 | M25: 4808.9302 | N25: 4808.9302 | O25: 4931.0898 | P25: 5111.0601 | Q25: 5264.8501 | R25: 5264.8501 | S25: 5341.8799 | T25: 5523.6401 | U25: 5669.6699 | V25: 5669.6699 | W25: 5767.3701 | X25: 5767.3701 | Y25: 6044.1699 | Z25: 6044.1699 | AA25: 6128.1802 | AB25: 6128.1802 | AC25: 6128.1802 | AD25: 6128.1802 | AE25: 6128.1802 | AF25: 6215.0801 | AG25: 6427.02 | AH25: 6508.23 | AI25: 6699.52 | AJ25: 6920.3398 | AK25: 6920.3398 | AL25: 6945.77 | AM25: 7002.2798 | AN25: 7002.2798 | AO25: 7002.2798 | AP25: 7219.8301 | AQ25: 7599.3799 | AR25: 7599.3799 | AS25: 7599.3799 | AT25: 7816.7002 | AU25: 7816.7002 | AV25: 7816.7002 | AW25: 7816.7002 | AX25: 7816.7002 | BC25: -0.024024024 | BD25: -0.024024024 | BF25: {=_xlfn.XLOOKUP(MIN(ABS($BJ$7:$BJ$29 - MEDIAN(MIN($BJ$7:$BJ$29), MAX($BJ$7:$BJ$29), BD25))), ABS($BJ$7:$BJ$29 - MEDIAN(MIN($BJ$7:$BJ$29), MAX($BJ$7:$BJ$29), BD25)), $BK$7:$BK$29, "Error", 0)} | BJ25: -0.14 | BK25: -9 | BL25: -14
B26: current price SPX | C26: 4076.6001 | D26: 3970.1499 | E26: 4109.3101 | F26: 4169.48 | G26: 4179.8301 | H26: 4450.3799 | I26: 4588.96 | J26: 4507.6602 | K26: 4288.0498 | L26: 4193.7998 | M26: 4567.7998 | N26: 4769.8301 | O26: 4845.6499 | P26: 5096.27 | Q26: 5254.3501 | R26: 5035.6899 | S26: 5277.5098 | T26: 5460.48 | U26: 5522.2998 | V26: 5648.3999 | W26: 5762.48 | X26: 5705.4502 | Y26: 6032.3799 | Z26: 5881.6299 | AA26: 6040.5298 | AB26: 5954.5 | AC26: 5611.8501 | AD26: 5569.0601 | AE26: 5911.6899 | AF26: 6204.9502 | AG26: 6339.3901 | AH26: 6460.2598 | AI26: 6688.46 | AJ26: 6840.2002 | AK26: 6849.0898 | AL26: 6845.5 | AM26: 6939.0298 | AN26: 6878.8799 | AO26: 6528.52 | AP26: 7209.0098 | AQ26: 7580.0601 | AR26: 7499.3599 | AS26: 7489.7202 | AT26: 7686.1401 | AU26: 7743.4102 | AV26: 7743.4102 | AW26: 7743.4102 | AX26: 7743.4102 | BC26: -0.028825292 | BD26: -0.028825292 | BF26: {=_xlfn.XLOOKUP(MIN(ABS($BJ$7:$BJ$29 - MEDIAN(MIN($BJ$7:$BJ$29), MAX($BJ$7:$BJ$29), BD26))), ABS($BJ$7:$BJ$29 - MEDIAN(MIN($BJ$7:$BJ$29), MAX($BJ$7:$BJ$29), BD26)), $BK$7:$BK$29, "Error", 0)} | BJ26: -0.16 | BK26: -7 | BL26: -16
B27: original index % change | C27: =+(C26-C25)/C25 | D27: =+(D26-D25)/D25 | E27: =+(E26-E25)/E25 | F27: =+(F26-F25)/F25 | G27: =+(G26-G25)/G25 | H27: =+(H26-H25)/H25 | I27: =+(I26-I25)/I25 | J27: =+(J26-J25)/J25 | ... AX27: =+(AX26-AX25)/AX25 | BC27: -0.001261494 | BD27: -0.001261494 | BF27: {=_xlfn.XLOOKUP(MIN(ABS($BJ$7:$BJ$29 - MEDIAN(MIN($BJ$7:$BJ$29), MAX($BJ$7:$BJ$29), BD27))), ABS($BJ$7:$BJ$29 - MEDIAN(MIN($BJ$7:$BJ$29), MAX($BJ$7:$BJ$29), BD27)), $BK$7:$BK$29, "Error", 0)} | BJ27: -0.18 | BK27: -5 | BL27: -18
B28: real % change | C28: =+C24-C27 | D28: =+D24-D27 | E28: =+E24-E27 | F28: =+F24-F27 | G28: =+G24-G27 | H28: =+H24-H27 | I28: =+I24-I27 | J28: =+J24-J27 | ... AX28: =+AX24-AX27 | BC28: -0.014692634 | BD28: -0.014692634 | BF28: {=_xlfn.XLOOKUP(MIN(ABS($BJ$7:$BJ$29 - MEDIAN(MIN($BJ$7:$BJ$29), MAX($BJ$7:$BJ$29), BD28))), ABS($BJ$7:$BJ$29 - MEDIAN(MIN($BJ$7:$BJ$29), MAX($BJ$7:$BJ$29), BD28)), $BK$7:$BK$29, "Error", 0)} | BJ28: -0.2 | BK28: -3 | BL28: -20
B29: Rating | C29: =_xlfn.XLOOKUP(MIN(ABS($BJ$7:$BJ$29 - MEDIAN(MIN($BJ$7:$BJ$29), MAX($BJ$7:$BJ$29), C28))), ABS($BJ$7:$BJ$29 - MEDIAN(MIN($BJ$7:$BJ$29), MAX($BJ$7:$BJ$29), C28)), $BK$7:$BK$29, "Error", 0) | D29: =_xlfn.XLOOKUP(MIN(ABS($BJ$7:$BJ$29 - MEDIAN(MIN($BJ$7:$BJ$29), MAX($BJ$7:$BJ$29), D28))), ABS($BJ$7:$BJ$29 - MEDIAN(MIN($BJ$7:$BJ$29), MAX($BJ$7:$BJ$29), D28)), $BK$7:$BK$29, "Error", 0) | E29: =_xlfn.XLOOKUP(MIN(ABS($BJ$7:$BJ$29 - MEDIAN(MIN($BJ$7:$BJ$29), MAX($BJ$7:$BJ$29), E28))), ABS($BJ$7:$BJ$29 - MEDIAN(MIN($BJ$7:$BJ$29), MAX($BJ$7:$BJ$29), E28)), $BK$7:$BK$29, "Error", 0) | F29: =_xlfn.XLOOKUP(MIN(ABS($BJ$7:$BJ$29 - MEDIAN(MIN($BJ$7:$BJ$29), MAX($BJ$7:$BJ$29), F28))), ABS($BJ$7:$BJ$29 - MEDIAN(MIN($BJ$7:$BJ$29), MAX($BJ$7:$BJ$29), F28)), $BK$7:$BK$29, "Error", 0) | G29: =_xlfn.XLOOKUP(MIN(ABS($BJ$7:$BJ$29 - MEDIAN(MIN($BJ$7:$BJ$29), MAX($BJ$7:$BJ$29), G28))), ABS($BJ$7:$BJ$29 - MEDIAN(MIN($BJ$7:$BJ$29), MAX($BJ$7:$BJ$29), G28)), $BK$7:$BK$29, "Error", 0) | H29: =_xlfn.XLOOKUP(MIN(ABS($BJ$7:$BJ$29 - MEDIAN(MIN($BJ$7:$BJ$29), MAX($BJ$7:$BJ$29), H28))), ABS($BJ$7:$BJ$29 - MEDIAN(MIN($BJ$7:$BJ$29), MAX($BJ$7:$BJ$29), H28)), $BK$7:$BK$29, "Error", 0) | I29: =_xlfn.XLOOKUP(MIN(ABS($BJ$7:$BJ$29 - MEDIAN(MIN($BJ$7:$BJ$29), MAX($BJ$7:$BJ$29), I28))), ABS($BJ$7:$BJ$29 - MEDIAN(MIN($BJ$7:$BJ$29), MAX($BJ$7:$BJ$29), I28)), $BK$7:$BK$29, "Error", 0) | J29: =_xlfn.XLOOKUP(MIN(ABS($BJ$7:$BJ$29 - MEDIAN(MIN($BJ$7:$BJ$29), MAX($BJ$7:$BJ$29), J28))), ABS($BJ$7:$BJ$29 - MEDIAN(MIN($BJ$7:$BJ$29), MAX($BJ$7:$BJ$29), J28)), $BK$7:$BK$29, "Error", 0) | ... AX29: =_xlfn.XLOOKUP(MIN(ABS($BJ$7:$BJ$29 - MEDIAN(MIN($BJ$7:$BJ$29), MAX($BJ$7:$BJ$29), AX28))), ABS($BJ$7:$BJ$29 - MEDIAN(MIN($BJ$7:$BJ$29), MAX($BJ$7:$BJ$29), AX28)), $BK$7:$BK$29, "Error", 0) | BC29: -0.0032494954 | BD29: -0.0032494954 | BF29: {=_xlfn.XLOOKUP(MIN(ABS($BJ$7:$BJ$29 - MEDIAN(MIN($BJ$7:$BJ$29), MAX($BJ$7:$BJ$29), BD29))), ABS($BJ$7:$BJ$29 - MEDIAN(MIN($BJ$7:$BJ$29), MAX($BJ$7:$BJ$29), BD29)), $BK$7:$BK$29, "Error", 0)} | BJ29: -0.25 | BK29: -2 | BL29: -25
A30: EUR USD | B30: All time High (CL) | C30: 6509.3003 | D30: 6509.3003 | E30: 6509.3003 | F30: 6509.3003 | G30: 6509.3003 | H30: 6509.3003 | I30: 6509.3003 | J30: 6509.3003 | K30: 6509.3003 | L30: 6509.3003 | M30: 6509.3003 | N30: 6509.3003 | O30: 6509.3003 | P30: 6509.3003 | Q30: 6509.3003 | R30: 6509.3003 | S30: 6509.3003 | T30: 6509.3003 | U30: 6509.3003 | V30: 6509.3003 | W30: 6509.3003 | X30: 6509.3003 | Y30: 6509.3003 | Z30: 6509.3003 | AA30: 6509.3003 | AB30: 6509.3003 | AC30: 6509.3003 | AD30: 6509.3003 | AE30: 6509.3003 | AF30: 6509.3003 | AG30: 6509.3003 | AH30: 6509.3003 | AI30: 6565.6989 | AJ30: 6754.3163 | AK30: 6780.1769 | AL30: 6852.8458 | AM30: 7278.6822 | AN30: 7395.3932 | AO30: 7395.3932 | AP30: 7395.3932 | AQ30: 7395.3932 | AR30: 7395.3932 | AS30: 7418.5292 | AT30: 7703.4437 | AU30: 7703.4437 | AV30: 7703.4437 | AW30: 7703.4437 | AX30: 7703.4437 | BC30: -0.015306411 | BD30: -0.015306411 | BF30: {=_xlfn.XLOOKUP(MIN(ABS($BJ$7:$BJ$29 - MEDIAN(MIN($BJ$7:$BJ$29), MAX($BJ$7:$BJ$29), BD30))), ABS($BJ$7:$BJ$29 - MEDIAN(MIN($BJ$7:$BJ$29), MAX($BJ$7:$BJ$29), BD30)), $BK$7:$BK$29, "Error", 0)}
B31: current price | C31: 4517.6325 | D31: 4497.4318 | E31: 4705.4106 | F31: 4851.2242 | G31: 4527.2516 | H31: 4780.9439 | I31: 4929.2903 | J31: 4697.8355 | K31: 4419.9684 | L31: 4310.8933 | M31: 4809.1894 | N31: 4999.0601 | O31: 5040.4458 | P31: 5286.9253 | Q31: 5490.8403 | R31: 5273.4327 | S31: 5400.0109 | T31: 5247.1533 | U31: 5270.607 | V31: 5484.4913 | W31: 5585.4104 | X31: 5242.4094 | Y31: 5083.4833 | Z31: 5094.8312 | AA31: 5496.9065 | AB31: 5679.4143 | AC31: 5680.8135 | AD31: 5877.1103 | AE31: 6091.4754 | AF31: 6219.3503 | AG31: 6080.3254 | AH31: 6254.2126 | AI31: 6487.4412 | AJ31: 6552.3772 | AK31: 6573.3154 | AL31: 6803.3388 | AM31: 7051.3452 | AN31: 7245.1845 | AO31: 6382.9127 | AP31: 6872.3679 | AQ31: 7055.2009 | AR31: 7227.9721 | AS31: 7326.6689 | AT31: 7440.2993 | AU31: 7185.9764 | AV31: 7185.9764 | AW31: 7185.9764 | AX31: 7185.9764 | BC31: 0.006181345 | BD31: 0.006181345 | BF31: {=_xlfn.XLOOKUP(MIN(ABS($BJ$7:$BJ$29 - MEDIAN(MIN($BJ$7:$BJ$29), MAX($BJ$7:$BJ$29), BD31))), ABS($BJ$7:$BJ$29 - MEDIAN(MIN($BJ$7:$BJ$29), MAX($BJ$7:$BJ$29), BD31)), $BK$7:$BK$29, "Error", 0)}
B32: % CHANGE | C32: =+(C31-C30)/C30 | D32: =+(D31-D30)/D30 | E32: =+(E31-E30)/E30 | F32: =+(F31-F30)/F30 | G32: =+(G31-G30)/G30 | H32: =+(H31-H30)/H30 | I32: =+(I31-I30)/I30 | J32: =+(J31-J30)/J30 | ... AX32: =+(AX31-AX30)/AX30 | BC32: 0.0016082147 | BD32: 0.0016082147 | BF32: {=_xlfn.XLOOKUP(MIN(ABS($BJ$7:$BJ$29 - MEDIAN(MIN($BJ$7:$BJ$29), MAX($BJ$7:$BJ$29), BD32))), ABS($BJ$7:$BJ$29 - MEDIAN(MIN($BJ$7:$BJ$29), MAX($BJ$7:$BJ$29), BD32)), $BK$7:$BK$29, "Error", 0)}
B33: All time High STOXX50 | C33: 4522.2402 | D33: 4522.2402 | E33: 4522.2402 | F33: 4522.2402 | G33: 4522.2402 | H33: 4522.2402 | I33: 4522.2402 | J33: 4522.2402 | K33: 4522.2402 | L33: 4522.2402 | M33: 4522.2402 | N33: 4593.1099 | O33: 4674.7402 | P33: 4898.3701 | Q33: 5103.2598 | R33: 5103.2598 | S33: 5103.2598 | T33: 5103.2598 | U33: 5103.2598 | V33: 5103.2598 | W33: 5103.2598 | X33: 5103.2598 | Y33: 5103.2598 | Z33: 5103.2598 | AA33: 5314.29 | AB33: 5544.1201 | AC33: 5544.1201 | AD33: 5544.1201 | AE33: 5544.1201 | AF33: 5544.1201 | AG33: 5544.1201 | AH33: 5544.1201 | AI33: 5544.1201 | AJ33: 5734.2798 | AK33: 5818.0698 | AL33: 5818.0698 | AM33: 6053.6802 | AN33: 6199.7798 | AO33: 6199.7798 | AP33: 6199.7798 | AQ33: 6199.7798 | AR33: 6337.2202 | AS33: 6431.4199 | AT33: 6577.2002 | AU33: 6577.2002 | AV33: 6577.2002 | AW33: 6577.2002 | AX33: 6577.2002
B34: current price STOXX50 | C34: 4163.4502 | D34: 4238.3799 | E34: 4315.0498 | F34: 4359.3101 | G34: 4218.04 | H34: 4399.0898 | I34: 4471.3101 | J34: 4297.1099 | K34: 4174.6602 | L34: 4061.1201 | M34: 4382.4702 | N34: 4521.6499 | O34: 4648.3999 | P34: 4877.77 | Q34: 5083.4199 | R34: 4921.2202 | S34: 4983.6699 | T34: 4894.02 | U34: 4872.9399 | V34: 4957.98 | W34: 5000.4502 | X34: 4827.6299 | Y34: 4804.3999 | Z34: 4895.98 | AA34: 5286.8701 | AB34: 5463.54 | AC34: 5248.3901 | AD34: 5160.2202 | AE34: 5366.5898 | AF34: 5303.2402 | AG34: 5319.9199 | AH34: 5351.73 | AI34: 5529.96 | AJ34: 5662.04 | AK34: 5668.1699 | AL34: 5791.4102 | AM34: 5947.8101 | AN34: 6138.4102 | AO34: 5569.73 | AP34: 5881.5098 | AQ34: 6050.54 | AR34: 6328.0898 | AS34: 6358.0098 | AT34: 6420.1602 | AU34: 6302.8198 | AV34: 6302.8198 | AW34: 6302.8198 | AX34: 6302.8198
B35: original index % change | C35: =+(C34-C33)/C33 | D35: =+(D34-D33)/D33 | E35: =+(E34-E33)/E33 | F35: =+(F34-F33)/F33 | G35: =+(G34-G33)/G33 | H35: =+(H34-H33)/H33 | I35: =+(I34-I33)/I33 | J35: =+(J34-J33)/J33 | ... AX35: =+(AX34-AX33)/AX33
B36: real % change | C36: =+C32-C35 | D36: =+D32-D35 | E36: =+E32-E35 | F36: =+F32-F35 | G36: =+G32-G35 | H36: =+H32-H35 | I36: =+I32-I35 | J36: =+J32-J35 | ... AX36: =+AX32-AX35
B37: Rating | C37: =_xlfn.XLOOKUP(MIN(ABS($BJ$7:$BJ$29 - MEDIAN(MIN($BJ$7:$BJ$29), MAX($BJ$7:$BJ$29), C36))), ABS($BJ$7:$BJ$29 - MEDIAN(MIN($BJ$7:$BJ$29), MAX($BJ$7:$BJ$29), C36)), $BK$7:$BK$29, "Error", 0) | D37: =_xlfn.XLOOKUP(MIN(ABS($BJ$7:$BJ$29 - MEDIAN(MIN($BJ$7:$BJ$29), MAX($BJ$7:$BJ$29), D36))), ABS($BJ$7:$BJ$29 - MEDIAN(MIN($BJ$7:$BJ$29), MAX($BJ$7:$BJ$29), D36)), $BK$7:$BK$29, "Error", 0) | E37: =_xlfn.XLOOKUP(MIN(ABS($BJ$7:$BJ$29 - MEDIAN(MIN($BJ$7:$BJ$29), MAX($BJ$7:$BJ$29), E36))), ABS($BJ$7:$BJ$29 - MEDIAN(MIN($BJ$7:$BJ$29), MAX($BJ$7:$BJ$29), E36)), $BK$7:$BK$29, "Error", 0) | F37: =_xlfn.XLOOKUP(MIN(ABS($BJ$7:$BJ$29 - MEDIAN(MIN($BJ$7:$BJ$29), MAX($BJ$7:$BJ$29), F36))), ABS($BJ$7:$BJ$29 - MEDIAN(MIN($BJ$7:$BJ$29), MAX($BJ$7:$BJ$29), F36)), $BK$7:$BK$29, "Error", 0) | G37: =_xlfn.XLOOKUP(MIN(ABS($BJ$7:$BJ$29 - MEDIAN(MIN($BJ$7:$BJ$29), MAX($BJ$7:$BJ$29), G36))), ABS($BJ$7:$BJ$29 - MEDIAN(MIN($BJ$7:$BJ$29), MAX($BJ$7:$BJ$29), G36)), $BK$7:$BK$29, "Error", 0) | H37: =_xlfn.XLOOKUP(MIN(ABS($BJ$7:$BJ$29 - MEDIAN(MIN($BJ$7:$BJ$29), MAX($BJ$7:$BJ$29), H36))), ABS($BJ$7:$BJ$29 - MEDIAN(MIN($BJ$7:$BJ$29), MAX($BJ$7:$BJ$29), H36)), $BK$7:$BK$29, "Error", 0) | I37: =_xlfn.XLOOKUP(MIN(ABS($BJ$7:$BJ$29 - MEDIAN(MIN($BJ$7:$BJ$29), MAX($BJ$7:$BJ$29), I36))), ABS($BJ$7:$BJ$29 - MEDIAN(MIN($BJ$7:$BJ$29), MAX($BJ$7:$BJ$29), I36)), $BK$7:$BK$29, "Error", 0) | J37: =_xlfn.XLOOKUP(MIN(ABS($BJ$7:$BJ$29 - MEDIAN(MIN($BJ$7:$BJ$29), MAX($BJ$7:$BJ$29), J36))), ABS($BJ$7:$BJ$29 - MEDIAN(MIN($BJ$7:$BJ$29), MAX($BJ$7:$BJ$29), J36)), $BK$7:$BK$29, "Error", 0) | ... AX37: =_xlfn.XLOOKUP(MIN(ABS($BJ$7:$BJ$29 - MEDIAN(MIN($BJ$7:$BJ$29), MAX($BJ$7:$BJ$29), AX36))), ABS($BJ$7:$BJ$29 - MEDIAN(MIN($BJ$7:$BJ$29), MAX($BJ$7:$BJ$29), AX36)), $BK$7:$BK$29, "Error", 0)
A38: EUR JPY | B38: All time High (CL) | C38: 2.2881019e+08 | D38: 2.2881019e+08 | E38: 2.2881019e+08 | F38: 2.2881019e+08 | G38: 2.2881019e+08 | H38: 2.2881019e+08 | I38: 2.2881019e+08 | J38: 2.2881019e+08 | K38: 2.2881019e+08 | L38: 2.2881019e+08 | M38: 2.2881019e+08 | N38: 2.2881019e+08 | O38: 2.2881019e+08 | P38: 2.2881019e+08 | Q38: 2.2881019e+08 | R38: 2.2881019e+08 | S38: 2.2881019e+08 | T38: 2.2881019e+08 | U38: 2.2881019e+08 | V38: 2.2881019e+08 | W38: 2.2881019e+08 | X38: 2.2881019e+08 | Y38: 2.2881019e+08 | Z38: 2.2881019e+08 | AA38: 2.2881019e+08 | AB38: 2.2881019e+08 | AC38: 2.2881019e+08 | AD38: 2.2881019e+08 | AE38: 2.2881019e+08 | AF38: 2.2881019e+08 | AG38: 2.2881019e+08 | AH38: 2.2881019e+08 | AI38: 2.2881019e+08 | AJ38: 2.2881019e+08 | AK38: 2.2881019e+08 | AL38: 2.2881019e+08 | AM38: 2.2881019e+08 | AN38: 2.2881019e+08 | AO38: 2.2881019e+08 | AP38: 2.2881019e+08 | AQ38: 2.2881019e+08 | AR38: 2.2881019e+08 | AS38: 2.2881019e+08 | AT38: 2.2881019e+08 | AU38: 2.2881019e+08 | AV38: 2.2881019e+08 | AW38: 2.2881019e+08 | AX38: 2.2881019e+08
B39: current price | C39: 589415.48 | D39: 612907.85 | E39: 626722.14 | F39: 661198.43 | G39: 632756.59 | H39: 692188.02 | I39: 693804.24 | J39: 686110.93 | K39: 659846.77 | L39: 642720.97 | M39: 707080.9 | N39: 704967.49 | O39: 742726.01 | P39: 796276.46 | Q39: 830983.79 | R39: 823792.56 | S39: 847203.96 | T39: 844123.99 | U39: 804580.86 | V39: 801823.44 | W39: 797471.78 | X39: 803187.27 | Y39: 761372.47 | Z39: 799934.59 | AA39: 846993.6 | AB39: 851918.84 | AC39: 849913.82 | AD39: 836249.84 | AE39: 877115.46 | AF39: 898655.24 | AG39: 907259.11 | AH39: 919744.56 | AI39: 963971.52 | AJ39: 1008403.7 | AK39: 1026805.2 | AL39: 1063997.9 | AM39: 1090926.1 | AN39: 1129142.2 | AO39: 1019945.7 | AP39: 1100912.8 | AQ39: 1124589 | AR39: 1170070.1 | AS39: 1173561.5 | AT39: 1191305.7 | AU39: 1128942.2 | AV39: 1128942.2 | AW39: 1128942.2 | AX39: 1128942.2
B40: % CHANGE | C40: =+(C39-C38)/C38 | D40: =+(D39-D38)/D38 | E40: =+(E39-E38)/E38 | F40: =+(F39-F38)/F38 | G40: =+(G39-G38)/G38 | H40: =+(H39-H38)/H38 | I40: =+(I39-I38)/I38 | J40: =+(J39-J38)/J38 | ... AX40: =+(AX39-AX38)/AX38
B41: All time High STOXX50 | C41: 4522.2402 | D41: 4522.2402 | E41: 4522.2402 | F41: 4522.2402 | G41: 4522.2402 | H41: 4522.2402 | I41: 4522.2402 | J41: 4522.2402 | K41: 4522.2402 | L41: 4522.2402 | M41: 4522.2402 | N41: 4593.1099 | O41: 4674.7402 | P41: 4898.3701 | Q41: 5103.2598 | R41: 5103.2598 | S41: 5103.2598 | T41: 5103.2598 | U41: 5103.2598 | V41: 5103.2598 | W41: 5103.2598 | X41: 5103.2598 | Y41: 5103.2598 | Z41: 5103.2598 | AA41: 5314.29 | AB41: 5544.1201 | AC41: 5544.1201 | AD41: 5544.1201 | AE41: 5544.1201 | AF41: 5544.1201 | AG41: 5544.1201 | AH41: 5544.1201 | AI41: 5544.1201 | AJ41: 5734.2798 | AK41: 5818.0698 | AL41: 5818.0698 | AM41: 6053.6802 | AN41: 6199.7798 | AO41: 6199.7798 | AP41: 6199.7798 | AQ41: 6199.7798 | AR41: 6337.2202 | AS41: 6431.4199 | AT41: 6577.2002 | AU41: 6577.2002 | AV41: 6577.2002 | AW41: 6577.2002 | AX41: 6577.2002
B42: current price STOXX50 | C42: 4163.4502 | D42: 4238.3799 | E42: 4315.0498 | F42: 4359.3101 | G42: 4218.04 | H42: 4399.0898 | I42: 4471.3101 | J42: 4297.1099 | K42: 4174.6602 | L42: 4061.1201 | M42: 4382.4702 | N42: 4521.6499 | O42: 4648.3999 | P42: 4877.77 | Q42: 5083.4199 | R42: 4921.2202 | S42: 4983.6699 | T42: 4894.02 | U42: 4872.9399 | V42: 4957.98 | W42: 5000.4502 | X42: 4827.6299 | Y42: 4804.3999 | Z42: 4895.98 | AA42: 5286.8701 | AB42: 5463.54 | AC42: 5248.3901 | AD42: 5160.2202 | AE42: 5366.5898 | AF42: 5303.2402 | AG42: 5319.9199 | AH42: 5351.73 | AI42: 5529.96 | AJ42: 5662.04 | AK42: 5668.1699 | AL42: 5791.4102 | AM42: 5947.8101 | AN42: 6138.4102 | AO42: 5569.73 | AP42: 5881.5098 | AQ42: 6050.54 | AR42: 6328.0898 | AS42: 6358.0098 | AT42: 6420.1602 | AU42: 6302.8198 | AV42: 6302.8198 | AW42: 6302.8198 | AX42: 6302.8198
B43: original index % change | C43: =+(C42-C41)/C41 | D43: =+(D42-D41)/D41 | E43: =+(E42-E41)/E41 | F43: =+(F42-F41)/F41 | G43: =+(G42-G41)/G41 | H43: =+(H42-H41)/H41 | I43: =+(I42-I41)/I41 | J43: =+(J42-J41)/J41 | ... AX43: =+(AX42-AX41)/AX41
B44: real % change | C44: =+C40-C43 | D44: =+D40-D43 | E44: =+E40-E43 | F44: =+F40-F43 | G44: =+G40-G43 | H44: =+H40-H43 | I44: =+I40-I43 | J44: =+J40-J43 | ... AX44: =+AX40-AX43
